Workbook

Sheet Leads
A1: ID | B1: Prioridade | C1: Pontuação | D1: Estado | E1: Responsável | F1: Ângulo | G1: Distrito | H1: Concelho | I1: Localidade | J1: Escola | K1: Grupo | L1: Contacto | M1: Cargo | N1: Telefone | O1: Telemóvel | P1: WhatsApp | Q1: Email | R1: Website | S1: Facebook | T1: Instagram | U1: Google ★ | V1: Google n.º | W1: Software atual | X1: Marcação de aulas | Y1: Sábado | Z1: Horário | AA1: Exames 2021 | AB1: Categorias | AC1: Sinais de dor | AD1: Motivo prioridade | AE1: Próxima ação | AF1: Data próxima ação | AG1: Último contacto | AH1: Passo seq | AI1: Próximo envio | AJ1: Motivo perda | AK1: Notas | AL1: Link WhatsApp | AM1: Software evidência | AN1: Morada | AO1: Fontes | AP1: Thread ID
A2: 1 | B2: A | C2: 10.5 | D2: Novo | E2: Pedro | F2: grupo | G2: Leiria | H2: Caldas da Rainha | I2: Caldas da Rainha | J2: Escola de Condução Bordalo Pinheiro | K2: Bordalo (grupo, segundo bomcondutor) | N2: 262 880 399 | O2: 916 267 390 | S2: https://www.facebook.com/pages/Escola-de-condução-Bordalo-Pinheiro/127727473957013 | U2: 2.4 | V2: 18 | X2: Telefone/presencial; reviews indicam falta de aviso de cancelamentos | AA2: 1132 | AC2: "Falta de organização, desmarcam aulas sem telefonar... já é a quinta aula que não ligam a avisar de cancelamento" (Google 1★, 03/2023) https://escola-de-conducao.pt/escola-de-conducao-bordalo-pinheiro-306171.html; "Não me mandavam mensagem para cancelamento de aulas" (Google 2★, 07/2023) https://escola-de-conducao.pt/escola-de-conducao-bordalo-pinheiro-306171.html; "falta de organização enorme" (Google 1★, 12/2022) https://escola-de-conducao.pt/escola-de-conducao-bordalo-pinheiro-306171.html | AD2: MELHOR LEAD: maior volume do distrito (1132 exames 2021) + dor exatamente no problema da Convlyx (cancelamentos sem aviso, desorganização) | AH2: 0 | AL2: =IF(IF(O2<>"",O2,IF(LEFT(TRIM(N2),1)="9",N2,""))="","",HYPERLINK("https://wa.me/351"&LEFT(SUBSTITUTE(SUBSTITUTE(SUBSTITUTE(IF(O2<>"",O2,IF(LEFT(TRIM(N2),1)="9",N2,""))," ",""),"+351",""),"-",""),9),"Abrir WhatsApp")) -> Abrir WhatsApp | AN2: Rua Dr. Ângelo Ferrari, 5 R/c Dto - 2500-113 Caldas da Rainha | AO2: https://passaprimeira.xyz/distritos-regioes/leiria/concelhos/caldas-da-rainha/escolas/bordalo-pinheiro-00913/; https://escola-de-conducao.pt/escola-de-conducao-bordalo-pinheiro-306171.html; https://www.bomcondutor.pt/escolas/escola/bordalo-pinheiro; https://www.andardemoto.pt/escolas-de-conducao/dir/d/leiria/c/caldas-da-rainha/p-2199/bordalo-pinheiro/
A3: 2 | B3: A | C3: 10.4 | D3: Novo | E3: Pedro | F3: grupo | G3: Leiria | H3: Caldas da Rainha | I3: Caldas da Rainha | J3: Escola de Condução Caldas (EC Caldas) | K3: Provável grupo EC Caldas (Nova Rainha, Cardal-Pombal; review refere escola em Quinta do Conde) - bomcondutor: "Segurança Activa" | N3: 262 877 371 | O3: 919 796 968 | R3: http://www.eccaldas.pt/ | S3: https://www.facebook.com/ECCALDAS | U3: 3 | V3: 83 | W3: Área do Aluno própria (login Joomla no site) | X3: Telefone/presencial; área do aluno web legada | Y3: Sim | Z3: Secretaria 2ª-6ª 10h-12h30 / 14h-20h; Sábado 9h-13h (ABERTO sábado); aulas teóricas sáb 10h, 11h, 12h | AA3: 729 | AB3: A, B (motociclos e ligeiros) | AC3: "Falta de organização, falta de informação, prazos longos" (Google 1★, 03/2024) https://escola-de-conducao.pt/escola-de-conducao-caldas-306021.html; "escola da Quinta do conde muito má super falta de organização alunos com muito tempo de espera fazer aulas" (Google 1★, 04/2022) https://escola-de-conducao.pt/escola-de-conducao-caldas-306021.html; muitas queixas sobre trato dos instrutores | AD3: Volume alto (729 exames 2021), provável grupo multi-escola, dor em organização/esperas; área do aluno muito antiga | AH3: 0 | AL3: =IF(IF(O3<>"",O3,IF(LEFT(TRIM(N3),1)="9",N3,""))="","",HYPERLINK("https://wa.me/351"&LEFT(SUBSTITUTE(SUBSTITUTE(SUBSTITUTE(IF(O3<>"",O3,IF(LEFT(TRIM(N3),1)="9",N3,""))," ",""),"+351",""),"-",""),9),"Abrir WhatsApp")) -> Abrir WhatsApp | AM3: http://www.eccaldas.pt/index.php/alunos - "Entrar na Área do Aluno" (Utilizador/Senha), site Joomla de 2012 | AN3: Av. Eng. Luís Paiva e Sousa, 22-B - 2500-329 Caldas da Rainha | AO3: https://passaprimeira.xyz/distritos-regioes/leiria/concelhos/caldas-da-rainha/escolas/caldas-01297/; http://www.eccaldas.pt/index.php/contactos; http://www.eccaldas.pt/index.php/horarios; https://escola-de-conducao.pt/escola-de-conducao-caldas-306021.html; https://www.bomcondutor.pt/escolas/escola/caldas
A4: 3 | B4: A | C4: 10.3 | D4: Novo | E4: Pedro | F4: grupo | G4: Lisboa | H4: Alenquer | I4: Alenquer | J4: Escola de Condução de Alenquer (Segurança Máxima; ex-Ideal de Alenquer) | K4: Segurança Máxima (~70 escolas: Grande Lisboa, Setúbal, Madeira) | N4: 263 711 912 | O4: 963 904 022 | Q4: alenquer@segurancamaxima.pt | R4: https://www.segurancamaxima.pt/escolas-de-conducao/escola-de-conducao-de-alenquer/ | S4: https://www.facebook.com/grupo.seguranca.maxima | T4: https://www.instagram.com/seguranca.maxima/ | U4: 3.7 | V4: 53 | W4: Softdrive (gestão/horários) + e-learning do grupo | X4: Secretaria/telefone; reviews dizem que se marca 'quando tem disponibilidade e não o aluno' | Y4: Sim | Z4: Secretaria dias úteis 09h-20h, Sábado 09h-13h; aulas de condução dias úteis 07h-20h50, Sábado 09h-13h (ABERTO sábado de manhã) | AA4: 691 | AB4: AM, A1, A2, A, B, B1, B+E, C, C1, C+E, D, D1, D+E | AC4: 'para marcar aulas é quando tem disponibilidade e não o aluno' (Google, 2022); 'a quase 90 dias a espera de vaga para fazer minha primeira aula prática e ainda a secretária disse que aulas podem ser cancelada' (Google, 2021); 'Atendimento demorado e ineficaz pelo telemóvel' (Google, 2023) - https://escola-de-conducao.pt/escola-de-conducao-seguranca-maxima-de-alenquer-lda-306155.html; Queixa 2019: aluno do Carregado com aulas em Alenquer e informação errada sobre a hora do exame - https://portaldaqueixa.com/brands/seguranca-maxima-escolas-de-conducao/complaints/seguranca-maxima-escolas-de-conducao-marcacao-de-exame-de-mecanica-para-categoria-c-27254919 | AD4: Muita evidência de dor (marcação, esperas, cancelamentos) e maior volume da zona (691). Atenção: grande grupo com decisão centralizada em Lisboa e já usa Softdrive | AH4: 0 | AL4: =IF(IF(O4<>"",O4,IF(LEFT(TRIM(N4),1)="9",N4,""))="","",HYPERLINK("https://wa.me/351"&LEFT(SUBSTITUTE(SUBSTITUTE(SUBSTITUTE(IF(O4<>"",O4,IF(LEFT(TRIM(N4),1)="9",N4,""))," ",""),"+351",""),"-",""),9),"Abrir WhatsApp")) -> Abrir WhatsApp | AM4: A página da escola liga a https://softdrive.me/#/horario/154 (horários; 154 = n.º IMT da escola) e ao e-learning https://ensinoadistancia.segurancarodoviaria.pt | AN4: Avenida dos Bombeiros Voluntários, nº 65 - 1º, 2580-289 Alenquer | AO4: https://www.segurancamaxima.pt/escolas-de-conducao/escola-de-conducao-de-alenquer/; https://escola-de-conducao.pt/escola-de-conducao-seguranca-maxima-de-alenquer-lda-306155.html; https://passaprimeira.xyz/distritos-regioes/lisboa/concelhos/alenquer/escolas/; https://www.imt-ip.pt/wp-content/uploads/2025/01/EscolasdeConducao-2021.pdf
A5: 4 | B5: A | C5: 10.1 | D5: Novo | E5: Pedro | F5: grupo | G5: Lisboa | H5: Alenquer | I5: Carregado | J5: Escola de Condução do Carregado (Segurança Máxima) | K5: Segurança Máxima (~70 escolas) | N5: 263 098 404 | O5: 918 210 710 | Q5: carregado@segurancamaxima.pt | R5: https://www.segurancamaxima.pt/escolas-de-conducao/escola-de-conducao-do-carregado/ | S5: https://www.facebook.com/grupo.seguranca.maxima | T5: https://www.instagram.com/seguranca.maxima/ | U5: 3.2 | V5: 33 | W5: Softdrive (gestão/horários) + e-learning do grupo | X5: Secretaria/telefone; reviews relatam meses sem conseguir marcar aulas práticas | Y5: Sim | Z5: Secretaria dias úteis 09h-20h, Sábado 09h-13h; aulas de condução Sábado 07h-13h (ABERTO sábado de manhã) | AA5: 646 | AB5: AM, A1, A2, A, B, B1, B+E, C, C1, C+E, D, D1, D+E | AC5: 'estou a 3 meses tentando marcar minhas aulas de condução e a resposta é sempre a mesma, “esse mês está cheio”' (Google, 2022); 'muito desorganizada e não tem professores que sejam suficiente para atender o número grande de alunos' (Google, 2022); 'Não atendem os telefones, nem email' (Google, 2021) - https://escola-de-conducao.pt/escola-de-conducao-maxima-carregado-306104.html; Queixa 2025: informação errada da secretaria sobre licença de aprendizagem - https://portaldaqueixa.com/brands/seguranca-maxima-escolas-de-conducao/complaints/seguranca-maxima-escolas-de-conducao-a-escola-seguranca-maxima-do-carregado-engana-os-alunos-para-ganhar-dinheiro-e-age-de-formas-ilegais-139435325 | AD5: Dor forte e recorrente em marcação de aulas/comunicação + volume alto (646); grupo grande já com Softdrive (decisão em Lisboa) | AH5: 0 | AL5: =IF(IF(O5<>"",O5,IF(LEFT(TRIM(N5),1)="9",N5,""))="","",HYPERLINK("https://wa.me/351"&LEFT(SUBSTITUTE(SUBSTITUTE(SUBSTITUTE(IF(O5<>"",O5,IF(LEFT(TRIM(N5),1)="9",N5,""))," ",""),"+351",""),"-",""),9),"Abrir WhatsApp")) -> Abrir WhatsApp | AM5: A página da escola liga a https://softdrive.me/#/horario/832 (horários; 832 = n.º IMT) e ao e-learning https://ensinoadistancia.segurancarodoviaria.pt | AN5: Rua Vaz Monteiro, Lote 33 R/C (Loja D), 2580-505 Carregado | AO5: https://www.segurancamaxima.pt/escolas-de-conducao/escola-de-conducao-do-carregado/; https://escola-de-conducao.pt/escola-de-conducao-maxima-carregado-306104.html; https://www.imt-ip.pt/wp-content/uploads/2025/01/EscolasdeConducao-2021.pdf; https://passaprimeira.xyz/distritos-regioes/lisboa/concelhos/alenquer/escolas/
A6: 5 | B6: A | C6: 9.5 | D6: Novo | E6: Pedro | F6: grupo | G6: Coimbra | H6: Coimbra | I6: Coimbra (Santa Clara) | J6: Escola de Condução Santa Clara | K6: Grupo MGA (Escolas MGA, desde 1971) - 5 escolas no distrito | N6: 239 404 497 | O6: 961 448 305 | Q6: geral@escolasmga.pt | R6: https://escolasmga.pt/escolas-de-conducao/coimbra-santa-clara/ | S6: https://www.facebook.com/escolasgrupomga | U6: 3.7 | V6: 27 | W6: BDrive | X6: Secretaria/telefone; BDrive para alunos registados (funcionalidades não detalhadas no site) | Y6: Não | Z6: Seg-Sex 09:00-12:00 / 14:00-19:00; Sábado encerrado (segundo listagem Google) | AA6: 979 | AB6: A, A1, A2, B1, B, B automático, BE, C, C1, CE, D, D1, DE, T, veículos adaptados; CAM | AC6: 'Têm um plano mensal de aulas presenciais marcado, pois chega-se a hora da aula, não aparece ninguém para dar aula' (https://escola-de-conducao.pt/escola-de-conducao-santa-clara-grupo-mga-desde-1971-305927.html); 'O plano de aulas teóricas previamente afixado não é cumprido!' (mesma fonte) | AD6: Grupo multi-escola (5 sites MGA no distrito), maior volume do grupo (979 provas 2021), queixas de aulas não cumpridas/comunicação; usa BDrive mas sem app próprio de marcação | AH6: 0 | AL6: =IF(IF(O6<>"",O6,IF(LEFT(TRIM(N6),1)="9",N6,""))="","",HYPERLINK("https://wa.me/351"&LEFT(SUBSTITUTE(SUBSTITUTE(SUBSTITUTE(IF(O6<>"",O6,IF(LEFT(TRIM(N6),1)="9",N6,""))," ",""),"+351",""),"-",""),9),"Abrir WhatsApp")) -> Abrir WhatsApp | AM6: https://escolasmga.pt/servicos/plataforma-bdrive/ (link para bdrive.pt, 'Acesso exclusivo a instruendos registados'); também 'Plataforma de Testes' e 'Pré-inscrição Online' | AN6: Rua Dr. Paulo Quintela, 23, 3030-393 Coimbra | AO6: https://escolasmga.pt/escolas-de-conducao/; https://escola-de-conducao.pt/escola-de-conducao-santa-clara-grupo-mga-desde-1971-305927.html; https://www.bomcondutor.pt/escolas/escola/santa-clara; https://www.andardemoto.pt/escolas-de-conducao/dir/d/coimbra/c/coimbra/p-2532/escola-de-conducao-santa-clara/; https://www.imt-ip.pt/wp-content/uploads/2025/01/EscolasdeConducao-2021.pdf
A7: 6 | B7: A | C7: 8.8 | D7: Novo | E7: Pedro | F7: grupo | G7: Santarém | H7: Santarém | I7: Santarém | J7: Escola de Condução Scallabis | K7: Grupo Caldas (11 escolas: Caldas, Louzan, Lizauto, Cardal, Via Maior, Capas Negras, Supertubos, Fica, Nova Setúbal, Scallabis, Nova Viseu) | O7: 910 403 321 | P7: yes | Q7: scallabis@grupocaldas.pt | R7: https://grupocaldas.pt/site/ecscallabis/ | S7: https://www.facebook.com/scallabis/ ; https://www.facebook.com/GrupoCaldasEC | T7: https://www.instagram.com/grupocaldas/ | U7: 2.6 | V7: 32 | X7: Telefone/WhatsApp e presencial (secretaria); calendário de teóricas em PDF | Y7: Sim | Z7: Secretaria: Seg-Sex 10:00-12:30 e 14:00-20:00; Sábado 09:00-13:00 (ABERTO SÁBADO) | AA7: 462 | AB7: A1, A2, A, B | AC7: 'A dificuldade que se tem para marcar (porque desmarcam 70% das vezes e sem avisar)' — https://escola-de-conducao.pt/escola-de-conducao-scallabis-306353.html; 'Tinha aulas de condução de 15 em 15 dias... cerca de 2 anos para concluir a carta' — idem; 'A escola não dá resposta aos pedidos de aulas de condução, o contacto telefónico... não teve qualquer resposta' — idem; 'Staff insuficiente' — idem; 'Nem sequer dão as aulas aos alunos! ... não conseguem marcar as aulas de condução' (Portal da Queixa, set 2023; índice de satisfação 13.9/100) — https://portaldaqueixa.com/brands/escola-de-conducao-scallabis | AD7: Grupo multi-escola (11 escolas, Grupo Caldas) + fortes queixas sobre marcação/desmarcação de aulas e falta de resposta; sem app próprio. Decisão provavelmente na sede (Caldas da Rainha, 262 877 371, info@eccaldas.pt) | AH7: 0 | AL7: =IF(IF(O7<>"",O7,IF(LEFT(TRIM(N7),1)="9",N7,""))="","",HYPERLINK("https://wa.me/351"&LEFT(SUBSTITUTE(SUBSTITUTE(SUBSTITUTE(IF(O7<>"",O7,IF(LEFT(TRIM(N7),1)="9",N7,""))," ",""),"+351",""),"-",""),9),"Abrir WhatsApp")) -> Abrir WhatsApp | AM7: Site do grupo só tem formulário de pré-inscrição, botão WhatsApp e PDF mensal 'Calendário de Aulas Teóricas' — sem área do aluno nem app | AN7: Av. Madre Andaluz 2A, 2000-210 Santarém | AO7: https://grupocaldas.pt/site/ecscallabis/; https://grupocaldas.pt/site/contactos/; https://escola-de-conducao.pt/escola-de-conducao-scallabis-306353.html; https://portaldaqueixa.com/brands/escola-de-conducao-scallabis; https://www.imt-ip.pt/wp-content/uploads/2025/01/EscolasdeConducao-2021.pdf
A8: 7 | B8: A | C8: 8.3 | D8: Novo | E8: Pedro | F8: grupo | G8: Leiria | H8: Batalha | I8: Golpilheira (Mouratos) | J8: Escola de Condução Batalhense - Batalha (sede) | K8: Grupo Batalhense | N8: 244 767 043 | O8: 917 073 335 | Q8: batalha@batalhense.com | R8: https://batalhense.com/escolas/escola-de-conducao-batalhense-batalha/ | S8: https://www.facebook.com/grupobatalhense | T8: https://www.instagram.com/batalhensegrupo/ | U8: 4.1 | V8: 23 | X8: Telefone/secretaria presencial; formulário de inscrição no site | Y8: Sim | Z8: Secretaria 2ª-6ª 9h30-12h30 / 14h30-20h; Sábado 9h30-12h30 (ABERTO sábado) | AA8: 445 | AB8: A, B, C, D; CAM, TCC, curso de instrutores, carta inclusiva (veículo adaptado) | AC8: "Instrutora com muita amargura, pouco interesse, constantemente tarde para às aulas" (Google 1★, 01/2024) https://escola-de-conducao.pt/escola-de-conducao-batalhense-306367.html | AD8: SEDE do Grupo Batalhense (6 escolas, desde 1996, contacto geral 244 767 043) - decisor provável aqui; 445 exames 2021 | AH8: 0 | AL8: =IF(IF(O8<>"",O8,IF(LEFT(TRIM(N8),1)="9",N8,""))="","",HYPERLINK("https://wa.me/351"&LEFT(SUBSTITUTE(SUBSTITUTE(SUBSTITUTE(IF(O8<>"",O8,IF(LEFT(TRIM(N8),1)="9",N8,""))," ",""),"+351",""),"-",""),9),"Abrir WhatsApp")) -> Abrir WhatsApp | AM8: Sem área do aluno/app no site batalhense.com; só formulário de inscrição (contacto). Aulas de código online de apoio (3ª e 5ª). | AN8: R. Comendador Joaquim Sales, Mouratos, 42 - 2440-042 Batalha | AO8: https://passaprimeira.xyz/distritos-regioes/leiria/concelhos/batalha/escolas/batalhense-00588/; https://batalhense.com/; https://batalhense.com/escolas/escola-de-conducao-batalhense-batalha/; https://escola-de-conducao.pt/escola-de-conducao-batalhense-306367.html
A9: 8 | B9: A | C9: 8 | D9: Novo | E9: Pedro | F9: grupo | G9: Leiria | H9: Pombal | I9: Pombal | J9: Clube do Condutor (Escolas de Condução Esteves - Pombal) | K9: Escolas de Condução Esteves | N9: 236 023 907 | O9: 916 844 922 | Q9: clubedocondutor@gmail.com | R9: https://ec-esteves.pt/ | S9: https://www.facebook.com/escolaesteves | U9: 2.5 | V9: 2 | X9: Telefone/secretaria | Y9: Sim | Z9: Secretaria dias úteis 10h-12h / 14h30-19h30; Sábado 10h-12h (ABERTO sábado); aulas de condução sáb 8h-13h | AA9: 128 | AC9: "Não achei a professora prestativa em querer ensinar o aluno acabei desistindo" (Google 1★, 2022) https://escola-de-conducao.pt/escola-de-conducao-clube-do-condutor-306908.html | AD9: Grupo Esteves (3 escolas); 128 exames 2021 | AH9: 0 | AL9: =IF(IF(O9<>"",O9,IF(LEFT(TRIM(N9),1)="9",N9,""))="","",HYPERLINK("https://wa.me/351"&LEFT(SUBSTITUTE(SUBSTITUTE(SUBSTITUTE(IF(O9<>"",O9,IF(LEFT(TRIM(N9),1)="9",N9,""))," ",""),"+351",""),"-",""),9),"Abrir WhatsApp")) -> Abrir WhatsApp | AN9: R. Albergaria dos Doze, 55/57 - 3100-456 Pombal | AO9: https://passaprimeira.xyz/distritos-regioes/leiria/concelhos/pombal/escolas/clube-do-condutor-01370/; https://ec-esteves.pt/contactos/; https://ec-esteves.pt/horarios/; https://escola-de-conducao.pt/escola-de-conducao-clube-do-condutor-306908.html
A10: 9 | B10: A | C10: 7.8 | D10: Novo | E10: Pedro | F10: grupo | G10: Leiria | H10: Pombal | I10: Pombal | J10: Escola de Condução Batalhense - Pombal (Triangular) | K10: Grupo Batalhense | N10: 236 218 033 | O10: 919 868 022 | Q10: triangular@batalhense.com | R10: https://batalhense.com/escolas/escola-de-conducao-batalhense-pombal-triangular/ | S10: https://www.facebook.com/grupobatalhense | T10: https://www.instagram.com/batalhensegrupo/ | U10: 4.2 | V10: 10 | X10: Telefone/secretaria presencial; formulário de inscrição no site | Y10: Sim | Z10: Secretaria 2ª-6ª 9h30-12h30 / 14h30-19h30; Sábado 9h30-12h30 (ABERTO sábado) | AA10: 314 | AB10: A, B, C, D (grupo) | AC10: "Minha experiência no atendimento não foi dos melhores... não foi passado a informação que desejava" (Google 1★, 01/2023) https://escola-de-conducao.pt/escola-de-conducao-automovel-triangular-lda-306649.html | AD10: Grupo Batalhense + queixas de atendimento; 314 exames 2021 | AH10: 0 | AL10: =IF(IF(O10<>"",O10,IF(LEFT(TRIM(N10),1)="9",N10,""))="","",HYPERLINK("https://wa.me/351"&LEFT(SUBSTITUTE(SUBSTITUTE(SUBSTITUTE(IF(O10<>"",O10,IF(LEFT(TRIM(N10),1)="9",N10,""))," ",""),"+351",""),"-",""),9),"Abrir WhatsApp")) -> Abrir WhatsApp | AM10: Sem área do aluno/app no site batalhense.com; só formulário de inscrição (contacto). Aulas de código online de apoio (3ª e 5ª). | AN10: Av. Arquitecto Rosado Correia 3 - 3100-430 Pombal | AO10: https://passaprimeira.xyz/distritos-regioes/leiria/concelhos/pombal/escolas/triangular-00537/; https://batalhense.com/; https://batalhense.com/escolas/escola-de-conducao-batalhense-pombal-triangular/; https://escola-de-conducao.pt/escola-de-conducao-automovel-triangular-lda-306649.html
A11: 10 | B11: A | C11: 7.8 | D11: Novo | E11: Pedro | F11: grupo | G11: Leiria | H11: Figueiró dos Vinhos | I11: Figueiró dos Vinhos | J11: Escola de Condução Lago Azul - Figueiró dos Vinhos | K11: Lago Azul (grupo, segundo bomcondutor) | N11: 236 551 611 | S11: https://www.facebook.com/ECLagoAzul | U11: 3.3 | V11: 3 | AA11: 86 | AC11: "eu tinha de pedir se faz favor para me ajudar e explicar melhor!! fiquei traumatizado com esta escola" (Google 1★, 03/2024) https://escola-de-conducao.pt/escola-de-conducao-lago-azul-lda-307080.html | AD11: Delegação de grupo (Lago Azul) + queixa recente; volume baixo (86 exames 2021) | AH11: 0 | AL11: =IF(IF(O11<>"",O11,IF(LEFT(TRIM(N11),1)="9",N11,""))="","",HYPERLINK("https://wa.me/351"&LEFT(SUBSTITUTE(SUBSTITUTE(SUBSTITUTE(IF(O11<>"",O11,IF(LEFT(TRIM(N11),1)="9",N11,""))," ",""),"+351",""),"-",""),9),"Abrir WhatsApp")) | AN11: Av. Dr. Francisco Sá Carneiro - 3260-400 Figueiró dos Vinhos | AO11: https://passaprimeira.xyz/distritos-regioes/leiria/concelhos/figueiro-dos-vinhos/escolas/lago-azul-figueiro-dos-vinhos-00491/; https://escola-de-conducao.pt/escola-de-conducao-lago-azul-lda-307080.html; https://www.bomcondutor.pt/escolas/escola/lago-azul-figueiro-dos-vinhos
A12: 11 | B12: A | C12: 7.6 | D12: Novo | E12: Pedro | F12: grupo | G12: Leiria | H12: Leiria | I12: Leiria (Nova Leiria) | J12: Escola de Condução Batalhense - Leiria (Nova Leiria) | K12: Grupo Batalhense | N12: 244 802 890 | O12: 918 782 380 | Q12: leiria@batalhense.com | R12: https://batalhense.com/escolas/escola-de-conducao-batalhense-leiria-nova-leiria/ | S12: https://www.facebook.com/grupobatalhense | T12: https://www.instagram.com/batalhensegrupo/ | U12: 4.4 | V12: 19 | X12: Telefone/secretaria presencial; formulário de inscrição no site | Y12: Sim | Z12: Secretaria 2ª-6ª 9h30-12h30 / 14h30-19h30; Sábado 10h-12h30 (ABERTO sábado de manhã) | AA12: 535 | AB12: A, B, C, D (grupo); CAM, TCC, curso de instrutores | AC12: "A escola nada responde e pelos vistos pouco se importa" (Google, 1★, 2022) https://escola-de-conducao.pt/escola-de-conducao-batalhense-de-leiria-306236.html | AD12: Grupo multi-escola (6 escolas no distrito: Leiria x2, Batalha, Marinha Grande, Alcobaça, Pombal); maior volume do grupo (535 exames 2021); sem app de aluno | AH12: 0 | AL12: =IF(IF(O12<>"",O12,IF(LEFT(TRIM(N12),1)="9",N12,""))="","",HYPERLINK("https://wa.me/351"&LEFT(SUBSTITUTE(SUBSTITUTE(SUBSTITUTE(IF(O12<>"",O12,IF(LEFT(TRIM(N12),1)="9",N12,""))," ",""),"+351",""),"-",""),9),"Abrir WhatsApp")) -> Abrir WhatsApp | AM12: Sem área do aluno/app no site batalhense.com; só formulário de inscrição (contacto). Aulas de código online de apoio (3ª e 5ª). | AN12: Av. Doutor Adelino Amaro da Costa, 2 - 2415-367 Leiria | AO12: https://passaprimeira.xyz/distritos-regioes/leiria/concelhos/leiria/escolas/batalhense-de-leiria-00872/; https://batalhense.com/; https://batalhense.com/escolas/escola-de-conducao-batalhense-leiria-nova-leiria/; https://escola-de-conducao.pt/escola-de-conducao-batalhense-de-leiria-306236.html; https://www.andardemoto.pt/escolas-de-conducao/dir/d/leiria/c/leiria/p-2191/batalhense-de-leiria/
A13: 12 | B13: A | C13: 7.5 | D13: Novo | E13: Pedro | F13: grupo | G13: Aveiro | H13: Aveiro | I13: Aveiro (centro) | J13: Escola de Condução Nova de Aveiro (Bordalo Pinheiro) | K13: Grupo Bordalo | N13: 234 025 683; 234 420 893 | S13: https://www.facebook.com/pages/Escola-de-condu%C3%A7%C3%A3o-Bordalo-Pinheiro/127727473957013 | U13: 2.8 | V13: 33 | X13: Não divulgado online (sem plataforma de marcação visível) | Y13: Sim | Z13: Seg-Sex 10:00-12:30 e 14:00-20:00; Sábado 10:00-12:30 (aberto ao sábado de manhã) | AA13: 378 | AC13: "desmarcam aulas à última da hora"; "ser do conhecimento da secretaria que o instrutor não poderia comparecer a uma aula e não me informarem" (10/2023); "A escola tem poucas aulas e poucos horários difíceis de frequentar"; "vai adiando no tempo as aulas e os pedidos de exames" (08/2023); "Recepção ruim. Não fornece informações" (01/2024) — https://escola-de-conducao.pt/nova-de-aveiro-escola-de-conducao-306455.html | AD13: Grupo Bordalo (multi-escola: Nova de Aveiro, Rainha de Aveiro, Águeda); 2.º maior volume do concelho; dor explícita com desmarcações e falta de comunicação — encaixe direto com notificações push | AH13: 0 | AL13: =IF(IF(O13<>"",O13,IF(LEFT(TRIM(N13),1)="9",N13,""))="","",HYPERLINK("https://wa.me/351"&LEFT(SUBSTITUTE(SUBSTITUTE(SUBSTITUTE(IF(O13<>"",O13,IF(LEFT(TRIM(N13),1)="9",N13,""))," ",""),"+351",""),"-",""),9),"Abrir WhatsApp")) | AN13: Av. 5 de Outubro, n.º 21, R/C Dt.º, 3800-428 Aveiro (Google: R. Cmte. Rocha e Cunha 3, 3800-126) | AO13: https://www.bomcondutor.pt/escolas/escola/bordalo-pinheiro-nova-de-aveiro; https://escola-de-conducao.pt/nova-de-aveiro-escola-de-conducao-306455.html (rating Google via snapshot escola-de-conducao.pt); https://passaprimeira.xyz/en/districts-regions/aveiro/municipalities/aveiro/schools/; https://transitoagora.pt/escolas-conducao/aveiro
A14: 13 | B14: A | C14: 7.4 | D14: Novo | E14: Pedro | F14: grupo | G14: Santarém | H14: Ferreira do Zêzere | I14: Ferreira do Zêzere | J14: Escola de Condução Lago Azul (alvará 'Ferreira do Zêzere') | K14: Lago Azul (Ferreira do Zêzere + Figueiró dos Vinhos) | N14: 249 361 434 | O14: 912 231 788 | U14: 3.3 | V14: 6 | X14: Presencial/telefone | Y14: Sim | Z14: Seg-Sex 09:00-13:00 e 15:00-20:00; Sábado 09:00-13:00 (ABERTO sábado) | AA14: 98 | AB14: A, B, C, D, E; CAM, ADR | AC14: 'Fiquei muito desagradado com o não cumprimento do horário... nem sequer dado qualquer satisfação' (1/5, 2023, consulta médica na escola) - https://escola-de-conducao.pt/escola-de-conducao-lago-azul-lda-253847.html; 'Não recomendo!' (1/5, 2024) - mesma fonte | AD14: Grupo multi-site (Ferreira do Zêzere + Figueiró dos Vinhos, este com 86 exames 2021), todas as categorias, queixas de falta de comunicação/horários; rating 3.3. Exames 2021 = entrada IMT 'Ferreira do Zêzere' (mesmo telefone/morada histórica). | AH14: 0 | AL14: =IF(IF(O14<>"",O14,IF(LEFT(TRIM(N14),1)="9",N14,""))="","",HYPERLINK("https://wa.me/351"&LEFT(SUBSTITUTE(SUBSTITUTE(SUBSTITUTE(IF(O14<>"",O14,IF(LEFT(TRIM(N14),1)="9",N14,""))," ",""),"+351",""),"-",""),9),"Abrir WhatsApp")) -> Abrir WhatsApp | AM14: Uma avaliação refere 'Plataformas de estudo Online e Aplicações para estudar' (e-learning de código, não marcação) | AN14: Rua Dr. Francisco Sá Carneiro, 30, 2240-353 Ferreira do Zêzere (antes Urb. Quinta do Adro) | AO14: https://escola-de-conducao.pt/escola-de-conducao-lago-azul-lda-253847.html; https://www.racius.com/escola-de-conducao-lago-azul-lda/; https://www.testesdecodigogratis.com/escola-de-conducao/lago-azul-ferreira-do-zezere/; https://www.andardemoto.pt/escolas-de-conducao/dir/d/santarem/c/ferreira-do-zezere/p-2954/escola-de-conducao-quinta-do-adro/; https://www.imt-ip.pt/wp-content/uploads/2025/01/EscolasdeConducao-2021.pdf
A15: 14 | B15: A | C15: 7.2 | D15: Novo | E15: Pedro | F15: grupo | G15: Santarém | H15: Almeirim | I15: Almeirim | J15: Escola de Condução Jorge Justino - Almeirim | K15: Escolas de Condução Matos (família Tomé; antigo site matosconducao.com, inativo) | N15: 243 591 755 ; 243 593 590 | O15: 934 100 817 | AA15: 672 | AD15: Maior volume da zona (672 provas em 2021) e parte do grupo Matos; sem plataforma digital visível | AH15: 0 | AL15: =IF(IF(O15<>"",O15,IF(LEFT(TRIM(N15),1)="9",N15,""))="","",HYPERLINK("https://wa.me/351"&LEFT(SUBSTITUTE(SUBSTITUTE(SUBSTITUTE(IF(O15<>"",O15,IF(LEFT(TRIM(N15),1)="9",N15,""))," ",""),"+351",""),"-",""),9),"Abrir WhatsApp")) -> Abrir WhatsApp | AM15: Site do grupo matosconducao.com já não resolve (arquivo web 2013-2016 lista: Almeirim J. Justino, Almeirinense, Alpiarça, Azambuja, Cartaxo, Fazendas de Almeirim, Santarém Ribatejana, Pedro de Santarém) — https://web.archive.org/web/2013/http://www.matosconducao.com/matos/4567579683; nenhum portal do aluno visível | AN15: Av. 25 de Abril, Bloco D (Edifício Sintra de Inverno, r/c), 2080-012 Almeirim | AO15: https://www.testesdecodigogratis.com/escola-de-conducao/jorge-justino/; https://escolasconducao.com/escola/escola-de-conducao-jorge-justino-lda; https://www.imt-ip.pt/wp-content/uploads/2025/01/EscolasdeConducao-2021.pdf
A16: 15 | B16: A | C16: 7.1 | D16: Novo | E16: Pedro | F16: grupo | G16: Santarém | H16: Benavente | I16: Benavente | J16: Escola de Condução Nossa Senhora da Paz | K16: Nossa Senhora da Paz (Benavente, Cartaxo, Santarém) | N16: 263 517 675 | O16: 919 171 910 | P16: yes | Q16: geral@escolaconducao.pt | R16: https://www.escolaconducao.pt/ | S16: https://www.facebook.com/EscolaDeConducaoNossaSraDaPaz/ | T16: https://www.instagram.com/escolaconducaonsrapaz/ | X16: Telefone/WhatsApp e formulário de contacto; aulas técnicas 'em conformidade com a disponibilidade do instruendo/instrutor'; sem marcação online | Y16: Sim | Z16: Secretaria: Seg-Sex 09:30-12:30 / 14:30-19:30 (sábado não indicado); aulas práticas 08:30-19:30 | AA16: 524 | AB16: AM, A1, A2, A, B1, B, B+E, C1, C, C+E, D, T3 (mais cursos CAM, TCC, ADR, tacógrafos) | AC16: 'ter que esperar 30 min pra ser atendido, e em dia de consulta marcada pode esperar até 1 hora' / 'nas aulas de condução fazem sempre o mesmo percurso' (nov. 2022) https://portaldaqueixa.com/brands/escola-de-conducao-nossa-senhora-da-paz/complaints/escola-de-conducao-nossa-senhora-da-paz-pior-escola-de-conducao-do-pais-82918222; queixa sobre chumbos e comunicação com a instrutora (jul. 2020) https://portaldaqueixa.com/brands/escola-de-conducao-nossa-senhora-da-paz/complaints/escola-de-conducao-nossa-senhora-da-paz-quero-que-seja-averiguado-o-motivo-de-tanto-chumbo-nesta-escola-43513520 | AD16: Grupo com 3 escolas, todas as categorias, volume alto (524 provas em 2021), presença digital ativa e queixas no Portal da Queixa sobre esperas no atendimento | AH16: 0 | AL16: =IF(IF(O16<>"",O16,IF(LEFT(TRIM(N16),1)="9",N16,""))="","",HYPERLINK("https://wa.me/351"&LEFT(SUBSTITUTE(SUBSTITUTE(SUBSTITUTE(IF(O16<>"",O16,IF(LEFT(TRIM(N16),1)="9",N16,""))," ",""),"+351",""),"-",""),9),"Abrir WhatsApp")) -> Abrir WhatsApp | AM16: O site tem plataforma de testes online para alunos (link para pugnatrix.com/proexamweb) e anuncia e-learning de código; não se identificou AGEOnline/BDrive/ALSIS. Também tem TikTok @escola.nossasradapaz | AN16: Rua Joaquim Rodrigues Parracho, Lote 25 R/C Dto, 2130-060 Benavente | AO16: https://www.escolaconducao.pt/; https://www.escolaconducao.pt/escola.html; https://www.escolaconducao.pt/contactos.html; https://www.escolaconducao.pt/cartas.html; https://www.bomcondutor.pt/escolas/escola/nossa-senhora-da-paz; https://portaldaqueixa.com/brands/escola-de-conducao-nossa-senhora-da-paz/complaints; https://www.imt-ip.pt/wp-content/uploads/2025/01/EscolasdeConducao-2021.pdf
A17: 16 | B17: A | C17: 7 | D17: Novo | E17: Pedro | F17: grupo | G17: Leiria | H17: Leiria | I17: Leiria (Guimarota) | J17: Escola de Condução Rota do Sol - Leiria | K17: Rota do Sol | N17: 244 828 600 | Q17: escola@rotadosol.pt | R17: http://www.rotadosol.pt/ | S17: https://www.facebook.com/escolarotadosol | U17: 5 | V17: 240 | X17: Telefone/presencial (reviews elogiam flexibilidade de horários ajustados pela secretaria) | Y17: Sim | Z17: 2ª-6ª 10h-13h / 15h-18h30; Sábado 10h-13h (ABERTO sábado, segundo Google) | AA17: 498 | AD17: 2 escolas (Leiria + Caranguejeira); 498 exames 2021; muito ativa em reviews (240, 5.0); site obsoleto, sem app | AH17: 0 | AL17: =IF(IF(O17<>"",O17,IF(LEFT(TRIM(N17),1)="9",N17,""))="","",HYPERLINK("https://wa.me/351"&LEFT(SUBSTITUTE(SUBSTITUTE(SUBSTITUTE(IF(O17<>"",O17,IF(LEFT(TRIM(N17),1)="9",N17,""))," ",""),"+351",""),"-",""),9),"Abrir WhatsApp")) | AM17: Site rotadosol.pt desatualizado (2012), sem área do aluno | AN17: Praceta Cristiano Schurmann, 55 - 2410-380 Leiria (Guimarota) | AO17: https://passaprimeira.xyz/distritos-regioes/leiria/concelhos/leiria/escolas/rota-do-sol-00695/; https://escola-de-conducao.pt/escola-de-conducao-rota-do-sol-leiria-306233.html; https://www.bomcondutor.pt/escolas/escola/rota-do-sol-leiria; https://www.andardemoto.pt/escolas-de-conducao/dir/d/leiria/c/leiria/p-2983/escola-de-conducao-rota-do-sol/
A18: 17 | B18: A | C18: 7 | D18: Novo | E18: Pedro | F18: grupo | G18: Lisboa | H18: Alenquer | I18: Alenquer | J18: Escola de Condução Nova Paredes (MegaDriving) | K18: MegaDriving | N18: 263 738 183 | O18: 966 216 719 | Q18: novaparedes.ec@gmail.com | R18: https://www.megadriving.com.pt/ec_novaparedes.php | S18: https://www.facebook.com/p/Escola-de-Condu%C3%A7%C3%A3o-Nova-Paredes-100057583264805/ | U18: 4.5 | V18: 4 | X18: Presencial/telefone; sem marcação online visível | Y18: Sim | Z18: Secretaria 2ª-6ª 10h-13h e 15h-20h; Sábado 10h-13h (ABERTO sábado de manhã; Google indica sábado 09h-13h) | AA18: 495 | AD18: Grupo MegaDriving + volume alto (495 provas 2021). Ocupa a morada da antiga 'Bordalo - Alão' listada no bomcondutor (dados desatualizados) | AH18: 0 | AL18: =IF(IF(O18<>"",O18,IF(LEFT(TRIM(N18),1)="9",N18,""))="","",HYPERLINK("https://wa.me/351"&LEFT(SUBSTITUTE(SUBSTITUTE(SUBSTITUTE(IF(O18<>"",O18,IF(LEFT(TRIM(N18),1)="9",N18,""))," ",""),"+351",""),"-",""),9),"Abrir WhatsApp")) -> Abrir WhatsApp | AM18: Site do grupo (megadriving.com.pt) só tem formulário de contacto e página de inscrição; sem área do aluno nem links para AGEOnline/BDrive/ALSIS | AN18: Rua Jorge Cunha e Carmo, Lt 35 R/C Direito, 2580-531 Alenquer | AO18: https://www.megadriving.com.pt/ec_novaparedes.php; https://passaprimeira.xyz/distritos-regioes/lisboa/concelhos/alenquer/escolas/; https://www.imt-ip.pt/wp-content/uploads/2025/01/EscolasdeConducao-2021.pdf; https://escola-de-conducao.pt/escola-de-conducao-nova-paredes-306473.html; https://www.bomcondutor.pt/escolas/escola/bordalo-alao
A19: 18 | B19: A | C19: 6.9 | D19: Novo | E19: Pedro | F19: grupo | G19: Leiria | H19: Alcobaça | I19: Benedita | J19: Escola de Condução Beneditense | K19: Grupo Letra (inferido: mesmo telefone 262 929 464 e ficha Google liga a grupoletra.pt) | N19: 262 929 464 | R19: http://www.grupoletra.pt/ | S19: https://www.facebook.com/beneditense | U19: 4.8 | V19: 9 | AA19: 465 | AD19: Provável Grupo Letra; volume elevado (465 exames 2021) | AH19: 0 | AL19: =IF(IF(O19<>"",O19,IF(LEFT(TRIM(N19),1)="9",N19,""))="","",HYPERLINK("https://wa.me/351"&LEFT(SUBSTITUTE(SUBSTITUTE(SUBSTITUTE(IF(O19<>"",O19,IF(LEFT(TRIM(N19),1)="9",N19,""))," ",""),"+351",""),"-",""),9),"Abrir WhatsApp")) | AN19: Rua Padre Dr. Fernando Maurício, 2 r/c - 2475-138 Benedita | AO19: https://passaprimeira.xyz/distritos-regioes/leiria/concelhos/alcobaca/escolas/beneditense-00528/; https://escola-de-conducao.pt/escola-de-conducao-beneditense-lda-307165.html; https://www.bomcondutor.pt/escolas/escola/beneditense
A20: 19 | B20: A | C20: 6.9 | D20: Novo | E20: Pedro | F20: grupo | G20: Lisboa | H20: Sobral de Monte Agraço | I20: Sobral de Monte Agraço | J20: Escola de Condução Sobralense (Progresso Sobralense) | K20: Sobralense / Arrudense (provável: partilham o telefone 261 941 052) | N20: 261 941 293; 261 941 052 | O20: 964 648 572 | S20: https://www.facebook.com/Escola.Sobralense | U20: 4.5 | V20: 19 | X20: Presencial/telefone | Y20: Sim | Z20: 2ª-6ª 09h-13h e 15h-21h; Sábado 09h-13h (ABERTO sábado de manhã) - Google | AA20: 465 | AD20: Volume alto (465) + provável grupo com a Arrudense; sem app | AH20: 0 | AL20: =IF(IF(O20<>"",O20,IF(LEFT(TRIM(N20),1)="9",N20,""))="","",HYPERLINK("https://wa.me/351"&LEFT(SUBSTITUTE(SUBSTITUTE(SUBSTITUTE(IF(O20<>"",O20,IF(LEFT(TRIM(N20),1)="9",N20,""))," ",""),"+351",""),"-",""),9),"Abrir WhatsApp")) -> Abrir WhatsApp | AN20: Avenida Marquês de Pombal, nº 53 Loja Dta, 2590-041 Sobral de Monte Agraço | AO20: https://www.bomcondutor.pt/escolas/escola/sobralense; https://escola-de-conducao.pt/escola-de-conducao-sobralense-237628.html; https://www.imt-ip.pt/wp-content/uploads/2025/01/EscolasdeConducao-2021.pdf
A21: 20 | B21: A | C21: 6.9 | D21: Novo | E21: Pedro | F21: grupo | G21: Coimbra | H21: Oliveira do Hospital | I21: Oliveira do Hospital | J21: Escola de Condução Oliveirense (sede Grupo MGA) | K21: Grupo MGA (Escolas MGA, desde 1971) - 5 escolas no distrito | N21: 238 609 505 | O21: 961 448 303; 969 027 540 | Q21: geral@escolasmga.pt | R21: https://escolasmga.pt/escolas-de-conducao/oliveira-do-hospital-oliveirense/ | S21: https://www.facebook.com/escolasgrupomga | U21: 4.5 | V21: 46 | W21: BDrive | X21: Secretaria/telefone; BDrive para alunos registados; oferece 'Carta em 1 mês' com alojamento | Y21: Sim | Z21: Seg-Sex 09:00-12:00 / 14:00-19:00; Sábado 09:00-12:00 (aberto ao sábado) | AA21: 594 | AB21: A, A1, A2, B1, B, B automático, BE, C, C1, CE, D, D1, DE, T, veículos adaptados; CAM | AC21: 'Liguei para obter algumas informações ... o Dono desta escola me responde num tom rude' (2024, https://escola-de-conducao.pt/escola-de-conducao-mga-oliveirense-desde-1971-305796.html) | AD21: Sede do Grupo MGA (5 escolas no distrito) — decisor do grupo; 594 provas 2021 | AH21: 0 | AL21: =IF(IF(O21<>"",O21,IF(LEFT(TRIM(N21),1)="9",N21,""))="","",HYPERLINK("https://wa.me/351"&LEFT(SUBSTITUTE(SUBSTITUTE(SUBSTITUTE(IF(O21<>"",O21,IF(LEFT(TRIM(N21),1)="9",N21,""))," ",""),"+351",""),"-",""),9),"Abrir WhatsApp")) -> Abrir WhatsApp | AM21: https://escolasmga.pt/servicos/plataforma-bdrive/ (link para bdrive.pt, 'Acesso exclusivo a instruendos registados'); também 'Plataforma de Testes' e 'Pré-inscrição Online' | AN21: Av. Dr. Carlos Campos, Apartado 1, 3404-909 Oliveira do Hospital | AO21: https://escolasmga.pt/escolas-de-conducao/; https://escola-de-conducao.pt/escola-de-conducao-mga-oliveirense-desde-1971-305796.html; https://www.andardemoto.pt/escolas-de-conducao/dir/d/coimbra/c/oliveira-do-hospital/p-3313/oliveirense/; https://www.imt-ip.pt/wp-content/uploads/2025/01/EscolasdeConducao-2021.pdf
A22: 21 | B22: A | C22: 6.8 | D22: Novo | E22: Pedro | F22: grupo | G22: Santarém | H22: Santarém | I22: Santarém | J22: Escola de Condução Ribatejana (Tomé) | K22: Escolas de Condução Matos (família Tomé; antigo site matosconducao.com, inativo) | N22: 243 322 500 ; 243 328 512 | O22: 939 349 024 | Q22: ecribatejana@hotmail.com | X22: Telefone/presencial | AA22: 580 | AD22: Parte do grupo Matos; maior volume do grupo em Santarém (IMT 2021 'Escola de Condução Tomé' = mesma morada/telefone 243 328 512) | AH22: 0 | AL22: =IF(IF(O22<>"",O22,IF(LEFT(TRIM(N22),1)="9",N22,""))="","",HYPERLINK("https://wa.me/351"&LEFT(SUBSTITUTE(SUBSTITUTE(SUBSTITUTE(IF(O22<>"",O22,IF(LEFT(TRIM(N22),1)="9",N22,""))," ",""),"+351",""),"-",""),9),"Abrir WhatsApp")) -> Abrir WhatsApp | AM22: Site do grupo matosconducao.com já não resolve (arquivo web 2013-2016 lista: Almeirim J. Justino, Almeirinense, Alpiarça, Azambuja, Cartaxo, Fazendas de Almeirim, Santarém Ribatejana, Pedro de Santarém) — https://web.archive.org/web/2013/http://www.matosconducao.com/matos/4567579683; nenhum portal do aluno visível | AN22: Largo Infante Santo nº 4, 1º Esq., 2005-246 Santarém | AO22: https://www.andardemoto.pt/escolas-de-conducao/dir/d/santarem/c/santarem/p-2964/escola-de-conducao-ribatejana/; https://www.testesdecodigogratis.com/escola-de-conducao/ribatejana/; https://www.municipiosefreguesias.pt/entidade/166988/escola-de-conducao-tome--santarem; https://www.imt-ip.pt/wp-content/uploads/2025/01/EscolasdeConducao-2021.pdf
A23: 22 | B23: A | C23: 6.7 | D23: Novo | E23: Pedro | F23: grupo | G23: Leiria | H23: Marinha Grande | I23: Marinha Grande | J23: Escola de Condução Batalhense - Marinha Grande | K23: Grupo Batalhense | N23: 244 569 430 | O23: 918 782 381 | Q23: marinha@batalhense.com | R23: https://batalhense.com/escolas/escola-de-conducao-batalhense-marinha-grande/ | S23: https://www.facebook.com/grupobatalhense | T23: https://www.instagram.com/batalhensegrupo/ | X23: Telefone/secretaria presencial; formulário de inscrição no site | Y23: Não | Z23: Secretaria 2ª-6ª 9h30-12h30 / 14h30-19h30; sábado não indicado no site (provavelmente fechado) | AA23: 426 | AB23: A, B, C, D (grupo) | AD23: Grupo Batalhense (multi-escola); 426 exames 2021 | AH23: 0 | AL23: =IF(IF(O23<>"",O23,IF(LEFT(TRIM(N23),1)="9",N23,""))="","",HYPERLINK("https://wa.me/351"&LEFT(SUBSTITUTE(SUBSTITUTE(SUBSTITUTE(IF(O23<>"",O23,IF(LEFT(TRIM(N23),1)="9",N23,""))," ",""),"+351",""),"-",""),9),"Abrir WhatsApp")) -> Abrir WhatsApp | AM23: Sem área do aluno/app no site batalhense.com; só formulário de inscrição (contacto). Aulas de código online de apoio (3ª e 5ª). | AN23: R. Alfredo Gândara, 22 - 2430-300 Marinha Grande | AO23: https://passaprimeira.xyz/distritos-regioes/leiria/concelhos/marinha-grande/escolas/batalhense-da-marinha-grande-00855/; https://batalhense.com/; https://batalhense.com/escolas/escola-de-conducao-batalhense-marinha-grande/
A24: 23 | B24: A | C24: 6.6 | D24: Novo | E24: Pedro | F24: grupo | G24: Leiria | H24: Alcobaça | I24: Alcobaça | J24: Escola de Condução Alcobacense | K24: Grupo Letra | N24: 262 929 464 | Q24: geral.alcobacense@gmail.com / esc.alcobacense@gmail.com | R24: https://www.alcobacense.com/ | S24: https://www.facebook.com/escconducaoalcobacense/ | T24: https://www.instagram.com/esc_alcobacense/ | U24: 4.9 | V24: 8 | X24: Telefone/presencial; inscrição por formulário no site | Y24: Sim | Z24: 2ª-6ª 9h-13h / 14h30-18h30; Sábado 10h-12h (sob consulta) | AA24: 412 | AB24: AM, A1, A2, A, B, B+E, condução com tutor, pesados; CAM, TVDE | AD24: Grupo Letra (Alcobacense + Beneditense + Motoschool + centro de formação); 412 exames 2021 | AH24: 0 | AL24: =IF(IF(O24<>"",O24,IF(LEFT(TRIM(N24),1)="9",N24,""))="","",HYPERLINK("https://wa.me/351"&LEFT(SUBSTITUTE(SUBSTITUTE(SUBSTITUTE(IF(O24<>"",O24,IF(LEFT(TRIM(N24),1)="9",N24,""))," ",""),"+351",""),"-",""),9),"Abrir WhatsApp")) | AM24: Site Webnode com páginas "Mapa de Aulas", "Ensino à Distância" e "Testes de Código" (sem área do aluno/app de marcação) | AN24: Rua Luís de Camões, 67 Lote A R/C - 2460-014 Alcobaça | AO24: https://passaprimeira.xyz/distritos-regioes/leiria/concelhos/alcobaca/escolas/alcobacense-00179/; https://grupoletra.pt/alcobacense/; https://grupoletra.pt/contacto/; https://www.alcobacense.com/; https://escola-de-conducao.pt/escola-de-conducao-alcobacense-306702.html
A25: 24 | B25: A | C25: 6.6 | D25: Novo | E25: Pedro | F25: grupo | G25: Santarém | H25: Ourém | I25: Ourém | J25: Escola de Condução Ouriense | K25: Espada & Oliveira (Ouriense, Fatimense, Caxariense) | N25: 249 545 208 | O25: 919 537 599 / 933 890 089 / 933 885 930 | Q25: ec-ouriense@espadaeoliveira.com | R25: https://www.espadaeoliveira.pt/ouriense.php | S25: https://www.facebook.com/pages/ESCOLA-DE-CONDU%C3%87%C3%83O-OURIENSE/117550408321810 | U25: 4.2 | V25: 6 | X25: Telefone/presencial; pré-inscrição por formulário no site | Y25: Sim | Z25: Seg-Sex 09:00-12:30 e 14:30-19:30; Sábado 09:00-12:00 (ABERTO sábado) | AA25: 524 | AB25: Todas as categorias (A, B, C, D, E); CAM, TCC, tacógrafos | AD25: Sede de um grupo com 3 escolas (Ourém, Fátima, Caxarias), alvará desde 1956, 524 exames 2021, também centro de formação CAM. | AH25: 0 | AL25: =IF(IF(O25<>"",O25,IF(LEFT(TRIM(N25),1)="9",N25,""))="","",HYPERLINK("https://wa.me/351"&LEFT(SUBSTITUTE(SUBSTITUTE(SUBSTITUTE(IF(O25<>"",O25,IF(LEFT(TRIM(N25),1)="9",N25,""))," ",""),"+351",""),"-",""),9),"Abrir WhatsApp")) -> Abrir WhatsApp | AM25: Sem área do aluno; testes de código online alojados em educacao-rodoviaria.pt (http://www.educacao-rodoviaria.pt/testesonline/ouriense/); inscrição por formulário web | AN25: Praceta Prof. António de Oliveira, 4, 2490-502 Ourém | AO25: https://www.espadaeoliveira.pt/ouriense.php; https://www.espadaeoliveira.pt/contactos_ouriense.php; https://escola-de-conducao.pt/escola-de-conducao-ouriense-306307.html; https://www.testesdecodigogratis.com/escola-de-conducao/ouriense/; https://www.imt-ip.pt/wp-content/uploads/2025/01/EscolasdeConducao-2021.pdf
A26: 25 | B26: A | C26: 6.6 | D26: Novo | E26: Pedro | F26: grupo | G26: Lisboa | H26: Lourinhã | I26: Lourinhã | J26: Escola de Condução Dinossauro | K26: Bordalo (segundo o bomcondutor; não confirmado) | N26: 261 419 702 | X26: Presencial/telefone | AA26: 410 | AD26: Volume alto (410) sem presença digital própria; possivelmente integra o grupo Bordalo (Caldas da Rainha) - confirmar | AH26: 0 | AL26: =IF(IF(O26<>"",O26,IF(LEFT(TRIM(N26),1)="9",N26,""))="","",HYPERLINK("https://wa.me/351"&LEFT(SUBSTITUTE(SUBSTITUTE(SUBSTITUTE(IF(O26<>"",O26,IF(LEFT(TRIM(N26),1)="9",N26,""))," ",""),"+351",""),"-",""),9),"Abrir WhatsApp")) | AN26: Rua (Casal) Santa Catarina, nº 1, 2530-116 Lourinhã | AO26: https://www.bomcondutor.pt/escolas/escola/dinossauro; https://www.autonews.pt/escolas-de-conducao/dir/d/lisboa/c/lourinha/p-2359/escola-conducao-dinossauro/; https://passaprimeira.xyz/distritos-regioes/lisboa/concelhos/lourinha/escolas/; https://www.imt-ip.pt/wp-content/uploads/2025/01/EscolasdeConducao-2021.pdf
A27: 26 | B27: A | C27: 6.5 | D27: Novo | E27: Pedro | F27: grupo | G27: Leiria | H27: Leiria | I27: Leiria | J27: Escola de Condução Esteves - Leiria | K27: Escolas de Condução Esteves | N27: 244 882 600 | O27: 918 732 181 | Q27: escola.esteves@gmail.com | R27: https://ec-esteves.pt/ | S27: https://www.facebook.com/escolaesteves | U27: 4.6 | V27: 18 | X27: Telefone/secretaria; formulário de contacto no site | Y27: Sim | Z27: Secretaria dias úteis 9h-12h / 14h-19h30; Sábado 9h30-12h (ABERTO sábado de manhã); aulas de código seg-sáb 10h-12h | AA27: 380 | AB27: B, CAM, TCC, tratores agrícolas | AD27: Grupo com 3 escolas (Leiria, Vieira de Leiria, Clube do Condutor - Pombal); 380 exames 2021; sem app | AH27: 0 | AL27: =IF(IF(O27<>"",O27,IF(LEFT(TRIM(N27),1)="9",N27,""))="","",HYPERLINK("https://wa.me/351"&LEFT(SUBSTITUTE(SUBSTITUTE(SUBSTITUTE(IF(O27<>"",O27,IF(LEFT(TRIM(N27),1)="9",N27,""))," ",""),"+351",""),"-",""),9),"Abrir WhatsApp")) -> Abrir WhatsApp | AM27: Site WordPress sem área do aluno; link "Testes Online" | AN27: Estrada da Estação, Lt. 1 - Lj. 52, 2415-440 Leiria (IMT: Rua António Alves Espírito Santo, Lote 1, Loja 92) | AO27: https://passaprimeira.xyz/distritos-regioes/leiria/concelhos/leiria/escolas/esteves-00766/; https://ec-esteves.pt/contactos/; https://ec-esteves.pt/horarios/; https://escola-de-conducao.pt/escola-de-conducao-esteves-305910.html
A28: 27 | B28: A | C28: 6.5 | D28: Novo | E28: Pedro | F28: grupo | G28: Lisboa | H28: Cadaval | I28: Cadaval | J28: Escola de Condução Auto do Cadaval (MegaDriving) | K28: MegaDriving (10 escolas: Cadaval, Painho, Merceana, Alenquer, Lourinhã, Campelos, Bombarral, Caldas da Rainha, Atouguia da Baleia, Castanheira do Ribatejo) | N28: 262 696 231 | O28: 961 147 180 | Q28: autocadaval.ec@gmail.com | R28: https://www.megadriving.com.pt/ec_cadaval.php | S28: https://www.facebook.com/MegaDrivingEC/ | X28: Presencial/telefone; 'Aulas teóricas e práticas em horário alargado, de acordo com as tuas necessidades!' (site); sem marcação online visível | Y28: Sim | Z28: Secretaria 2ª-6ª 10h-13h e 15h-20h; Sábado 10h-13h (ABERTO sábado de manhã) | AA28: 365 | AB28: Todas as categorias (inclui pesados de passageiros); o grupo dá formação CAM, TCC, ADR, tacógrafos | AD28: Grupo multi-escola (MegaDriving, 10 escolas, 6 no âmbito) sem app/plataforma de aluno; escola mais antiga da região (1971) | AH28: 0 | AL28: =IF(IF(O28<>"",O28,IF(LEFT(TRIM(N28),1)="9",N28,""))="","",HYPERLINK("https://wa.me/351"&LEFT(SUBSTITUTE(SUBSTITUTE(SUBSTITUTE(IF(O28<>"",O28,IF(LEFT(TRIM(N28),1)="9",N28,""))," ",""),"+351",""),"-",""),9),"Abrir WhatsApp")) -> Abrir WhatsApp | AM28: Site do grupo (megadriving.com.pt) só tem formulário de contacto e página de inscrição; sem área do aluno nem links para AGEOnline/BDrive/ALSIS | AN28: Rua D. Fernando, 55 - 1º, 2550-142 Cadaval | AO28: https://www.megadriving.com.pt/ec_cadaval.php; https://www.megadriving.com.pt/; https://passaprimeira.xyz/distritos-regioes/lisboa/concelhos/cadaval/escolas/; https://www.imt-ip.pt/wp-content/uploads/2025/01/EscolasdeConducao-2021.pdf; https://www.municipiosefreguesias.pt/entidade/166451/escola-de-conducao-auto-do-cadaval
A29: 28 | B29: A | C29: 6.5 | D29: Novo | E29: Pedro | F29: grupo | G29: Viseu | H29: Viseu | I29: Viseu | J29: Escolas de Condução Viriato | K29: Escolas de Condução Viriato (Viriato + ex-Viseense/Xandey + Etapas & Objectivos) | N29: 232422907 | O29: 927539210 | Q29: ecviriato@outlook.pt | R29: https://ecviriato.pt | S29: https://www.facebook.com/escoladeconducaoviriato | T29: https://www.instagram.com/escoladeconducaoviriato | U29: 4.3 | V29: 40 | W29: Área do aluno própria no site (login por NIF + senha, /login/) + inscrição online; fornecedor e funcionalidades desconhecidos | X29: Presencial/telefone com a secretaria (avaliações: 'relativamente às marcações de aulas, são super acessíveis'; 'dando bastantes alternativas'); sem evidência de marcação online | Y29: Sim | Z29: Seg-Sex 10h-12h, 14h-19h30; Sáb 10h-12h | AA29: 790 | AB29: A1, A2, A, B, B1, C, C+E, D (site: única em Viseu com todas as categorias); também CAM, formação de instrutores (Etapas & Objectivos), Condução para Todos | AC29: Portal da Queixa 31/01/2022 (sem resolução): aluno inscrito em 2019 perde prazo de exame; resposta por telefone 'não havia nada a fazer' - https://portaldaqueixa.com/brands/escola-de-conducao-viriato/complaints/escola-de-conducao-viriato-carta-de-conducao-70821422; Avaliação 1/5 (10/03/2022): 'Justificasse sempre com o Covid. Para tirar uma carta quasse 1 anos' - https://escola-de-conducao.pt/escolas-de-conducao-viriato-306062.html; Portal da Queixa 16/04/2019: demora no exame CAM - https://portaldaqueixa.com/brands/escola-de-conducao-viriato | AD29: Maior escola do concelho (790 provas 2021); grupo (fusão com Viseense + centro de formação Etapas & Objectivos); sinais de dor documentados; presença social muito ativa (FB 4193 seguidores/46 a falar; IG 1296 posts). Atenção: já tem área do aluno própria (login NIF) - verificar se inclui marcação de aulas. | AH29: 0 | AL29: =IF(IF(O29<>"",O29,IF(LEFT(TRIM(N29),1)="9",N29,""))="","",HYPERLINK("https://wa.me/351"&LEFT(SUBSTITUTE(SUBSTITUTE(SUBSTITUTE(IF(O29<>"",O29,IF(LEFT(TRIM(N29),1)="9",N29,""))," ",""),"+351",""),"-",""),9),"Abrir WhatsApp")) -> Abrir WhatsApp | AM29: https://ecviriato.pt/login/login.php; https://ecviriato.pt/inscricao-online/ | AN29: Praça de Goa, Lote/Bloco 14 R/C, 3510-069 Viseu | AO29: https://ecviriato.pt/; https://ecviriato.pt/login/login.php; https://escola-de-conducao.pt/escolas-de-conducao-viriato-306062.html; https://portaldaqueixa.com/brands/escola-de-conducao-viriato; https://www.imt-ip.pt/wp-content/uploads/2025/07/EntidadesReconhecidas-IMT-MinistracaoDeCursosDeFormacao.pdf; https://www.facebook.com/escoladeconducaoviriato; https://www.instagram.com/escoladeconducaoviriato/
A30: 29 | B30: A | C30: 6.4 | D30: Novo | E30: Pedro | F30: grupo | G30: Leiria | H30: Marinha Grande | I30: Vieira de Leiria | J30: Escola de Condução Esteves - Vieira de Leiria | K30: Escolas de Condução Esteves | N30: 244 691 902 | O30: 912 265 148 | Q30: escola.esteves.vieira@gmail.com | R30: https://ec-esteves.pt/ | S30: https://www.facebook.com/escolaesteves | U30: 4.6 | V30: 8 | X30: Telefone/secretaria | Y30: Sim | Z30: Secretaria dias úteis 10h-12h30 / 14h30-20h; FECHADO ao sábado | AA30: 346 | AD30: Grupo Esteves (3 escolas); 346 exames 2021 | AH30: 0 | AL30: =IF(IF(O30<>"",O30,IF(LEFT(TRIM(N30),1)="9",N30,""))="","",HYPERLINK("https://wa.me/351"&LEFT(SUBSTITUTE(SUBSTITUTE(SUBSTITUTE(IF(O30<>"",O30,IF(LEFT(TRIM(N30),1)="9",N30,""))," ",""),"+351",""),"-",""),9),"Abrir WhatsApp")) -> Abrir WhatsApp | AN30: Estádio Tomé Albano Feteira, Rua de Leiria - 2430-773 Vieira de Leiria | AO30: https://passaprimeira.xyz/distritos-regioes/leiria/concelhos/marinha-grande/escolas/esteves-da-vieira-01170/; https://ec-esteves.pt/contactos/; https://ec-esteves.pt/horarios/; https://escola-de-conducao.pt/escola-de-conducao-esteves-da-vieira-305908.html
A31: 30 | B31: A | C31: 6.4 | D31: Novo | E31: Pedro | F31: grupo | G31: Santarém | H31: Ourém | I31: Fátima | J31: Escola de Condução Fatimense | K31: Espada & Oliveira (Ouriense, Fatimense, Caxariense) | N31: 249 532 161 | O31: 919 613 040 / 933 890 047 | Q31: ec-fatimense@espadaeoliveira.com | R31: https://www.espadaeoliveira.pt/fatimense.php | S31: https://www.facebook.com/pages/ESCOLA-DE-CONDU%C3%87%C3%83O-OURIENSE/117550408321810 | U31: 4 | V31: 4 | X31: Telefone/presencial; pré-inscrição por formulário no site | Y31: Sim | Z31: Seg-Sex 10:30-13:00 e 15:00-19:30; Sábado 09:00-12:00 (ABERTO sábado) | AA31: 98 | AC31: 'Gama de preços muito elevada' (1/5, 2017) - https://escola-de-conducao.pt/escola-de-conducao-fatimense-306031.html | AD31: Delegação do grupo Espada & Oliveira (3 escolas). | AH31: 0 | AL31: =IF(IF(O31<>"",O31,IF(LEFT(TRIM(N31),1)="9",N31,""))="","",HYPERLINK("https://wa.me/351"&LEFT(SUBSTITUTE(SUBSTITUTE(SUBSTITUTE(IF(O31<>"",O31,IF(LEFT(TRIM(N31),1)="9",N31,""))," ",""),"+351",""),"-",""),9),"Abrir WhatsApp")) -> Abrir WhatsApp | AM31: Sem área do aluno; testes de código online alojados em educacao-rodoviaria.pt (http://www.educacao-rodoviaria.pt/testesonline/ouriense/); inscrição por formulário web | AN31: Estrada Principal de Fátima, Edifício Fátima, Loja 2 R/C, 2495-552 Fátima | AO31: https://www.espadaeoliveira.pt/contactos_fatimense.php; https://escola-de-conducao.pt/escola-de-conducao-fatimense-306031.html; https://www.testesdecodigogratis.com/escola-de-conducao/fatimense/; https://www.imt-ip.pt/wp-content/uploads/2025/01/EscolasdeConducao-2021.pdf
A32: 31 | B32: A | C32: 6.4 | D32: Novo | E32: Pedro | F32: grupo | G32: Santarém | H32: Santarém | I32: Santarém (S. Domingos) | J32: Escola de Condução Santarém | K32: Possível grupo Andrade (Escola de Condução Andrade Lda; mesma morada listada como 'Escola de Condução de Coruche') — a confirmar | N32: 243 372 579 | O32: 914 895 609 | Q32: geral@ecsantarem.com | R32: https://ecsantarem.com/ | S32: https://www.facebook.com/escoladeconducao.santarem/ | U32: 4.4 | V32: 31 | X32: Telefone/presencial; teóricas sem marcação prévia (site) | Y32: Sim | Z32: Site: Semana 09:00-18:00, Sábado 09:00-13:00 (secretaria 2ª-6ª 09:00-12:00/14:30-19:00); aulas práticas 2ª-6ª 09-13/14-20 e Sábado 09:00-13:00; Google: Sáb 09:00-13:00 (ABERTO SÁBADO) | AA32: 349 | AB32: A1, A2, A, B, C, CE (+ CAM, ADR, Táxi) | AC32: 'Já tentei ligar mas não atendem, tbm já mandei um e-mail e não tive retorno' — https://escola-de-conducao.pt/escola-de-conducao-de-santarem-306347.html | AD32: Escola de volume médio-alto com formação profissional (CAM/ADR), sem app/área do aluno, queixa de não atender telefone; possível ligação a Coruche | AH32: 0 | AL32: =IF(IF(O32<>"",O32,IF(LEFT(TRIM(N32),1)="9",N32,""))="","",HYPERLINK("https://wa.me/351"&LEFT(SUBSTITUTE(SUBSTITUTE(SUBSTITUTE(IF(O32<>"",O32,IF(LEFT(TRIM(N32),1)="9",N32,""))," ",""),"+351",""),"-",""),9),"Abrir WhatsApp")) -> Abrir WhatsApp | AM32: Site WordPress institucional (ecsantarem.com) sem área do aluno, e-learning ou link a plataforma; só formulário de contacto | AN32: Av. Marquês de Pombal nº 117 R/C (junto à Rotunda da Fonte Luminosa), S. Domingos, 2005-170 Santarém | AO32: https://ecsantarem.com/; https://escola-de-conducao.pt/escola-de-conducao-de-santarem-306347.html; https://www.andardemoto.pt/escolas-de-conducao/dir/d/santarem/c/santarem/p-2111/escola-de-conducao-de-coruche/; https://escolasconducao.com/escola/escola-de-conducao-andrade-lda; https://www.imt-ip.pt/wp-content/uploads/2025/01/EscolasdeConducao-2021.pdf
A33: 32 | B33: A | C33: 6.4 | D33: Novo | E33: Pedro | F33: grupo | G33: Lisboa | H33: Arruda dos Vinhos | I33: Arruda dos Vinhos | J33: Escola de Condução Automóvel Arrudense | K33: Sobralense / Arrudense (provável: partilham o telefone 261 941 052) | N33: 263 975 100; 261 941 052 | S33: https://www.facebook.com/escola.arrudense | X33: Presencial/telefone | AA33: 351 | AD33: Provável grupo com a Sobralense (telefone partilhado; diretório refere uma 'Filial A. Vinhos' na mesma morada); volume médio | AH33: 0 | AL33: =IF(IF(O33<>"",O33,IF(LEFT(TRIM(N33),1)="9",N33,""))="","",HYPERLINK("https://wa.me/351"&LEFT(SUBSTITUTE(SUBSTITUTE(SUBSTITUTE(IF(O33<>"",O33,IF(LEFT(TRIM(N33),1)="9",N33,""))," ",""),"+351",""),"-",""),9),"Abrir WhatsApp")) | AN33: Rua Manuel Policarpo Martins, nº 15 R/C Dto, 2630-110 Arruda dos Vinhos | AO33: https://www.bomcondutor.pt/escolas/escola/arrudense; https://www.municipiosefreguesias.pt/entidade/166472/escola-de-conducao-automovel-arrudense-lda--arruda-dos-vinhos; https://passaprimeira.xyz/distritos-regioes/lisboa/concelhos/arruda-dos-vinhos/escolas/; https://www.imt-ip.pt/wp-content/uploads/2025/01/EscolasdeConducao-2021.pdf
A34: 33 | B34: A | C34: 6.3 | D34: Novo | E34: Pedro | F34: grupo | G34: Coimbra | H34: Coimbra | I34: Coimbra (Solum) | J34: Escola de Condução Quinta das Flores | K34: Possível grupo Capas Negras / Quinta das Flores / Solum (não confirmado) | O34: 915 742 412 | S34: https://www.facebook.com/ecquintadasflores/ | U34: 4.7 | V34: 55 | Y34: Sim | Z34: Seg-Sex 10:00-13:00 / 14:00-20:00; Sábado 10:00-13:00 (aberto ao sábado) | AA34: 454 | AC34: 'não sabe cumprir a sua palavra nem os seus prazos' (https://escola-de-conducao.pt/escola-de-conducao-quinta-das-flores-306247.html); 'péssimo planejamento das últimas aulas de código do dia ficando em sobrelotação' (idem) | AD34: Volume 454 provas (2021), queixas de planeamento/prazos, provável grupo com Capas Negras/Solum | AH34: 0 | AL34: =IF(IF(O34<>"",O34,IF(LEFT(TRIM(N34),1)="9",N34,""))="","",HYPERLINK("https://wa.me/351"&LEFT(SUBSTITUTE(SUBSTITUTE(SUBSTITUTE(IF(O34<>"",O34,IF(LEFT(TRIM(N34),1)="9",N34,""))," ",""),"+351",""),"-",""),9),"Abrir WhatsApp")) -> Abrir WhatsApp | AM34: Sem website identificado | AN34: Av. Dr. Mendes Silva, loja 285, 3030-193 Coimbra | AO34: https://escola-de-conducao.pt/escola-de-conducao-quinta-das-flores-306247.html; https://www.imt-ip.pt/wp-content/uploads/2025/01/EscolasdeConducao-2021.pdf
A35: 34 | B35: A | C35: 6.2 | D35: Novo | E35: Pedro | F35: grupo | G35: Leiria | H35: Pombal | I35: Pombal (Várzea) | J35: Escola de Condução Cardal | K35: Provável grupo EC Caldas (inferido) | O35: 917 774 734 | R35: http://www.eccaldas.pt/ (ligado na ficha Google) | U35: 4.7 | V35: 33 | X35: Telefone/presencial | Y35: Sim | Z35: 2ª-6ª 10h-12h30 / 14h-20h; Sábado 9h-13h (ABERTO sábado) | AA35: 168 | AC35: "Péssimo atendimento, não fornece as informações necessárias, parece que estamos a pedir-lhe favor" (Google 1★, 01/2023) https://escola-de-conducao.pt/escola-de-conducao-cardal-306425.html | AD35: Ficha Google aponta para eccaldas.pt (provável grupo com EC Caldas/Nova Rainha); queixa de atendimento | AH35: 0 | AL35: =IF(IF(O35<>"",O35,IF(LEFT(TRIM(N35),1)="9",N35,""))="","",HYPERLINK("https://wa.me/351"&LEFT(SUBSTITUTE(SUBSTITUTE(SUBSTITUTE(IF(O35<>"",O35,IF(LEFT(TRIM(N35),1)="9",N35,""))," ",""),"+351",""),"-",""),9),"Abrir WhatsApp")) -> Abrir WhatsApp | AN35: Av. Heróis do Ultramar, 177 - 3100-462 Pombal (IMT: Rua Marechal António Spínola, Ed. Intermarché, Várzea) | AO35: https://passaprimeira.xyz/distritos-regioes/leiria/concelhos/pombal/escolas/cardal-01394/; https://escola-de-conducao.pt/escola-de-conducao-cardal-306425.html
A36: 35 | B36: A | C36: 6.2 | D36: Novo | E36: Pedro | F36: grupo | G36: Leiria | H36: Caldas da Rainha | I36: Caldas da Rainha | J36: Escola de Condução Nova Rainha | K36: Provável grupo EC Caldas (mesma morada IMT que EC Caldas) | AA36: 294 | AD36: Mesma morada IMT que a EC Caldas (provável grupo); 294 exames 2021 | AH36: 0 | AL36: =IF(IF(O36<>"",O36,IF(LEFT(TRIM(N36),1)="9",N36,""))="","",HYPERLINK("https://wa.me/351"&LEFT(SUBSTITUTE(SUBSTITUTE(SUBSTITUTE(IF(O36<>"",O36,IF(LEFT(TRIM(N36),1)="9",N36,""))," ",""),"+351",""),"-",""),9),"Abrir WhatsApp")) | AN36: Rua Cardeal Alpedrinha, 72 A - 2500-843 Caldas da Rainha | AO36: https://passaprimeira.xyz/distritos-regioes/leiria/concelhos/caldas-da-rainha/escolas/nova-rainha-01333/
A37: 36 | B37: A | C37: 6.2 | D37: Novo | E37: Pedro | F37: grupo | G37: Coimbra | H37: Figueira da Foz | I37: Figueira da Foz | J37: Escola de Condução Abadias | K37: Escolas de Condução Abadias (Figueira da Foz + Marinha das Ondas) | N37: 233 434 846 | O37: 924 064 305 | P37: yes | R37: https://ecabadias.pt/ | S37: Página 'Escola de Condução Abadias' (ligada no site) | U37: 4.5 | V37: 30 | X37: Telefone/WhatsApp | Y37: Sim | Z37: Seg-Sex 10:00-13:00 / 14:00-19:00; Sábado 10:00-13:00 (aberto ao sábado) | AA37: 433 | AC37: 'plataforma fraca para o custo do serviço' (2020, https://escola-de-conducao.pt/escola-de-conducao-abadias-lda-305931.html) | AD37: Grupo com 2 escolas (Abadias + Marinha das Ondas), 433 provas 2021, site moderno com WhatsApp; portal só cobre teoria — não marcação de aulas | AH37: 0 | AL37: =IF(IF(O37<>"",O37,IF(LEFT(TRIM(N37),1)="9",N37,""))="","",HYPERLINK("https://wa.me/351"&LEFT(SUBSTITUTE(SUBSTITUTE(SUBSTITUTE(IF(O37<>"",O37,IF(LEFT(TRIM(N37),1)="9",N37,""))," ",""),"+351",""),"-",""),9),"Abrir WhatsApp")) -> Abrir WhatsApp | AM37: Site liga a portal de estudo teórico ensinoadistancia.segurancarodoviaria.pt (perguntas IMT, histórico, contacto com instrutor); WhatsApp (joinchat) no site | AN37: Rua Dr. Joaquim Sotto Mayor, 101, 3080-300 Figueira da Foz | AO37: https://ecabadias.pt/; https://escola-de-conducao.pt/escola-de-conducao-abadias-lda-305931.html; https://www.andardemoto.pt/escolas-de-conducao/dir/d/coimbra/c/figueira-da-foz/p-2054/abadias/; https://www.imt-ip.pt/wp-content/uploads/2025/01/EscolasdeConducao-2021.pdf
A38: 37 | B38: A | C38: 6.2 | D38: Novo | E38: Pedro | F38: grupo | G38: Coimbra | H38: Coimbra | I38: Coimbra | J38: Escola de Condução Capas Negras | K38: Possível grupo Capas Negras / Quinta das Flores / Solum (não confirmado) | O38: 916 762 665 | S38: https://www.facebook.com/eccapasnegras | T38: https://www.instagram.com/capas_negras/ | U38: 4.6 | V38: 54 | X38: Marcação pela escola (alunos queixam-se de poucas aulas marcadas) | Y38: Sim | Z38: Seg-Sex 10:00-20:00; Sábado 10:00-13:00 (aberto ao sábado) | AA38: 416 | AC38: 'não marcam nem as aulas 2 no máximo 3 mês' (https://escola-de-conducao.pt/escola-de-conducao-capas-negras-306495.html); 'marca 2 aulas por mês quando marca' (idem); 'não possuem comprometimento com os horários agendados' (idem); 2 queixas jun/2024 (https://portaldaqueixa.com/brands/escola-de-conducao-capas-negras) | AD38: Fortes sinais de dor na marcação de aulas + Instagram ativo + provável grupo com Quinta das Flores/Solum (telemóveis sequenciais e avaliações idênticas) | AH38: 0 | AL38: =IF(IF(O38<>"",O38,IF(LEFT(TRIM(N38),1)="9",N38,""))="","",HYPERLINK("https://wa.me/351"&LEFT(SUBSTITUTE(SUBSTITUTE(SUBSTITUTE(IF(O38<>"",O38,IF(LEFT(TRIM(N38),1)="9",N38,""))," ",""),"+351",""),"-",""),9),"Abrir WhatsApp")) -> Abrir WhatsApp | AM38: Sem website identificado | AN38: Largo da Portagem, 39, 4º andar, 3000-337 Coimbra | AO38: https://escola-de-conducao.pt/escola-de-conducao-capas-negras-306495.html; https://portaldaqueixa.com/brands/escola-de-conducao-capas-negras; https://www.imt-ip.pt/wp-content/uploads/2025/01/EscolasdeConducao-2021.pdf
A39: 38 | B39: A | C39: 6.1 | D39: Novo | E39: Pedro | F39: grupo | G39: Coimbra | H39: Tábua | I39: Tábua | J39: Escola de Condução Automóvel de Tábua / Rota da Estrela (Tábua) | K39: Grupo Rota da Estrela (Arganil, Penacova, Tábua + Seia/Nelas/Viseu/Tondela/Gouveia fora do distrito) | N39: 235 412 151 | O39: 962 806 877 | U39: 3.7 | V39: 3 | Y39: Sim | Z39: Seg-Sex 09:00-12:30 / 14:00-19:30; Sábado 09:00-12:00 (aberto ao sábado) | AA39: 283 | AD39: Delegação de grupo multi-site (Rota da Estrela); 283 provas 2021. Nota: mesma morada surge também como 'Filipa Ramos Barros Unipessoal' — possível mudança de titular | AH39: 0 | AL39: =IF(IF(O39<>"",O39,IF(LEFT(TRIM(N39),1)="9",N39,""))="","",HYPERLINK("https://wa.me/351"&LEFT(SUBSTITUTE(SUBSTITUTE(SUBSTITUTE(IF(O39<>"",O39,IF(LEFT(TRIM(N39),1)="9",N39,""))," ",""),"+351",""),"-",""),9),"Abrir WhatsApp")) -> Abrir WhatsApp | AM39: Site do grupo em baixo | AN39: Centro Comercial Jardim, R. Dr. Fortunato Vieira das Neves, Loja 11, 3420-324 Tábua | AO39: https://escola-de-conducao.pt/escola-de-conducao-automovel-de-tabua-307094.html; https://www.andardemoto.pt/escolas-de-conducao/dir/d/coimbra/c/tabua/p-2981/escola-de-conducao-rota-da-estrela/; https://www.andardemoto.pt/escolas-de-conducao/dir/d/coimbra/c/tabua/p-2173/automovel-de-tabua/; https://escola-de-conducao.pt/filipa-ramos-barros-unipessoal-limitada-307659.html; https://www.imt-ip.pt/wp-content/uploads/2025/01/EscolasdeConducao-2021.pdf
A40: 39 | B40: A | C40: 6 | D40: Novo | E40: Pedro | F40: grupo | G40: Leiria | H40: Leiria | I40: Leiria | J40: Escola de Condução Batalhense - Leiria (D. Dinis) | K40: Grupo Batalhense | N40: 244 092 862 | O40: 916 156 426 | Q40: ddinis@batalhense.com | R40: https://batalhense.com/escolas/escola-de-conducao-batalhense-leiria-d-dinis/ | S40: https://www.facebook.com/grupobatalhense | T40: https://www.instagram.com/batalhensegrupo/ | U40: 4.3 | V40: 9 | X40: Telefone/secretaria presencial; formulário de inscrição no site | Y40: Sim | Z40: Secretaria 2ª-6ª 10h-12h30 / 14h30-19h30 (2ª e 4ª até 20h); FECHADO ao sábado | AA40: 239 | AB40: A, B, C, D (grupo) | AD40: Delegação do Grupo Batalhense (multi-escola); fechada ao sábado - abordar via sede/Nova Leiria | AH40: 0 | AL40: =IF(IF(O40<>"",O40,IF(LEFT(TRIM(N40),1)="9",N40,""))="","",HYPERLINK("https://wa.me/351"&LEFT(SUBSTITUTE(SUBSTITUTE(SUBSTITUTE(IF(O40<>"",O40,IF(LEFT(TRIM(N40),1)="9",N40,""))," ",""),"+351",""),"-",""),9),"Abrir WhatsApp")) -> Abrir WhatsApp | AM40: Sem área do aluno/app no site batalhense.com; só formulário de inscrição (contacto). Aulas de código online de apoio (3ª e 5ª). | AN40: Av. Gen. Humberto Delgado, 275 - 2410-250 Leiria | AO40: https://passaprimeira.xyz/distritos-regioes/leiria/concelhos/leiria/escolas/d-dinis-00869/; https://batalhense.com/; https://batalhense.com/escolas/escola-de-conducao-batalhense-leiria-d-dinis/; https://escola-de-conducao.pt/escola-de-conducao-d-dinis-grupo-batalhense-306493.html
A41: 40 | B41: A | C41: 5.9 | D41: Novo | E41: Pedro | F41: grupo | G41: Leiria | H41: Figueiró dos Vinhos | I41: Aguda (Figueiró dos Vinhos) | J41: Escola de Condução Avenida (Type Gear II) | K41: Arte de Conduzir (segundo bomcondutor) | N41: 236 551 213 | S41: https://www.facebook.com/Ensino-em-Movimento-Esc-Condução-Avenida-255848417912117 | AA41: 224 | AD41: Volume médio (224 exames 2021); possível pertença a grupo "Arte de Conduzir" - confirmar | AH41: 0 | AL41: =IF(IF(O41<>"",O41,IF(LEFT(TRIM(N41),1)="9",N41,""))="","",HYPERLINK("https://wa.me/351"&LEFT(SUBSTITUTE(SUBSTITUTE(SUBSTITUTE(IF(O41<>"",O41,IF(LEFT(TRIM(N41),1)="9",N41,""))," ",""),"+351",""),"-",""),9),"Abrir WhatsApp")) | AN41: Rua Bombeiros Voluntários, 26 B - 3260-023 Aguda / Figueiró dos Vinhos | AO41: https://passaprimeira.xyz/distritos-regioes/leiria/concelhos/figueiro-dos-vinhos/escolas/avenida-00628/; https://www.andardemoto.pt/escolas-de-conducao/dir/d/leiria/c/figueiro-dos-vinhos/p-3485/type-gear-ii-escola-de-conducao/; https://www.bomcondutor.pt/escolas/escola/avenida-2
A42: 41 | B42: A | C42: 5.9 | D42: Novo | E42: Pedro | F42: grupo | G42: Leiria | H42: Leiria | I42: Caranguejeira | J42: Escola de Condução Rota do Sol - Caranguejeira | K42: Rota do Sol | N42: 244 732 680 | O42: 912 921 022 | Q42: escola@rotadosol.pt | R42: http://www.rotadosol.pt/ | S42: http://www.facebook.com/pages/Escola-de-Condu%C3%A7%C3%A3o-Rota-do-Sol/163704730348004 | U42: 4 | V42: 4 | X42: Telefone/presencial | Y42: Sim | Z42: 2ª-6ª 14h30-21h; Sábado 9h-13h / 14h30-18h (ABERTO sábado) | AA42: 233 | AD42: Delegação do grupo Rota do Sol (2 escolas); 233 exames 2021 | AH42: 0 | AL42: =IF(IF(O42<>"",O42,IF(LEFT(TRIM(N42),1)="9",N42,""))="","",HYPERLINK("https://wa.me/351"&LEFT(SUBSTITUTE(SUBSTITUTE(SUBSTITUTE(IF(O42<>"",O42,IF(LEFT(TRIM(N42),1)="9",N42,""))," ",""),"+351",""),"-",""),9),"Abrir WhatsApp")) -> Abrir WhatsApp | AM42: Site rotadosol.pt (2012) sem área do aluno | AN42: Rua de São Cristóvão, 16 r/c Esq. - 2420-104 Caranguejeira | AO42: https://passaprimeira.xyz/distritos-regioes/leiria/concelhos/leiria/escolas/rota-do-sol-da-caranguejeira-01114/; http://www.rotadosol.pt/; https://escola-de-conducao.pt/rota-do-sol-escola-de-conducao-306237.html; https://www.andardemoto.pt/escolas-de-conducao/dir/d/leiria/c/leiria/p-2984/escola-de-conducao-rota-do-sol/
A43: 42 | B43: A | C43: 5.9 | D43: Novo | E43: Pedro | F43: grupo | G43: Santarém | H43: Cartaxo | I43: Cartaxo | J43: Escola de Condução José Justino - Cartaxo (Matos) | K43: Nossa Senhora da Paz (Benavente, Cartaxo, Santarém) — ex-grupo Matos? | Escolas de Condução Matos (família Tomé; antigo site matosconducao.com, inativo) | N43: 243 770 072 | O43: 937 702 769 | Q43: eccartaxo@hotmail.com ; cartaxo@escolaconducao.pt | R43: https://www.escolaconducao.pt | V43: 9 | X43: Telefone/presencial | Y43: Não | Z43: Seg 10:00-13:00/14:00-19:00; Ter-Sex 10:00-13:00/14:30-19:00; Sábado encerrado (Google) | Site NS Paz: atendimento Seg-Sex 09h30-12h30/14h30-19h30 | AA43: 232 | AC43: '3 aulas por dia (9h, 14h e 19H)... demasiados alunos só para uma escola com muito poucos professores. Pouca organização' — https://escola-de-conducao.pt/matos-306352.html; 'Péssimo, desde o atendimento até as aulas' — idem | AD43: Grupo Matos + queixas de capacidade/organização de aulas; fechada ao sábado. Morada e telefone constam hoje como delegação Cartaxo da EC Nossa Senhora da Paz (escolaconducao.pt) — confirmar marca atual | AH43: 0 | AL43: =IF(IF(O43<>"",O43,IF(LEFT(TRIM(N43),1)="9",N43,""))="","",HYPERLINK("https://wa.me/351"&LEFT(SUBSTITUTE(SUBSTITUTE(SUBSTITUTE(IF(O43<>"",O43,IF(LEFT(TRIM(N43),1)="9",N43,""))," ",""),"+351",""),"-",""),9),"Abrir WhatsApp")) -> Abrir WhatsApp | AM43: Site do grupo matosconducao.com já não resolve (arquivo web 2013-2016 lista: Almeirim J. Justino, Almeirinense, Alpiarça, Azambuja, Cartaxo, Fazendas de Almeirim, Santarém Ribatejana, Pedro de Santarém) — https://web.archive.org/web/2013/http://www.matosconducao.com/matos/4567579683; nenhum portal do aluno visível | AN43: Rua Serpa Pinto nº 3/5 (3 B, 1º Dto), 2070-116 Cartaxo | AO43: https://escola-de-conducao.pt/matos-306352.html; https://escola-de-conducao.pt/jorge-manuel-alves-tome-sociedade-unipessoal-lda-307177.html; https://www.andardemoto.pt/escolas-de-conducao/dir/d/santarem/c/cartaxo/; https://www.testesdecodigogratis.com/escola-de-conducao/jose-justino/; https://www.imt-ip.pt/wp-content/uploads/2025/01/EscolasdeConducao-2021.pdf; https://www.escolaconducao.pt/contactos.html
A44: 43 | B44: A | C44: 5.9 | D44: Novo | E44: Pedro | F44: grupo | G44: Coimbra | H44: Coimbra | I44: Coimbra (Solum) | J44: Escola de Condução Solum | K44: Possível grupo Capas Negras / Quinta das Flores / Solum (não confirmado) | O44: 915 742 408 | U44: 5 | V44: 1 | Y44: Sim | Z44: Seg-Sex 10:00-13:00 / 14:00-20:00; Sábado 10:00-13:00 (aberto ao sábado) | AA44: 359 | AC44: 'escola diz ter muitos alunos para poucos carros sendo que todas as semanas me têm cancelado aulas práticas' (https://portaldaqueixa.com/brands/escola-de-conducao-solum); 6+ queixas 2025-2026 (incumprimento de aulas práticas), taxa de resposta 0% (idem) | AD44: Dor explícita e recente com cancelamento semanal de aulas práticas (Portal da Queixa 2025-26); provável grupo com Capas Negras/Quinta das Flores | AH44: 0 | AL44: =IF(IF(O44<>"",O44,IF(LEFT(TRIM(N44),1)="9",N44,""))="","",HYPERLINK("https://wa.me/351"&LEFT(SUBSTITUTE(SUBSTITUTE(SUBSTITUTE(IF(O44<>"",O44,IF(LEFT(TRIM(N44),1)="9",N44,""))," ",""),"+351",""),"-",""),9),"Abrir WhatsApp")) -> Abrir WhatsApp | AM44: Sem website identificado | AN44: C.C. Girassolum, R. João de Deus Ramos, Loja 317, 3º andar, 3030-328 Coimbra | AO44: https://escola-de-conducao.pt/escola-de-conducao-solum-306497.html; https://portaldaqueixa.com/brands/escola-de-conducao-solum; https://www.imt-ip.pt/wp-content/uploads/2025/01/EscolasdeConducao-2021.pdf
A45: 44 | B45: A | C45: 5.9 | D45: Novo | E45: Pedro | F45: grupo | G45: Aveiro | H45: Aveiro | I45: Aveiro (Vera Cruz) | J45: Escola de Condução Santos e Gamelas / IP5 | K45: Grupo IP5 | N45: 234 422 436; 234 421 323 | O45: 939 515 530 | Q45: santosegamelas@grupoip5.pt | R45: grupoip5.pt (domínio não resolve em out/2026) | S45: https://www.facebook.com/escolaconducao.egamelas | U45: 4 | V45: 12 | X45: Não divulgado online (sem plataforma de marcação visível) | Y45: Sim | Z45: Seg-Sex 10:00-12:00 e 14:00-20:00; Sábado 10:00-12:00 (aberto ao sábado de manhã) | AA45: 229 | AC45: "desligaram me na cara... Muita falta de competência" (pedido de preço por telefone, 09/2023) https://escola-de-conducao.pt/escola-de-conducao-santos-e-gamelas-306438.html; "mestres a omitir informação" (02/2023) https://escola-de-conducao.pt/escola-de-conducao-santos-e-gamelas-306438.html | AD45: Grupo IP5 com 2+ escolas em Aveiro (Santos e Gamelas/IP5 + Aveirense); queixas de atendimento telefónico; site do grupo em baixo | AH45: 0 | AL45: =IF(IF(O45<>"",O45,IF(LEFT(TRIM(N45),1)="9",N45,""))="","",HYPERLINK("https://wa.me/351"&LEFT(SUBSTITUTE(SUBSTITUTE(SUBSTITUTE(IF(O45<>"",O45,IF(LEFT(TRIM(N45),1)="9",N45,""))," ",""),"+351",""),"-",""),9),"Abrir WhatsApp")) -> Abrir WhatsApp | AM45: Site do grupo (grupoip5.pt) inacessível; sem área do aluno identificada | AN45: Rua do Magistério Primário, 20/24, 3800-212 Aveiro (Google indica Av. Nossa Sra. da Alegria 1 / Av. da Força Aérea Portuguesa 1) | AO45: https://www.bomcondutor.pt/escolas/escola/santos-gamelas-ip5; https://escola-de-conducao.pt/escola-de-conducao-santos-e-gamelas-306438.html (rating Google via snapshot escola-de-conducao.pt); https://passaprimeira.xyz/en/districts-regions/aveiro/municipalities/aveiro/schools/; https://transitoagora.pt/escolas-conducao/aveiro; https://grupoip5.pt/contactos-ip5.php
A46: 45 | B46: A | C46: 5.8 | D46: Novo | E46: Pedro | F46: grupo | G46: Leiria | H46: Alcobaça | I46: Alcobaça | J46: Escola de Condução Batalhense - Alcobaça | K46: Grupo Batalhense | N46: 262 596 700 | O46: 918 782 384 | Q46: alcobaca@batalhense.com | R46: https://batalhense.com/escolas/escola-de-conducao-batalhense-alcobaca/ | S46: https://www.facebook.com/pages/Escola-de-Condução-Batalhense-de-Alcobaça/102711916581909 | T46: https://www.instagram.com/batalhensegrupo/ | U46: 4 | V46: 4 | X46: Telefone/secretaria presencial; formulário de inscrição no site | Y46: Sim | Z46: Secretaria 2ª-6ª 9h30-12h30 / 14h30-20h; Sábado 9h30-12h30 (ABERTO sábado, segundo site) | AA46: 204 | AB46: A, B, C, D (grupo) | AD46: Grupo Batalhense (multi-escola); 204 exames 2021 | AH46: 0 | AL46: =IF(IF(O46<>"",O46,IF(LEFT(TRIM(N46),1)="9",N46,""))="","",HYPERLINK("https://wa.me/351"&LEFT(SUBSTITUTE(SUBSTITUTE(SUBSTITUTE(IF(O46<>"",O46,IF(LEFT(TRIM(N46),1)="9",N46,""))," ",""),"+351",""),"-",""),9),"Abrir WhatsApp")) -> Abrir WhatsApp | AM46: Sem área do aluno/app no site batalhense.com; só formulário de inscrição (contacto). Aulas de código online de apoio (3ª e 5ª). | AN46: R. Mercedes e Carlos Campeão, 10 - 2460-067 Alcobaça | AO46: https://passaprimeira.xyz/distritos-regioes/leiria/concelhos/alcobaca/escolas/batalhense-alcobaca-00961/; https://batalhense.com/; https://batalhense.com/escolas/escola-de-conducao-batalhense-alcobaca/; https://escola-de-conducao.pt/escola-de-conducao-batalhense-de-alcobaca-306032.html
A47: 46 | B47: A | C47: 5.8 | D47: Novo | E47: Pedro | F47: grupo | G47: Lisboa | H47: Lourinhã | I47: Lourinhã | J47: Escola de Condução A. Figueiredo (MegaDriving) | K47: MegaDriving | N47: 261 422 133 | O47: 968 629 234 | Q47: afigueiro.ec@gmail.com | R47: https://www.megadriving.com.pt/ec_a_figueiredo.php | S47: https://www.facebook.com/MegaDrivingEC/ | U47: 4.8 | V47: 12 | X47: Presencial/telefone; sem marcação online visível | Y47: Sim | Z47: Secretaria 2ª-6ª 10h-13h e 15h-20h; Sábado 10h-13h (ABERTO sábado de manhã) | AA47: 209 | AD47: Delegação do grupo MegaDriving | AH47: 0 | AL47: =IF(IF(O47<>"",O47,IF(LEFT(TRIM(N47),1)="9",N47,""))="","",HYPERLINK("https://wa.me/351"&LEFT(SUBSTITUTE(SUBSTITUTE(SUBSTITUTE(IF(O47<>"",O47,IF(LEFT(TRIM(N47),1)="9",N47,""))," ",""),"+351",""),"-",""),9),"Abrir WhatsApp")) -> Abrir WhatsApp | AM47: Site do grupo (megadriving.com.pt) só tem formulário de contacto e página de inscrição; sem área do aluno nem links para AGEOnline/BDrive/ALSIS | AN47: Avenida de Angola, nº 63, 2530-114 Lourinhã | AO47: https://www.megadriving.com.pt/ec_a_figueiredo.php; https://passaprimeira.xyz/distritos-regioes/lisboa/concelhos/lourinha/escolas/; https://www.imt-ip.pt/wp-content/uploads/2025/01/EscolasdeConducao-2021.pdf; https://escola-de-conducao.pt/escola-de-conducao-a-figueiredo-306514.html
A48: 47 | B48: A | C48: 5.8 | D48: Novo | E48: Pedro | F48: grupo | G48: Lisboa | H48: Torres Vedras | I48: Campelos | J48: Escola de Condução Campelos (MegaDriving) | K48: MegaDriving | N48: 261 437 654 | O48: 925 860 038 | Q48: campelos.ec@gmail.com | R48: https://www.megadriving.com.pt/ec_campelos.php | S48: https://www.facebook.com/MegaDrivingEC/ | X48: Presencial/telefone; sem marcação online visível | Y48: Sim | Z48: Secretaria 2ª-6ª 10h-13h e 15h-20h; Sábado 10h-13h (ABERTO sábado de manhã) | AA48: 194 | AD48: Delegação do grupo MegaDriving. Mesmo telefone da 'EC Virtual' (Rua da Cruz 37, Campelos) do bomcondutor e da 'Forming People Lda.' (R. Francisco Antunes 1, Campelos) -> mesma escola, não duplicar | AH48: 0 | AL48: =IF(IF(O48<>"",O48,IF(LEFT(TRIM(N48),1)="9",N48,""))="","",HYPERLINK("https://wa.me/351"&LEFT(SUBSTITUTE(SUBSTITUTE(SUBSTITUTE(IF(O48<>"",O48,IF(LEFT(TRIM(N48),1)="9",N48,""))," ",""),"+351",""),"-",""),9),"Abrir WhatsApp")) -> Abrir WhatsApp | AM48: Site do grupo (megadriving.com.pt) só tem formulário de contacto e página de inscrição; sem área do aluno nem links para AGEOnline/BDrive/ALSIS | AN48: Rua das Malhadinhas, 1, 2565-037 Campelos | AO48: https://www.megadriving.com.pt/ec_campelos.php; https://passaprimeira.xyz/distritos-regioes/lisboa/concelhos/torres-vedras/escolas/; https://www.imt-ip.pt/wp-content/uploads/2025/01/EscolasdeConducao-2021.pdf; https://www.bomcondutor.pt/escolas/escola/virtual; https://portalnacional.com.pt/lisboa/torres-vedras/empresas/ensino/escolas-de-conducao/
A49: 48 | B49: A | C49: 5.8 | D49: Novo | E49: Pedro | F49: grupo | G49: Lisboa | H49: Alenquer | I49: Aldeia Galega da Merceana | J49: Escola de Condução Montejunto (MegaDriving) | K49: MegaDriving | N49: 263 769 259 | O49: 961 655 579 | Q49: montejunto.ec@gmail.com | R49: https://www.megadriving.com.pt/ec_montejunto.php | S49: https://www.facebook.com/MegaDrivingEC/ | X49: Presencial/telefone; sem marcação online visível | Y49: Sim | Z49: Secretaria 2ª-6ª 10h-13h e 15h-20h; Sábado 10h-13h (ABERTO sábado de manhã) | AA49: 207 | AD49: Delegação do grupo MegaDriving | AH49: 0 | AL49: =IF(IF(O49<>"",O49,IF(LEFT(TRIM(N49),1)="9",N49,""))="","",HYPERLINK("https://wa.me/351"&LEFT(SUBSTITUTE(SUBSTITUTE(SUBSTITUTE(IF(O49<>"",O49,IF(LEFT(TRIM(N49),1)="9",N49,""))," ",""),"+351",""),"-",""),9),"Abrir WhatsApp")) -> Abrir WhatsApp | AM49: Site do grupo (megadriving.com.pt) só tem formulário de contacto e página de inscrição; sem área do aluno nem links para AGEOnline/BDrive/ALSIS | AN49: Rua 25 de Abril, nº 33 A, 2580-087 Merceana | AO49: https://www.megadriving.com.pt/ec_montejunto.php; https://passaprimeira.xyz/distritos-regioes/lisboa/concelhos/alenquer/escolas/; https://www.imt-ip.pt/wp-content/uploads/2025/01/EscolasdeConducao-2021.pdf
A50: 49 | B50: A | C50: 5.8 | D50: Novo | E50: Pedro | F50: grupo | G50: Coimbra | H50: Cantanhede | I50: Cantanhede | J50: Escola de Condução Marialvas | K50: Grupo MAO (Febres + Marialvas/Cantanhede) | N50: 231 411 433 | O50: 918 106 087 | Q50: cantanhede@grupomao.com | R50: http://www.grupomao.com/ | S50: https://www.facebook.com/ecmarialva/ | X50: Telefone/presencial | AA50: 462 | AD50: Grupo multi-site (Grupo MAO: Marialvas + Febres), 462 provas 2021, site desatualizado | AH50: 0 | AL50: =IF(IF(O50<>"",O50,IF(LEFT(TRIM(N50),1)="9",N50,""))="","",HYPERLINK("https://wa.me/351"&LEFT(SUBSTITUTE(SUBSTITUTE(SUBSTITUTE(IF(O50<>"",O50,IF(LEFT(TRIM(N50),1)="9",N50,""))," ",""),"+351",""),"-",""),9),"Abrir WhatsApp")) -> Abrir WhatsApp | AM50: Site grupomao.com é animação Hype antiga, sem área de aluno | AN50: Rua Luís de Camões, 26, Loja 2, 3060-183 Cantanhede | AO50: https://www.andardemoto.pt/escolas-de-conducao/dir/d/coimbra/c/cantanhede/p-2822/escola-de-conducao-marialvas/; http://www.grupomao.com/; https://escola-de-conducao.pt/maia-filhos-lda-307207.html; https://www.imt-ip.pt/wp-content/uploads/2025/01/EscolasdeConducao-2021.pdf
A51: 50 | B51: A | C51: 5.7 | D51: Novo | E51: Pedro | F51: grupo | G51: Viseu | H51: Lamego | I51: Lamego | J51: Escola de Condução Lamego | K51: Grupo AFMG (EC Lamego + EC M.G. Tarouca + EC DS Armamar) | N51: 254655920 | O51: 933854921 | S51: https://www.facebook.com/lamego.ec | U51: 4/5 (escola-de-conducao.pt, proxy) | V51: 8 | X51: Telefone/presencial (sem plataforma online encontrada) | Y51: Sim | Z51: Seg-Sex 9h30-13h e 15h-19h30; Sáb 9h-12h; Dom fechado | AA51: 546 | AC51: Avaliação 1/5 sem texto (escola-de-conducao.pt, 26/10/2023) - https://escola-de-conducao.pt/escola-de-conducao-lamego-306445.html; Portal da Queixa: sem página de marca encontrada | AD51: Grupo multi-site (AFMG: Lamego, Tarouca, Armamar) + volume >400 exames em 2021 + FB ativo (4343 seguidores, posts #grupoafmg) sem app própria | AH51: 0 | AL51: =IF(IF(O51<>"",O51,IF(LEFT(TRIM(N51),1)="9",N51,""))="","",HYPERLINK("https://wa.me/351"&LEFT(SUBSTITUTE(SUBSTITUTE(SUBSTITUTE(IF(O51<>"",O51,IF(LEFT(TRIM(N51),1)="9",N51,""))," ",""),"+351",""),"-",""),9),"Abrir WhatsApp")) -> Abrir WhatsApp | AN51: Rua Dr. Bernardo Pinheiro de Aragão, nº7 Cave, 5100-118 Lamego | AO51: https://www.facebook.com/lamego.ec; https://escola-de-conducao.pt/escola-de-conducao-lamego-306445.html; https://www.facebook.com/people/Afmg-Escolas-DE-Condu%C3%A7%C3%A3o/100077324387281/; https://www.facebook.com/afmgescolasconducao/; https://www.andardemoto.pt/escolas-de-conducao/dir/d/viseu/c/lamego/p-3223/lamego/
A52: 51 | B52: A | C52: 5.6 | D52: Novo | E52: Pedro | F52: grupo | G52: Coimbra | H52: Penacova | I52: Penacova | J52: Escola de Condução Penacova (Rota da Estrela) | K52: Grupo Rota da Estrela (Arganil, Penacova, Tábua + Seia/Nelas/Viseu/Tondela/Gouveia fora do distrito) | N52: 239 478 765; 239 476 012 | Q52: penacova@rotadaestrela.pt | R52: www.rotadaestrela.pt (domínio não resolve) | S52: https://www.facebook.com/pages/category/Local-Business/Escola-de-condu%C3%A7%C3%A3o-Penacova-578809955516068/ | U52: 2.3 | V52: 3 | AA52: 138 | AD52: Delegação de grupo multi-site (Rota da Estrela, ~3 escolas no distrito e mais no distrito de Viseu/Guarda); rating Google baixo | AH52: 0 | AL52: =IF(IF(O52<>"",O52,IF(LEFT(TRIM(N52),1)="9",N52,""))="","",HYPERLINK("https://wa.me/351"&LEFT(SUBSTITUTE(SUBSTITUTE(SUBSTITUTE(IF(O52<>"",O52,IF(LEFT(TRIM(N52),1)="9",N52,""))," ",""),"+351",""),"-",""),9),"Abrir WhatsApp")) | AM52: Site do grupo em baixo | AN52: Rua de São João, 25, 3360-191 Penacova | AO52: https://www.andardemoto.pt/escolas-de-conducao/dir/d/coimbra/c/penacova/p-3324/penacova/; https://escola-de-conducao.pt/escola-de-conducao-penacova-305917.html; https://www.imt-ip.pt/wp-content/uploads/2025/01/EscolasdeConducao-2021.pdf
A53: 52 | B53: A | C53: 5.6 | D53: Novo | E53: Pedro | F53: grupo | G53: Viseu | H53: Santa Comba Dão | I53: Santa Comba Dão | J53: Escola de Condução 'do Emigrante' | K53: Grupo Emigrante | N53: 232890090; 232880210 | O53: 919311337; 919312427 | Q53: geral@ec-emigrante.com | R53: https://www.ec-emigrante.com/ | S53: https://www.facebook.com/ecemigrante/ | T53: https://www.instagram.com/ecemigrante/ | U53: 4 | V53: 15 | X53: Pré-inscrição online; restante por telefone | Y53: Sim | Z53: Seg-Sex 9h-12h e 14h-19h; Sáb 9h-12h | AA53: 267 | AB53: A1, A2, A, B, BE, C, CE, D; CAM/ADR/máquinas | AC53: Não atendem o telefone: 'Estou a ligar para lá a 2 dias e ninguém atende' (2024); 'A 3dias que ligo, envio email, mensagem no Messeger e ninguém responde' (2023) https://escola-de-conducao.pt/escola-de-conducao-do-emigrante-306281.html | AD53: Sinais de dor (falta de resposta por telefone/email/Messenger); assina 'Grupo Emigrante' (histórico também em Mortágua) | AH53: 0 | AL53: =IF(IF(O53<>"",O53,IF(LEFT(TRIM(N53),1)="9",N53,""))="","",HYPERLINK("https://wa.me/351"&LEFT(SUBSTITUTE(SUBSTITUTE(SUBSTITUTE(IF(O53<>"",O53,IF(LEFT(TRIM(N53),1)="9",N53,""))," ",""),"+351",""),"-",""),9),"Abrir WhatsApp")) -> Abrir WhatsApp | AM53: Site WordPress com formulário de pré-inscrição; sem área do aluno/app | AN53: Edifício Nova Estrela, Av. Dr. Sá Carneiro 5, 3440-324 Santa Comba Dão (IMT: Av. Gen. Humberto Delgado 8) | AO53: https://www.ec-emigrante.com/; https://escola-de-conducao.pt/escola-de-conducao-do-emigrante-306281.html; https://passaprimeira.xyz/distritos-regioes/viseu/concelhos/santa-comba-dao/escolas/emigrante-00545/; https://www.bomcondutor.pt/escolas/escola/do-emigrante; https://www.facebook.com/ecemigrante/
A54: 53 | B54: A | C54: 5.5 | D54: Novo | E54: Pedro | F54: grupo | G54: Lisboa | H54: Cadaval | I54: Painho | J54: Escola de Condução Duarte (MegaDriving) | K54: MegaDriving | N54: 262 741 169 | O54: 968 579 670 | Q54: escolaconducaoduarte@gmail.com | R54: https://www.megadriving.com.pt/ec_duarte.php | S54: https://www.facebook.com/MegaDrivingEC/ | U54: 4.7 | V54: 3 | X54: Presencial/telefone; sem marcação online visível | Y54: Sim | Z54: Secretaria 2ª-6ª 15h-20h; Sábado 10h-13h (ABERTO sábado de manhã) | AA54: 131 | AD54: Delegação do grupo MegaDriving (decisão provavelmente centralizada); escola pequena | AH54: 0 | AL54: =IF(IF(O54<>"",O54,IF(LEFT(TRIM(N54),1)="9",N54,""))="","",HYPERLINK("https://wa.me/351"&LEFT(SUBSTITUTE(SUBSTITUTE(SUBSTITUTE(IF(O54<>"",O54,IF(LEFT(TRIM(N54),1)="9",N54,""))," ",""),"+351",""),"-",""),9),"Abrir WhatsApp")) -> Abrir WhatsApp | AM54: Site do grupo (megadriving.com.pt) só tem formulário de contacto e página de inscrição; sem área do aluno nem links para AGEOnline/BDrive/ALSIS | AN54: Rua Prof. Marcelo Caetano, nº 15 R/C, 2550-429 Painho - Cadaval | AO54: https://www.megadriving.com.pt/ec_duarte.php; https://passaprimeira.xyz/distritos-regioes/lisboa/concelhos/cadaval/escolas/; https://www.imt-ip.pt/wp-content/uploads/2025/01/EscolasdeConducao-2021.pdf; https://escola-de-conducao.pt/escola-conducao-duarte-306036.html
A55: 54 | B55: A | C55: 5.5 | D55: Novo | E55: Pedro | F55: grupo | G55: Coimbra | H55: Coimbra | I55: Coimbra (Pedrulha) | J55: Escola de Condução Académica | K55: Grupo MGA (Escolas MGA, desde 1971) - 5 escolas no distrito | N55: 239 495 492 | O55: 961 448 306 | Q55: geral@escolasmga.pt | R55: https://escolasmga.pt/escolas-de-conducao/coimbra-academica/ | S55: https://www.facebook.com/escolasgrupomga | U55: 3 | V55: 2 | W55: BDrive | X55: Secretaria/telefone; BDrive para alunos registados | Y55: Sim | Z55: Seg-Sex 09:00-12:00 / 14:00-19:00; Sábado 09:00-12:00 (aberto ao sábado) | AA55: 134 | AB55: A, A1, A2, B1, B, B automático, BE, C, C1, CE, D, D1, DE, T, veículos adaptados; CAM | AD55: Parte do Grupo MGA (multi-site); abordar via sede do grupo (Oliveira do Hospital) | AH55: 0 | AL55: =IF(IF(O55<>"",O55,IF(LEFT(TRIM(N55),1)="9",N55,""))="","",HYPERLINK("https://wa.me/351"&LEFT(SUBSTITUTE(SUBSTITUTE(SUBSTITUTE(IF(O55<>"",O55,IF(LEFT(TRIM(N55),1)="9",N55,""))," ",""),"+351",""),"-",""),9),"Abrir WhatsApp")) -> Abrir WhatsApp | AM55: https://escolasmga.pt/servicos/plataforma-bdrive/ (link para bdrive.pt, 'Acesso exclusivo a instruendos registados'); também 'Plataforma de Testes' e 'Pré-inscrição Online' | AN55: Urbanização da Pedrulha, Lote 24 R/C, Sala 1 e 2, 3025-248 Coimbra | AO55: https://escolasmga.pt/escolas-de-conducao/; https://escola-de-conducao.pt/escola-de-conducao-academica-grupo-mga-desde-1971-305918.html; https://www.bomcondutor.pt/escolas/escola/academica-coimbra; https://www.andardemoto.pt/escolas-de-conducao/dir/d/coimbra/c/coimbra/p-2060/academica/; https://www.imt-ip.pt/wp-content/uploads/2025/01/EscolasdeConducao-2021.pdf
A56: 55 | B56: A | C56: 5.4 | D56: Novo | E56: Pedro | F56: telefone | G56: Leiria | H56: Leiria | I56: Leiria | J56: Escola de Condução Morais (Entreguias) | N56: 244 823 983 | S56: https://www.facebook.com/pages/Escola-Condução-Morais/470142536415608 | U56: 4 | V56: 21 | X56: Telefone/presencial | Y56: Sim | Z56: 2ª-6ª 10h-19h30; FECHADO ao sábado (Google) | AA56: 474 | AC56: "Marcar aulas é uma tarefa quase impossível... estão sempre a desmarcar. Comunicação e assertividade péssimas" (Google 1★, 11/2021) https://escola-de-conducao.pt/escola-de-conducao-morais-306562.html; "Agendar aulas era muito complicado com eles, a disponibilidade era muito pouca" (Google 1★, 10/2022) https://escola-de-conducao.pt/escola-de-conducao-morais-306562.html | AD56: Dor explícita em marcação/desmarcação de aulas e comunicação; volume alto (474 exames 2021). Nota: fechada ao sábado | AH56: 0 | AL56: =IF(IF(O56<>"",O56,IF(LEFT(TRIM(N56),1)="9",N56,""))="","",HYPERLINK("https://wa.me/351"&LEFT(SUBSTITUTE(SUBSTITUTE(SUBSTITUTE(IF(O56<>"",O56,IF(LEFT(TRIM(N56),1)="9",N56,""))," ",""),"+351",""),"-",""),9),"Abrir WhatsApp")) | AN56: Av. dos Combatentes da Grande Guerra, 48, Edf. Lena, 2º Piso - 2400-122 Leiria | AO56: https://passaprimeira.xyz/distritos-regioes/leiria/concelhos/leiria/escolas/morais-00336/; https://escola-de-conducao.pt/escola-de-conducao-morais-306562.html; https://www.bomcondutor.pt/escolas/escola/morais; https://www.andardemoto.pt/escolas-de-conducao/dir/d/leiria/c/leiria/p-2315/entreguias/
A57: 56 | B57: A | C57: 5.4 | D57: Novo | E57: Pedro | F57: grupo | G57: Leiria | H57: Caldas da Rainha | I57: Caldas da Rainha | J57: Escola de Condução Motoschool | K57: Grupo Letra | N57: 262 097 008 / 262 929 464 | P57: yes (262 097 008) | Q57: geral@motoschool.pt | R57: https://www.motoschool.pt/ | S57: https://www.facebook.com/motooschool | T57: https://www.instagram.com/motoschool_oficial/ | X57: Telefone/WhatsApp/presencial | Y57: Sim | Z57: 2ª-6ª 10h-13h / 14h30-19h; sábado não indicado | AA57: 89 | AB57: AM, A1, A2, A, B | AD57: Grupo Letra; escola jovem e orientada para redes sociais (Instagram, WhatsApp, eventos) | AH57: 0 | AL57: =IF(IF(O57<>"",O57,IF(LEFT(TRIM(N57),1)="9",N57,""))="","",HYPERLINK("https://wa.me/351"&LEFT(SUBSTITUTE(SUBSTITUTE(SUBSTITUTE(IF(O57<>"",O57,IF(LEFT(TRIM(N57),1)="9",N57,""))," ",""),"+351",""),"-",""),9),"Abrir WhatsApp")) | AM57: Site Webnode com "Calendário", "Ensino à distância" (e-learning Segurança Rodoviária) e loja online; sem área do aluno | AN57: Rua Capitão Filipe de Sousa, 130A - 2500-140 Caldas da Rainha | AO57: https://passaprimeira.xyz/distritos-regioes/leiria/concelhos/caldas-da-rainha/escolas/motoschool-01418/; https://www.motoschool.pt/contacto-moto-school/; https://grupoletra.pt/nova-caldense/
A58: 57 | B58: A | C58: 5.4 | D58: Novo | E58: Pedro | F58: telefone | G58: Santarém | H58: Entroncamento | I58: Entroncamento | J58: Escola de Condução do Entroncamento (Oliveira, Santos & Aguiar, Lda.) | N58: 249 726 672 | O58: 965 190 393 / 966 021 659 | Q58: escconducaoentroncamento@iol.pt (antigo, não confirmado) | U58: 4.2 | V58: 14 | X58: Presencial/telefone | Y58: Sim | Z58: Seg-Sex 10:00-13:00 e 15:00-19:00; Sábado 11:00-12:00 (ABERTO sábado, só 1 hora) | AA58: 606 | AC58: 'por duas vezes que lá vou não consegui ser atendida... estive mais de meia hora à espera para ser atendida' (1/5, nov 2023) - https://escola-de-conducao.pt/escola-de-conducao-do-entroncamento-306537.html; 'demora muito para poder obter a carta' (3/5, mar 2024) - mesma fonte | AD58: Maior volume da zona (606 exames 2021) + queixas de espera/atendimento na secretaria; 'escola mais antiga do Entroncamento'. | AH58: 0 | AL58: =IF(IF(O58<>"",O58,IF(LEFT(TRIM(N58),1)="9",N58,""))="","",HYPERLINK("https://wa.me/351"&LEFT(SUBSTITUTE(SUBSTITUTE(SUBSTITUTE(IF(O58<>"",O58,IF(LEFT(TRIM(N58),1)="9",N58,""))," ",""),"+351",""),"-",""),9),"Abrir WhatsApp")) -> Abrir WhatsApp | AN58: Rua Almirante Reis, 44 - 1º Esq., 2330-099 Entroncamento | AO58: https://escola-de-conducao.pt/escola-de-conducao-do-entroncamento-306537.html; https://www.racius.com/escola-de-conducao-do-entroncamento-de-oliveira-santos-aguiar-lda/; https://www.testesdecodigogratis.com/escola-de-conducao/entroncamento/; https://www.andardemoto.pt/escolas-de-conducao/dir/d/santarem/c/entroncamento/p-2645/escola-de-conducao-do-entroncamento-de-oliveira-santos-aguiar/; https://www.imt-ip.pt/wp-content/uploads/2025/01/EscolasdeConducao-2021.pdf
A59: 58 | B59: A | C59: 5.4 | D59: Novo | E59: Pedro | F59: telefone | G59: Lisboa | H59: Torres Vedras | I59: A-dos-Cunhados | J59: Escola de Condução da Vila (A-dos-Cunhados) | N59: 261 981 215 | R59: https://www.escoladeconducaodavila.com/ | U59: 2.5 | V59: 2 | X59: Presencial/telefone; formulário de contacto no site | Y59: Sim | Z59: 2ª-6ª 10h-20h; Sábado 10h-13h (ABERTO sábado de manhã) - Google | AA59: 224 | AC59: 'Não sei o motivo de colocar um número de telemóvel se nunca atendem.' (Google, 2023) - https://escola-de-conducao.pt/escola-de-conducao-da-vila-lda-305991.html | AD59: Sinal de dor (não atendem o telefone); escola pequena com 2 instrutores | AH59: 0 | AL59: =IF(IF(O59<>"",O59,IF(LEFT(TRIM(N59),1)="9",N59,""))="","",HYPERLINK("https://wa.me/351"&LEFT(SUBSTITUTE(SUBSTITUTE(SUBSTITUTE(IF(O59<>"",O59,IF(LEFT(TRIM(N59),1)="9",N59,""))," ",""),"+351",""),"-",""),9),"Abrir WhatsApp")) | AM59: Site institucional simples (2014), sem área do aluno | AN59: Rua Monsenhor José Jorge Fialho, Edifício Azenha, Fração A, Loja R/C, 2560-027 A-dos-Cunhados | AO59: https://www.escoladeconducaodavila.com/contatos; https://escola-de-conducao.pt/escola-de-conducao-da-vila-lda-305991.html; https://passaprimeira.xyz/distritos-regioes/lisboa/concelhos/torres-vedras/escolas/; https://www.imt-ip.pt/wp-content/uploads/2025/01/EscolasdeConducao-2021.pdf
A60: 59 | B60: A | C60: 5.4 | D60: Novo | E60: Pedro | F60: grupo | G60: Aveiro | H60: Oliveira do Bairro | I60: Oiã | J60: Escola de Condução de Oiã | K60: Escolas Miguel Silva | N60: 234 723 927 | O60: 968 426 437 / 968 426 438 | Q60: ecms.oia@gmail.com | R60: https://escolasmiguelsilva.pt/contact-oia/ | S60: https://www.facebook.com/escolas.miguel.silva/ | T60: https://www.instagram.com/escolas.miguel.silva/ | U60: 3.8 | V60: 5 | X60: Telefone/presencial (sem marcação online visível) | Y60: Não | Z60: Seg 09:30–19:00 Ter 09:30–19:00 Qua 09:30–19:00 Qui 09:30–19:00 Sex 09:30–19:00 SÁB 09:00–12:30 Dom Encerrado — aberto sábado de manhã | AA60: 109 | AC60: "No inicio sentia que não estavam a entender que realmente eu tinha urgência em começar a avançar com as aulas" (4★, 18/05/2022) https://escola-de-conducao.pt/escola-de-conducao-oia-escolas-miguel-silva-306275.html | AD60: Grupo multi-sede Escolas Miguel Silva; queixa sobre ritmo de marcação de aulas | AH60: 0 | AL60: =IF(IF(O60<>"",O60,IF(LEFT(TRIM(N60),1)="9",N60,""))="","",HYPERLINK("https://wa.me/351"&LEFT(SUBSTITUTE(SUBSTITUTE(SUBSTITUTE(IF(O60<>"",O60,IF(LEFT(TRIM(N60),1)="9",N60,""))," ",""),"+351",""),"-",""),9),"Abrir WhatsApp")) -> Abrir WhatsApp | AM60: Site WordPress do grupo só com contactos; sem área do aluno, e-learning ou link de software visível | AN60: Rua Eng. Agnelo Prazeres nº 45 r/c, 3770-059 Oiã | AO60: https://escolasmiguelsilva.pt/contact-oia/; https://escola-de-conducao.pt/escola-de-conducao-oia-escolas-miguel-silva-306275.html; https://passaprimeira.xyz/en/districts-regions/aveiro/municipalities/oliveira-do-bairro/schools/; https://www.bomcondutor.pt/escolas/escola/oia
A61: 60 | B61: A | C61: 5.4 | D61: Novo | E61: Pedro | F61: grupo | G61: Viseu | H61: Mangualde | I61: Mangualde | J61: Escola de Condução Arede (Isabel & Arede) – Mangualde (alvará IMT 100 'Azurara') | K61: Isabel & Arede Escolas de Condução (Mangualde, Nelas, Tábua, Fornos de Algodres) | N61: 232623217 | O61: 911025443 | S61: https://www.facebook.com/isabelaredeec/ | T61: https://www.instagram.com/escoladeconducaoarede/ | X61: Desconhecido | AA61: 589 | AD61: Grupo multi-sede (4 escolas: Mangualde sede, Nelas, Tábua, Fornos de Algodres); maior volume da zona (589 provas 2021); Instagram com ~4.050 seguidores | AH61: 0 | AL61: =IF(IF(O61<>"",O61,IF(LEFT(TRIM(N61),1)="9",N61,""))="","",HYPERLINK("https://wa.me/351"&LEFT(SUBSTITUTE(SUBSTITUTE(SUBSTITUTE(IF(O61<>"",O61,IF(LEFT(TRIM(N61),1)="9",N61,""))," ",""),"+351",""),"-",""),9),"Abrir WhatsApp")) -> Abrir WhatsApp | AM61: Sem website próprio encontrado; sem evidência de área do aluno/app | AN61: Largo do Rossio 52, 3530-133 Mangualde | AO61: https://passaprimeira.xyz/distritos-regioes/viseu/concelhos/mangualde/escolas/azurara-00100/; https://www.bomcondutor.pt/escolas/escola/azurara/; https://maisbeiras.sapo.pt/isabelarede-escolas-de-conducao-em-fornos-de-algodres; https://www.testesdecodigogratis.com/escola-de-conducao/arede/; https://www.instagram.com/escoladeconducaoarede/; https://www.facebook.com/isabelaredeec/; https://www.amarelas.pt/c/mangualde-isabel-arede-escola-de-conducao-lda-158742
A62: 61 | B62: A | C62: 5.2 | D62: Novo | E62: Pedro | F62: grupo | G62: Leiria | H62: Pedrógão Grande | I62: Pedrógão Grande | J62: Escola de Condução Pedroguense | K62: Escolas Castanheirense / Figueiroense / Pedroguense | O62: 962 077 383 / 961 533 250 | Q62: ecpedroguense@gmail.com | R62: https://www.escolaconducaocastanheirense.pt/ | X62: Telefone; pré-inscrição online | Y62: Sim | Z62: 2ª-6ª 7h-21h; Sábado 9h-13h (ABERTO sábado) | AA62: 45 | AD62: Grupo de 3 escolas (interior norte do distrito, volume baixo - Castanheirense 16, Figueiroense 17, Pedroguense 45 exames 2021); decisão única para 3 sites | AH62: 0 | AL62: =IF(IF(O62<>"",O62,IF(LEFT(TRIM(N62),1)="9",N62,""))="","",HYPERLINK("https://wa.me/351"&LEFT(SUBSTITUTE(SUBSTITUTE(SUBSTITUTE(IF(O62<>"",O62,IF(LEFT(TRIM(N62),1)="9",N62,""))," ",""),"+351",""),"-",""),9),"Abrir WhatsApp")) -> Abrir WhatsApp | AM62: Site comum (escolaconducaocastanheirense.pt) com menu "Área do Aluno" que só leva a testes/simuladores e impressos IMT - sem marcação online | AN62: Urbanização Valbom, Lote 2, sub Cave A/B - 3270-162 Pedrógão Grande | AO62: https://passaprimeira.xyz/distritos-regioes/leiria/concelhos/pedrogao-grande/escolas/pedroguense-00560/; https://www.escolaconducaocastanheirense.pt/contactos/; https://escola-de-conducao.pt/escola-de-conducao-pedroguense-306837.html
A63: 62 | B63: A | C63: 5.2 | D63: Novo | E63: Pedro | F63: telefone | G63: Lisboa | H63: Torres Vedras | I63: Torres Vedras | J63: Escola de Condução Instromóvel (OKCondutor) | N63: 261 316 028; 261 316 814 | O63: 914 097 671 | U63: 2.7 | V63: 45 | X63: Secretaria/telefone; reviews relatam grande dificuldade em marcar aulas e aulas desmarcadas de véspera | Y63: Sim | Z63: 2ª-6ª 10h-20h (Google); sábado não confirmado | AA63: 187 | AC63: 'Dificuldade gigante em marcar aulas!' (Google, 2023); 'desmarcam inúmeras aulas de véspera ... Há erros na secretaria a marcar exames e provavelmente também as aulas' (Google, 2022); 'a nível de secretariado muito fraco' (Google, 2022); 'A escola não tem organização' (Google, 2020) - https://escola-de-conducao.pt/okcondutor-instromovel-escola-de-conducao-305993.html | AD63: Forte evidência de dor em marcação/cancelamentos/secretaria | AH63: 0 | AL63: =IF(IF(O63<>"",O63,IF(LEFT(TRIM(N63),1)="9",N63,""))="","",HYPERLINK("https://wa.me/351"&LEFT(SUBSTITUTE(SUBSTITUTE(SUBSTITUTE(IF(O63<>"",O63,IF(LEFT(TRIM(N63),1)="9",N63,""))," ",""),"+351",""),"-",""),9),"Abrir WhatsApp")) -> Abrir WhatsApp | AN63: Várzea do Choupal, Edifício Choupal R/C Esq., Corpo C, 2560-230 Torres Vedras | AO63: https://escola-de-conducao.pt/okcondutor-instromovel-escola-de-conducao-305993.html; https://www.municipiosefreguesias.pt/entidade/166725/escola-de-conducao-instromovel-lda--torres-vedras; https://passaprimeira.xyz/distritos-regioes/lisboa/concelhos/torres-vedras/escolas/; https://www.imt-ip.pt/wp-content/uploads/2025/01/EscolasdeConducao-2021.pdf
A64: 63 | B64: A | C64: 5.1 | D64: Novo | E64: Pedro | F64: grupo | G64: Leiria | H64: Castanheira de Pera | I64: Castanheira de Pêra | J64: Escola de Condução Castanheirense | K64: Escolas Castanheirense / Figueiroense / Pedroguense | O64: 962 077 383 / 961 533 250 | Q64: eccastanheirense@gmail.com | R64: https://www.escolaconducaocastanheirense.pt/ | U64: 5 | V64: 1 | X64: Telefone; pré-inscrição online | Y64: Sim | Z64: 2ª-6ª 7h-21h; Sábado 9h-13h (ABERTO sábado) | AA64: 16 | AD64: Grupo de 3 escolas (interior norte do distrito, volume baixo - Castanheirense 16, Figueiroense 17, Pedroguense 45 exames 2021); decisão única para 3 sites | AH64: 0 | AL64: =IF(IF(O64<>"",O64,IF(LEFT(TRIM(N64),1)="9",N64,""))="","",HYPERLINK("https://wa.me/351"&LEFT(SUBSTITUTE(SUBSTITUTE(SUBSTITUTE(IF(O64<>"",O64,IF(LEFT(TRIM(N64),1)="9",N64,""))," ",""),"+351",""),"-",""),9),"Abrir WhatsApp")) -> Abrir WhatsApp | AM64: Site comum (escolaconducaocastanheirense.pt) com menu "Área do Aluno" que só leva a testes/simuladores e impressos IMT - sem marcação online | AN64: Avenida São Domingos, 51, 1.º - 3280-013 Castanheira de Pêra | AO64: https://passaprimeira.xyz/distritos-regioes/leiria/concelhos/castanheira-de-pera/escolas/castanheirense-00213/; https://www.escolaconducaocastanheirense.pt/contactos/; https://escola-de-conducao.pt/escola-de-conducao-castanheirense-306231.html
A65: 64 | B65: A | C65: 5.1 | D65: Novo | E65: Pedro | F65: grupo | G65: Leiria | H65: Figueiró dos Vinhos | I65: Figueiró dos Vinhos | J65: Escola de Condução Figueiroense | K65: Escolas Castanheirense / Figueiroense / Pedroguense | O65: 962 077 383 / 961 533 250 | Q65: ecfigueiroense@gmail.com | R65: https://www.escolaconducaocastanheirense.pt/ | X65: Telefone; pré-inscrição online | Y65: Sim | Z65: 2ª-6ª 7h-21h; Sábado 9h-13h (ABERTO sábado) | AA65: 17 | AD65: Grupo de 3 escolas (interior norte do distrito, volume baixo - Castanheirense 16, Figueiroense 17, Pedroguense 45 exames 2021); decisão única para 3 sites | AH65: 0 | AL65: =IF(IF(O65<>"",O65,IF(LEFT(TRIM(N65),1)="9",N65,""))="","",HYPERLINK("https://wa.me/351"&LEFT(SUBSTITUTE(SUBSTITUTE(SUBSTITUTE(IF(O65<>"",O65,IF(LEFT(TRIM(N65),1)="9",N65,""))," ",""),"+351",""),"-",""),9),"Abrir WhatsApp")) -> Abrir WhatsApp | AM65: Site comum (escolaconducaocastanheirense.pt) com menu "Área do Aluno" que só leva a testes/simuladores e impressos IMT - sem marcação online | AN65: Rua Major Neutel Abreu, 1.º Dto - 3260-427 Figueiró dos Vinhos | AO65: https://passaprimeira.xyz/distritos-regioes/leiria/concelhos/figueiro-dos-vinhos/escolas/figueiroense-00473/; https://www.escolaconducaocastanheirense.pt/contactos/
A66: 65 | B66: A | C66: 5.1 | D66: Novo | E66: Pedro | F66: telefone | G66: Leiria | H66: Alvaiázere | I66: Alvaiázere | J66: Escola de Condução de Alvaiázere (Marques & Marques, Lda.) | N66: 236 655 272 | U66: 3.7 | V66: 9 | AA66: 162 | AC66: "não existirem vagas para marcar aulas... não aconselho" (Google 1★, 06/2023, ficha "Escola de conducão" Alvaiázere) https://escola-de-conducao.pt/escola-de-conducao-305869.html | AD66: Evidência de dor (falta de vagas para marcar aulas); única escola do concelho (162 exames 2021) | AH66: 0 | AL66: =IF(IF(O66<>"",O66,IF(LEFT(TRIM(N66),1)="9",N66,""))="","",HYPERLINK("https://wa.me/351"&LEFT(SUBSTITUTE(SUBSTITUTE(SUBSTITUTE(IF(O66<>"",O66,IF(LEFT(TRIM(N66),1)="9",N66,""))," ",""),"+351",""),"-",""),9),"Abrir WhatsApp")) | AN66: Rua Prof. José Maria Castelão - 3250-115 Alvaiázere | AO66: https://passaprimeira.xyz/distritos-regioes/leiria/concelhos/alvaiazere/escolas/alvaiazere-00239/; https://escola-de-conducao.pt/escola-de-conducao-305869.html; https://escola-de-conducao.pt/marques-marques-lda-306555.html; https://www.andardemoto.pt/escolas-de-conducao/dir/d/leiria/c/alvaiazere/p-2578/escola-de-conducao-de-alvaiazere/
A67: 66 | B67: A | C67: 5.1 | D67: Novo | E67: Pedro | F67: grupo | G67: Santarém | H67: Abrantes | I67: Abrantes | J67: Escola de Condução Traquina | K67: Traquina e Sardoalense (Abrantes + Sardoal) | N67: 241 372 259 | S67: https://www.facebook.com/pages/Escolas-Condu%C3%A7%C3%A3o-Traquina-e-Sardoalense/114156232091227 | AA67: 161 | AD67: Grupo multi-escola (Traquina + Sardoalense, página Facebook conjunta) | AH67: 0 | AL67: =IF(IF(O67<>"",O67,IF(LEFT(TRIM(N67),1)="9",N67,""))="","",HYPERLINK("https://wa.me/351"&LEFT(SUBSTITUTE(SUBSTITUTE(SUBSTITUTE(IF(O67<>"",O67,IF(LEFT(TRIM(N67),1)="9",N67,""))," ",""),"+351",""),"-",""),9),"Abrir WhatsApp")) | AN67: Rua Cidade de Parthenay, Bloco E, R/C Loja 7, 2200-238 Abrantes | AO67: https://www.bomcondutor.pt/escolas/escola/traquina; https://www.autonews.pt/escolas-de-conducao/dir/d/santarem/c/abrantes/p-2241/traquina/; https://www.imt-ip.pt/wp-content/uploads/2025/01/EscolasdeConducao-2021.pdf
A68: 67 | B68: A | C68: 5.1 | D68: Novo | E68: Pedro | F68: grupo | G68: Aveiro | H68: Aveiro | I68: Aveiro (São Bernardo) | J68: Escola de Condução Drive IN Aveiro (ex-São Bernardo / Nova de Esgueira) | K68: Drive IN | O68: 924 413 117 | S68: https://www.facebook.com/EC.Nova.de.Esgueira/ | U68: 4.2 | V68: 5 | X68: Não divulgado online (sem plataforma de marcação visível) | Y68: Sim | Z68: Seg-Sex 10:00-12:30 e 14:30-19:30; Sábado 10:00-12:30 (aberto ao sábado de manhã) | AA68: 20 | AC68: "tratado como lixo durante aulas práticas, com o instrutor a ouvir música" (11/2023) https://escola-de-conducao.pt/escola-de-conducao-drive-in-aveiro-306690.html | AD68: Marca Drive IN com 2 escolas (Aveiro + Águeda); nova marca, a reestruturar-se — abertura a ferramentas novas | AH68: 0 | AL68: =IF(IF(O68<>"",O68,IF(LEFT(TRIM(N68),1)="9",N68,""))="","",HYPERLINK("https://wa.me/351"&LEFT(SUBSTITUTE(SUBSTITUTE(SUBSTITUTE(IF(O68<>"",O68,IF(LEFT(TRIM(N68),1)="9",N68,""))," ",""),"+351",""),"-",""),9),"Abrir WhatsApp")) -> Abrir WhatsApp | AN68: Estrada de São Bernardo / Estrada de Vilar, 53 R/C, 3810-164 Aveiro | AO68: https://escola-de-conducao.pt/escola-de-conducao-drive-in-aveiro-306690.html (rating Google via snapshot escola-de-conducao.pt); https://passaprimeira.xyz/en/districts-regions/aveiro/municipalities/aveiro/schools/ (licença IMT 1379 'São Bernardo'); https://escola-de-conducao.pt/escola-de-conducao-drive-in-agueda-306420.html
A69: 68 | B69: A | C69: 5 | D69: Novo | E69: Pedro | F69: telefone | G69: Leiria | H69: Óbidos | I69: Gaeiras | J69: Escola de Condução Santa Maria de Óbidos | N69: 262 877 700 | O69: 926 849 566 | P69: yes (wa.me/926849566) | Q69: info@grpsantamaria.com | R69: https://ec-santamaria.com/ | S69: https://www.facebook.com/EscolaSantaMariadeObidos/ | T69: https://www.instagram.com/escola_santa_maria_obidos/ | U69: 4.8 | V69: 73 | X69: Telefone/WhatsApp/secretaria | Y69: Sim | Z69: Secretaria 2ª-6ª 9h30-13h / 14h30-20h; Sábado 9h-13h (ABERTO sábado); aulas 7h-24h | AA69: 756 | AB69: A, B, C, D, trator agrícola; CAM, ADR, TCC | AD69: 2.º maior volume do distrito (756 exames 2021), programa intensivo "exames em 10 dias" com aulas 7h-24h = logística pesada de marcação; usa WhatsApp/Instagram | AH69: 0 | AL69: =IF(IF(O69<>"",O69,IF(LEFT(TRIM(N69),1)="9",N69,""))="","",HYPERLINK("https://wa.me/351"&LEFT(SUBSTITUTE(SUBSTITUTE(SUBSTITUTE(IF(O69<>"",O69,IF(LEFT(TRIM(N69),1)="9",N69,""))," ",""),"+351",""),"-",""),9),"Abrir WhatsApp")) -> Abrir WhatsApp | AM69: Site WordPress com link WhatsApp; sem área do aluno/app | AN69: Estrada Nacional 8, Lote 4 - 2510-737 Gaeiras, Óbidos | AO69: https://passaprimeira.xyz/distritos-regioes/leiria/concelhos/obidos/escolas/santa-maria-de-obidos-00487/; https://ec-santamaria.com/contactos/; https://escola-de-conducao.pt/escola-de-conducao-santa-maria-de-obidos-306056.html
A70: 69 | B70: A | C70: 5 | D70: Novo | E70: Pedro | F70: grupo | G70: Santarém | H70: Ourém | I70: Caxarias | J70: Escola de Condução Caxariense | K70: Espada & Oliveira (Ouriense, Fatimense, Caxariense) | N70: 249 571 396 | O70: 912 509 255 / 933 890 031 | Q70: ec-caxariense@espadaeoliveira.com | R70: https://www.espadaeoliveira.pt/caxariense.php | S70: https://www.facebook.com/pages/ESCOLA-DE-CONDU%C3%87%C3%83O-OURIENSE/117550408321810 | X70: Telefone/presencial; pré-inscrição por formulário no site | Y70: Sim | Z70: Seg-Sex 10:30-13:00 e 15:00-19:30; Sábado 09:00-12:00 (ABERTO sábado) | AA70: 123 | AD70: Delegação do grupo Espada & Oliveira (3 escolas). | AH70: 0 | AL70: =IF(IF(O70<>"",O70,IF(LEFT(TRIM(N70),1)="9",N70,""))="","",HYPERLINK("https://wa.me/351"&LEFT(SUBSTITUTE(SUBSTITUTE(SUBSTITUTE(IF(O70<>"",O70,IF(LEFT(TRIM(N70),1)="9",N70,""))," ",""),"+351",""),"-",""),9),"Abrir WhatsApp")) -> Abrir WhatsApp | AM70: Sem área do aluno; testes de código online alojados em educacao-rodoviaria.pt (http://www.educacao-rodoviaria.pt/testesonline/ouriense/); inscrição por formulário web | AN70: Av. 21 de Junho, 32 R/C Dto., Chã, 2435-087 Caxarias | AO70: https://www.espadaeoliveira.pt/contactos_caxariense.php; https://www.andardemoto.pt/escolas-de-conducao/dir/d/santarem/c/ourem/p-2529/escola-de-conducao-caxariense/; https://www.imt-ip.pt/wp-content/uploads/2025/01/EscolasdeConducao-2021.pdf
A71: 70 | B71: A | C71: 5 | D71: Novo | E71: Pedro | F71: grupo | G71: Santarém | H71: Alpiarça | I71: Alpiarça | J71: Escola de Condução Matos - Alpiarça (EC Alpiarça) | K71: Escolas de Condução Matos (família Tomé; antigo site matosconducao.com, inativo) | N71: 243 557 719 | O71: 932 852 252 | Q71: ec-alpiarca@hotmail.com | V71: 2 | AA71: 114 | AD71: Delegação do grupo Matos | AH71: 0 | AL71: =IF(IF(O71<>"",O71,IF(LEFT(TRIM(N71),1)="9",N71,""))="","",HYPERLINK("https://wa.me/351"&LEFT(SUBSTITUTE(SUBSTITUTE(SUBSTITUTE(IF(O71<>"",O71,IF(LEFT(TRIM(N71),1)="9",N71,""))," ",""),"+351",""),"-",""),9),"Abrir WhatsApp")) -> Abrir WhatsApp | AM71: Site do grupo matosconducao.com já não resolve (arquivo web 2013-2016 lista: Almeirim J. Justino, Almeirinense, Alpiarça, Azambuja, Cartaxo, Fazendas de Almeirim, Santarém Ribatejana, Pedro de Santarém) — https://web.archive.org/web/2013/http://www.matosconducao.com/matos/4567579683; nenhum portal do aluno visível | AN71: Rua Silvestre Bernardo Lima nº 16, 2090-077 Alpiarça | AO71: https://www.testesdecodigogratis.com/escola-de-conducao/matos-alpiarca/; https://www.andardemoto.pt/escolas-de-conducao/dir/d/santarem/c/alpiarca/p-2577/escola-de-conducao-de-alpiarca/; https://escola-de-conducao.pt/escola-de-conducao-alpiarca-306904.html; https://www.imt-ip.pt/wp-content/uploads/2025/01/EscolasdeConducao-2021.pdf
A72: 71 | B72: A | C72: 5 | D72: Novo | E72: Pedro | F72: grupo | G72: Santarém | H72: Santarém | I72: Santarém | J72: Escola de Condução Matos - Santarém (Pedro de Santarém / Tomé-Pinto Lda) | K72: Nossa Senhora da Paz (Benavente, Cartaxo, Santarém) — ex-grupo Matos? | Escolas de Condução Matos (família Tomé; antigo site matosconducao.com, inativo) | N72: 243 332 936 | O72: 932 061 452 ; 919 350 906 | Q72: escola.conducao.tome@gmail.com ; santarem@escolaconducao.pt | R72: https://www.escolaconducao.pt | U72: 4.4 | V72: 15 | X72: Telefone/presencial (sem canal online conhecido) | Y72: Não | Z72: Seg-Sex 09:00-20:00; Sábado encerrado (Google) | Site NS Paz: atendimento Seg-Sex 09h30-12h30/14h30-19h30 | AC72: 'Seriamente deplorante para tirar a carta, demorado e mal organizado' — https://escola-de-conducao.pt/escola-de-conducao-matos-santarem-306124.html; 'demoram uma eternidade para marcar o exame prático' — idem | AD72: Sede do grupo Matos (7 escolas no âmbito + Azambuja/Aveiras de Cima); sem plataforma digital, site do grupo morto; queixas de demora/desorganização. Fechada ao sábado — visitar em dia útil. Morada e telefone constam hoje como delegação Santarém da EC Nossa Senhora da Paz (escolaconducao.pt) — confirmar marca atual | AH72: 0 | AL72: =IF(IF(O72<>"",O72,IF(LEFT(TRIM(N72),1)="9",N72,""))="","",HYPERLINK("https://wa.me/351"&LEFT(SUBSTITUTE(SUBSTITUTE(SUBSTITUTE(IF(O72<>"",O72,IF(LEFT(TRIM(N72),1)="9",N72,""))," ",""),"+351",""),"-",""),9),"Abrir WhatsApp")) -> Abrir WhatsApp | AM72: Site do grupo matosconducao.com já não resolve (arquivo web 2013-2016 lista: Almeirim J. Justino, Almeirinense, Alpiarça, Azambuja, Cartaxo, Fazendas de Almeirim, Santarém Ribatejana, Pedro de Santarém) — https://web.archive.org/web/2013/http://www.matosconducao.com/matos/4567579683; nenhum portal do aluno visível | AN72: Rua Pedro de Santarém 130 (1º Esq.), 2000-223 Santarém | AO72: https://escola-de-conducao.pt/escola-de-conducao-matos-santarem-306124.html; https://escola-de-conducao.pt/escola-de-conducao-tome-pinto-lda-306630.html; https://www.andardemoto.pt/escolas-de-conducao/dir/d/santarem/c/santarem/p-2233/escola-de-conducao-pedro-de-santarem/; https://escolasconducao.com/escola/matos-conducao-lda; https://www.escolaconducao.pt/contactos.html
A73: 72 | B73: A | C73: 5 | D73: Novo | E73: Pedro | F73: grupo | G73: Santarém | H73: Rio Maior | I73: Rio Maior | J73: Escola de Condução Via Maior | K73: Grupo Caldas (11 escolas: Caldas, Louzan, Lizauto, Cardal, Via Maior, Capas Negras, Supertubos, Fica, Nova Setúbal, Scallabis, Nova Viseu) — antes pertencia ao grupo Matos | N73: 243 140 906 | O73: 914 098 152 | P73: yes | Q73: viamaior@grupocaldas.pt | R73: https://grupocaldas.pt/site/ecviamaior/ | S73: https://www.facebook.com/ecviamaior | T73: https://www.instagram.com/ecviamaior/ | U73: 4.7 | V73: 10 | X73: Telefone/WhatsApp/presencial | Y73: Sim | Z73: Secretaria Seg-Sex 10:00-12:30 e 14:00-20:00; Sábado 09:00-13:00 (ABERTO SÁBADO) | AA73: 128 | AB73: A1, A2, A2B, B (C, CE, D em parceria c/ EC Bordalo Pinheiro; A, AB c/ EC Caldas) | AD73: Grupo Caldas (11 escolas) — mesmo decisor que Scallabis; usa WhatsApp e redes sociais (aberto a tecnologia) | AH73: 0 | AL73: =IF(IF(O73<>"",O73,IF(LEFT(TRIM(N73),1)="9",N73,""))="","",HYPERLINK("https://wa.me/351"&LEFT(SUBSTITUTE(SUBSTITUTE(SUBSTITUTE(IF(O73<>"",O73,IF(LEFT(TRIM(N73),1)="9",N73,""))," ",""),"+351",""),"-",""),9),"Abrir WhatsApp")) -> Abrir WhatsApp | AM73: Site do grupo só com pré-inscrição, WhatsApp e PDF 'Calendário de Aulas Teóricas'; sem área do aluno | AN73: Rua Madre Teresa de Saldanha nº 5-A, Urb. Pá da Ribeira, 2040-227 Rio Maior | AO73: https://grupocaldas.pt/site/ecviamaior/; https://grupocaldas.pt/site/contactos/; https://escola-de-conducao.pt/escola-de-conducao-via-maior-306348.html; https://escolasconducao.com/escola/viamaior-2-centro-de-formacao-rodoviaria-lda; https://web.archive.org/web/20160718122825/http://www.matosconducao.com:80/rio-maior/4591278027; https://www.imt-ip.pt/wp-content/uploads/2025/01/EscolasdeConducao-2021.pdf
A74: 73 | B74: A | C74: 5 | D74: Novo | E74: Pedro | F74: grupo | G74: Aveiro | H74: Águeda | I74: Águeda | J74: Escola de Condução Drive IN Águeda | K74: Drive IN | O74: 924 413 255 | Q74: drive.inlda@gmail.com | U74: 3.9 | V74: 7 | W74: DriveBox (plataforma online de ensino teórico) | Y74: Não | Z74: Seg 10:00–12:30 14:30–19:30 Ter 10:00–12:30 14:30–19:30 Qua 10:00–12:30 14:30–19:30 Qui 10:00–12:30 14:30–19:30 Sex 10:00–12:30 14:30–19:30 SÁB 10:00–12:30 Dom Encerrado — aberto sábado de manhã | AC74: "Auto escola, sem ética, sem transparência ... e principalmente suporte de apoio ao aluno" (Portal da Queixa, 20/02/2024) https://portaldaqueixa.com/brands/escola-de-conducao-drive-in/complaints/escola-de-conducao-drive-in-metodologia-duvidosa-e-cobrancas-indevidas-108127424; pedido de reembolso sem resposta no prazo (Portal da Queixa, 30/07/2025) https://portaldaqueixa.com/brands/escola-de-conducao-drive-in/complaints/escola-de-conducao-drive-in-queixa-contra-escola-de-conducao-drive-in-agueda-138294725; "instrutor que fica a jogar cartas e a ler notícias no telemóvel" (1★, 20/01/2024) https://escola-de-conducao.pt/escola-de-conducao-drive-in-agueda-306420.html | AD74: Multi-sede (Águeda + Aveiro) e várias queixas públicas; já usa plataforma online (DriveBox) — abertura a tecnologia; verificar se cobre marcação/app | AH74: 0 | AL74: =IF(IF(O74<>"",O74,IF(LEFT(TRIM(N74),1)="9",N74,""))="","",HYPERLINK("https://wa.me/351"&LEFT(SUBSTITUTE(SUBSTITUTE(SUBSTITUTE(IF(O74<>"",O74,IF(LEFT(TRIM(N74),1)="9",N74,""))," ",""),"+351",""),"-",""),9),"Abrir WhatsApp")) -> Abrir WhatsApp | AM74: Queixa no Portal da Queixa (2025) refere contacto "através da plataforma DriveBox"; queixa de 2024 descreve método teórico online com aulas em vídeo e testes bloqueados 48h/€2 | AN74: Rua Joaquim Valente de Almeida 388, 3750-154 Águeda | AO74: https://escola-de-conducao.pt/escola-de-conducao-drive-in-agueda-306420.html; https://dadosabertos.cm-agueda.pt/dataset/3213f991-5d35-4bef-9e2a-b7794f3598e8 (CM Águeda dados abertos 2023); https://portaldaqueixa.com/brands/escola-de-conducao-drive-in; https://www.racius.com/drive-in-unipessoal-lda/
A75: 74 | B75: A | C75: 5 | D75: Novo | E75: Pedro | F75: grupo | G75: Aveiro | H75: Águeda | I75: Águeda (EN1, Corga/Recardães) | J75: Escola de Condução de Águeda (Nº1 Miguel Silva) | K75: Escolas Miguel Silva | N75: 234 622 565 | Q75: eca.miguel.agueda@gmail.com | R75: https://escolasmiguelsilva.pt/ | S75: https://www.facebook.com/escolas.miguel.silva/ ; https://pt-pt.facebook.com/ECAMiguelSilva | T75: https://www.instagram.com/escolas.miguel.silva/ | U75: 4.7 | V75: 19 | X75: Telefone/presencial (sem marcação online visível) | Y75: Não | Z75: Seg 09:00–19:00 Ter 09:00–19:00 Qua 09:00–19:00 Qui 09:00–19:00 Sex 09:00–19:00 SÁB Encerrado Dom Encerrado — fechado ao sábado | AA75: 240 | AC75: "Horrível, não tiveram o mínimo de paciência para ensinar" (1★, 27/02/2024) https://escola-de-conducao.pt/escola-de-conducao-de-agueda-escolas-miguel-silva-306419.html | AD75: Sede de grupo multi-sede (5 escolas: Águeda, Aguada de Cima, Oiã, Oliveira do Bairro, Palhaça) sem app/plataforma de alunos; volume médio-alto | AH75: 0 | AL75: =IF(IF(O75<>"",O75,IF(LEFT(TRIM(N75),1)="9",N75,""))="","",HYPERLINK("https://wa.me/351"&LEFT(SUBSTITUTE(SUBSTITUTE(SUBSTITUTE(IF(O75<>"",O75,IF(LEFT(TRIM(N75),1)="9",N75,""))," ",""),"+351",""),"-",""),9),"Abrir WhatsApp")) | AM75: Site WordPress do grupo só com contactos; sem área do aluno, e-learning ou link de software visível | AN75: Rua Miguel de Almeida e Silva, EN1 nº 655, 3750-318 Águeda | AO75: https://escolasmiguelsilva.pt/contact-agueda/; https://escola-de-conducao.pt/escola-de-conducao-de-agueda-escolas-miguel-silva-306419.html; https://passaprimeira.xyz/en/districts-regions/aveiro/municipalities/agueda/schools/; https://dadosabertos.cm-agueda.pt/dataset/3213f991-5d35-4bef-9e2a-b7794f3598e8 (CM Águeda dados abertos 2023)
A76: 75 | B76: A | C76: 4.9 | D76: Novo | E76: Pedro | F76: grupo | G76: Aveiro | H76: Aveiro | I76: Aveiro | J76: Escola de Condução Aveirense | K76: Grupo IP5 | N76: 234 429 838 | O76: 939 515 531 | Q76: aveirense@grupoip5.pt | R76: grupoip5.pt (domínio não resolve em out/2026); escoladeconducaoaveirense.negocio.site (404) | U76: 4.6 | V76: 36 | X76: Não divulgado online (sem plataforma de marcação visível) | Y76: Sim | Z76: Seg-Sex 10:00-12:00 e 14:00-20:00; Sábado 10:00-12:00 (aberto ao sábado de manhã) | AA76: 230 | AC76: "foi durante uma aula de código que me foi pedido... que avaliássemos a escola com 5 estrelas"; "20 aulas extra e 540€ depois" (10/2023) https://escola-de-conducao.pt/escola-de-conducao-aveirense-306454.html | AD76: Pertence ao Grupo IP5 (multi-escola); volume médio-alto; presença digital fraca (sites em baixo) | AH76: 0 | AL76: =IF(IF(O76<>"",O76,IF(LEFT(TRIM(N76),1)="9",N76,""))="","",HYPERLINK("https://wa.me/351"&LEFT(SUBSTITUTE(SUBSTITUTE(SUBSTITUTE(IF(O76<>"",O76,IF(LEFT(TRIM(N76),1)="9",N76,""))," ",""),"+351",""),"-",""),9),"Abrir WhatsApp")) -> Abrir WhatsApp | AM76: Sem site ativo; sem área do aluno identificada | AN76: Rua Dr. Mário Sacramento / EN, n.º 109, Loja F R/C Dt.º, 3810-104 Aveiro (Google: Rua Dr. Pompeu de Melo Cardoso, loja 11, 3810-106) | AO76: https://escola-de-conducao.pt/escola-de-conducao-aveirense-306454.html (rating Google via snapshot escola-de-conducao.pt); https://passaprimeira.xyz/en/districts-regions/aveiro/municipalities/aveiro/schools/; https://grupoip5.pt/contactos-aveirense.php; https://www.andardemoto.pt/escolas-de-conducao/dir/d/aveiro/c/aveiro/p-2175/aveirense/
A77: 76 | B77: A | C77: 4.9 | D77: Novo | E77: Pedro | F77: grupo | G77: Aveiro | H77: Oliveira do Bairro | I77: Oliveira do Bairro | J77: Escola de Condução de Oliveira do Bairro | K77: Escolas Miguel Silva | N77: 234 748 613 | Q77: ecobform@gmail.com | R77: https://escolasmiguelsilva.pt/contact-oliveira/ | S77: https://www.facebook.com/escolas.miguel.silva/ | T77: https://www.instagram.com/escolas.miguel.silva/ | U77: 4.8 | V77: 26 | X77: Telefone/presencial (sem marcação online visível) | Y77: Não | Z77: Seg 09:00–19:00 Ter 09:00–19:00 Qua 09:00–19:00 Qui 09:00–19:00 Sex 09:00–19:00 SÁB 10:00–12:00 Dom Encerrado — aberto sábado de manhã | AA77: 218 | AC77: "Fiquei frustrada com a Escola por vezes" (3★, 04/10/2023) https://escola-de-conducao.pt/escola-de-conducao-oliveira-do-bairro-escolas-miguel-silva-306529.html | AD77: Grupo multi-sede Escolas Miguel Silva; volume relevante (218 exames 2021); sem app | AH77: 0 | AL77: =IF(IF(O77<>"",O77,IF(LEFT(TRIM(N77),1)="9",N77,""))="","",HYPERLINK("https://wa.me/351"&LEFT(SUBSTITUTE(SUBSTITUTE(SUBSTITUTE(IF(O77<>"",O77,IF(LEFT(TRIM(N77),1)="9",N77,""))," ",""),"+351",""),"-",""),9),"Abrir WhatsApp")) | AM77: Site WordPress do grupo só com contactos; sem área do aluno, e-learning ou link de software visível | AN77: Rua da Misericórdia, nº 2 r/c, 3770-215 Oliveira do Bairro | AO77: https://escolasmiguelsilva.pt/contact-oliveira/; https://escola-de-conducao.pt/escola-de-conducao-oliveira-do-bairro-escolas-miguel-silva-306529.html; https://passaprimeira.xyz/en/districts-regions/aveiro/municipalities/oliveira-do-bairro/schools/; https://www.bomcondutor.pt/escolas/escola/oliveira-do-bairro
A78: 77 | B78: A | C78: 4.8 | D78: Novo | E78: Pedro | F78: grupo | G78: Coimbra | H78: Oliveira do Hospital | I78: Oliveira do Hospital | J78: Escola de Condução FICA | K78: Escola de Condução FICA (Oliveira do Hospital + Coimbra) | N78: 238 605 761; 238 605 762 | Q78: geral@escolafica.pt | R78: www.escolafica.pt (não responde) | S78: https://www.facebook.com/pages/Escola-de-Condu%C3%A7%C3%A3o-FICA/324266437679152 | U78: 4.8 | V78: 4 | Y78: Sim | Z78: Seg-Qui 09:00-12:30 / 14:00-19:00; Sex 09:00-19:00; Sábado 09:00-13:00 (aberto ao sábado) | AA78: 211 | AD78: Grupo multi-site (FICA: Oliveira do Hospital + Coimbra) | AH78: 0 | AL78: =IF(IF(O78<>"",O78,IF(LEFT(TRIM(N78),1)="9",N78,""))="","",HYPERLINK("https://wa.me/351"&LEFT(SUBSTITUTE(SUBSTITUTE(SUBSTITUTE(IF(O78<>"",O78,IF(LEFT(TRIM(N78),1)="9",N78,""))," ",""),"+351",""),"-",""),9),"Abrir WhatsApp")) | AM78: Website inacessível | AN78: Rua António Nobre, 16-A (ficha Google: R. Ameal 9A r/c, 3400-101), 3400-084 Oliveira do Hospital | AO78: https://www.bomcondutor.pt/escolas/escola/fica; https://escola-de-conducao.pt/escola-de-conducao-fica-lda-306442.html; https://www.andardemoto.pt/escolas-de-conducao/dir/d/coimbra/c/oliveira-do-hospital/p-2695/escola-de-conducao-fica/; https://www.imt-ip.pt/wp-content/uploads/2025/01/EscolasdeConducao-2021.pdf
A79: 78 | B79: A | C79: 4.8 | D79: Novo | E79: Pedro | F79: grupo | G79: Coimbra | H79: Figueira da Foz | I79: Figueira da Foz | J79: Escola de Condução Florbela | K79: Grupo MGA (Escolas MGA, desde 1971) - 5 escolas no distrito | N79: 233 423 100 | O79: 961 448 308 | Q79: geral@escolasmga.pt | R79: https://escolasmga.pt/escolas-de-conducao/figueira-da-foz-florbela/ | S79: https://www.facebook.com/escolasgrupomga | U79: 4.2 | V79: 5 | W79: BDrive | X79: Secretaria/telefone; BDrive para alunos registados | Y79: Sim | Z79: Seg-Sex 08:30-12:00 / 14:00-19:00; Sábado 08:30-12:00 (aberto ao sábado) | AA79: 205 | AB79: A, A1, A2, B1, B, B automático, BE, C, C1, CE, D, D1, DE, T, veículos adaptados; CAM | AD79: Delegação do Grupo MGA (multi-site) | AH79: 0 | AL79: =IF(IF(O79<>"",O79,IF(LEFT(TRIM(N79),1)="9",N79,""))="","",HYPERLINK("https://wa.me/351"&LEFT(SUBSTITUTE(SUBSTITUTE(SUBSTITUTE(IF(O79<>"",O79,IF(LEFT(TRIM(N79),1)="9",N79,""))," ",""),"+351",""),"-",""),9),"Abrir WhatsApp")) -> Abrir WhatsApp | AM79: https://escolasmga.pt/servicos/plataforma-bdrive/ (link para bdrive.pt, 'Acesso exclusivo a instruendos registados'); também 'Plataforma de Testes' e 'Pré-inscrição Online' | AN79: Rua Dr. José Jardim, 22, 1º, 3080-066 Figueira da Foz | AO79: https://escolasmga.pt/escolas-de-conducao/; https://escola-de-conducao.pt/escola-de-conducao-florbela-grupo-mga-desde-1971-305934.html; https://www.imt-ip.pt/wp-content/uploads/2025/01/EscolasdeConducao-2021.pdf
A80: 79 | B80: A | C80: 4.8 | D80: Novo | E80: Pedro | F80: grupo | G80: Coimbra | H80: Figueira da Foz | I80: Marinha das Ondas | J80: Escola de Condução Marinha das Ondas | K80: Escolas de Condução Abadias (Figueira da Foz + Marinha das Ondas) | N80: 233 098 213 | O80: 916 633 701 | P80: yes | R80: https://ecabadias.pt/ | S80: Página 'Escola de Condução Marinha das Ondas' (ligada no site) | X80: Telefone/WhatsApp | AA80: 198 | AD80: Delegação do grupo Abadias (multi-site) | AH80: 0 | AL80: =IF(IF(O80<>"",O80,IF(LEFT(TRIM(N80),1)="9",N80,""))="","",HYPERLINK("https://wa.me/351"&LEFT(SUBSTITUTE(SUBSTITUTE(SUBSTITUTE(IF(O80<>"",O80,IF(LEFT(TRIM(N80),1)="9",N80,""))," ",""),"+351",""),"-",""),9),"Abrir WhatsApp")) -> Abrir WhatsApp | AM80: Mesmo site/portal teórico do grupo Abadias (ensinoadistancia.segurancarodoviaria.pt) | AN80: Rua dos Alentejeiros, 22, 3090-485 Marinha das Ondas | AO80: https://ecabadias.pt/; https://www.imt-ip.pt/wp-content/uploads/2025/01/EscolasdeConducao-2021.pdf
A81: 80 | B81: A | C81: 4.8 | D81: Novo | E81: Pedro | F81: grupo | G81: Coimbra | H81: Tábua | I81: Tábua | J81: Escola de Condução Nossa Senhora de Fátima | K81: Grupo MGA (Escolas MGA, desde 1971) - 5 escolas no distrito | N81: 235 413 830 | O81: 961 448 313 | Q81: geral@escolasmga.pt | R81: https://escolasmga.pt/escolas-de-conducao/tabua-na-sra-de-fatima/ | S81: https://www.facebook.com/escolasgrupomga | U81: 5 | V81: 2 | W81: BDrive | X81: Secretaria/telefone; BDrive para alunos registados | Y81: Sim | Z81: Seg-Sex 09:00-12:00 / 14:00-19:00; Sábado 09:00-12:00 (aberto ao sábado) | AA81: 195 | AB81: A, A1, A2, B1, B, B automático, BE, C, C1, CE, D, D1, DE, T, veículos adaptados; CAM | AD81: Delegação do Grupo MGA (multi-site) | AH81: 0 | AL81: =IF(IF(O81<>"",O81,IF(LEFT(TRIM(N81),1)="9",N81,""))="","",HYPERLINK("https://wa.me/351"&LEFT(SUBSTITUTE(SUBSTITUTE(SUBSTITUTE(IF(O81<>"",O81,IF(LEFT(TRIM(N81),1)="9",N81,""))," ",""),"+351",""),"-",""),9),"Abrir WhatsApp")) -> Abrir WhatsApp | AM81: https://escolasmga.pt/servicos/plataforma-bdrive/ (link para bdrive.pt, 'Acesso exclusivo a instruendos registados'); também 'Plataforma de Testes' e 'Pré-inscrição Online' | AN81: Av. Dr. Castanheira Figueiredo, Bloco 2 R/C, 3420-302 Tábua | AO81: https://escolasmga.pt/escolas-de-conducao/; https://escola-de-conducao.pt/escola-de-conducao-nossa-senhora-de-fatima-grupo-mga-desde-1971-306565.html; https://www.imt-ip.pt/wp-content/uploads/2025/01/EscolasdeConducao-2021.pdf
A82: 81 | B82: A | C82: 4.8 | D82: Novo | E82: Pedro | F82: grupo | G82: Aveiro | H82: Águeda | I82: Águeda | J82: Escola de Condução Nova em Águeda | K82: Grupo Bordalo | N82: 234 029 745 | O82: 917 352 640 | Q82: novaagueda@grupobordalo.pt | R82: https://grupobordalo.pt/ (sem conteúdo acessível) | S82: https://www.facebook.com/ECNOVAAGUEDA/ | AA82: 322 | AD82: Parte do Grupo Bordalo (multi-escola: Nova de Aveiro, Rainha de Aveiro, Caldas da Rainha...); 322 exames 2021 | AH82: 0 | AL82: =IF(IF(O82<>"",O82,IF(LEFT(TRIM(N82),1)="9",N82,""))="","",HYPERLINK("https://wa.me/351"&LEFT(SUBSTITUTE(SUBSTITUTE(SUBSTITUTE(IF(O82<>"",O82,IF(LEFT(TRIM(N82),1)="9",N82,""))," ",""),"+351",""),"-",""),9),"Abrir WhatsApp")) -> Abrir WhatsApp | AM82: grupobordalo.pt devolve página vazia; sem evidência de software | AN82: Rua Armando Castela nº 1/3, R/C Centro, Fração A, 3750-124 Águeda | AO82: https://dadosabertos.cm-agueda.pt/dataset/3213f991-5d35-4bef-9e2a-b7794f3598e8 (CM Águeda dados abertos 2023); https://www.testesdecodigogratis.com/escola-de-conducao/nova-em-agueda/; https://passaprimeira.xyz/en/districts-regions/aveiro/municipalities/agueda/schools/; https://www.facebook.com/ECNOVAAGUEDA/
A83: 82 | B83: A | C83: 4.7 | D83: Novo | E83: Pedro | F83: telefone | G83: Santarém | H83: Entroncamento | I83: Entroncamento | J83: Escola de Condução Carmona (Escortamega - Ensino de Condução Automóvel, Lda.) | N83: 249 716 150 | S83: https://www.facebook.com/escoladeconducao.carmona | U83: 3.6 | V83: 5 | AA83: 183 | AC83: 'Muito mau, falta de respeito e de pedagogia, fazem o que querem' (1/5, 2018) - https://escola-de-conducao.pt/escortamega-ensino-de-conducao-automovel-lda-306710.html | AD83: Volume médio; a Escortamega só tem contas públicas até 2016 - confirmar a entidade exploradora atual e se está ativa. | AH83: 0 | AL83: =IF(IF(O83<>"",O83,IF(LEFT(TRIM(N83),1)="9",N83,""))="","",HYPERLINK("https://wa.me/351"&LEFT(SUBSTITUTE(SUBSTITUTE(SUBSTITUTE(IF(O83<>"",O83,IF(LEFT(TRIM(N83),1)="9",N83,""))," ",""),"+351",""),"-",""),9),"Abrir WhatsApp")) | AN83: Rua da Junta de Freguesia - Shopping Parque, Loja 14, 2330-114 Entroncamento | AO83: https://escola-de-conducao.pt/escortamega-ensino-de-conducao-automovel-lda-306710.html; https://www.racius.com/escortamega-ensino-de-conducao-automovel-lda/; https://www.testesdecodigogratis.com/escola-de-conducao/carmona/; https://www.imt-ip.pt/wp-content/uploads/2025/01/EscolasdeConducao-2021.pdf
A84: 83 | B84: A | C84: 4.7 | D84: Novo | E84: Pedro | F84: grupo | G84: Santarém | H84: Sardoal | I84: Sardoal | J84: Escola de Condução do Sardoal / Sardoalense | K84: Traquina e Sardoalense (Abrantes + Sardoal) | N84: 241 855 354 | S84: https://www.facebook.com/pages/Escolas-Condu%C3%A7%C3%A3o-Traquina-e-Sardoalense/114156232091227 | AA84: 48 | AD84: Faz parte do grupo Traquina e Sardoalense (multi-escola); volume pequeno | AH84: 0 | AL84: =IF(IF(O84<>"",O84,IF(LEFT(TRIM(N84),1)="9",N84,""))="","",HYPERLINK("https://wa.me/351"&LEFT(SUBSTITUTE(SUBSTITUTE(SUBSTITUTE(IF(O84<>"",O84,IF(LEFT(TRIM(N84),1)="9",N84,""))," ",""),"+351",""),"-",""),9),"Abrir WhatsApp")) | AN84: Avenida Heróis do Ultramar, N.º 16, 2230-224 Sardoal | AO84: https://www.bomcondutor.pt/escolas/escola/do-sardoal; https://www.autonews.pt/escolas-de-conducao/dir/d/santarem/c/sardoal/p-2624/escola-de-conducao-de-sardoal/; https://escolasconducao.com/escola/escola-de-conducao-sardoalense-lda; https://www.imt-ip.pt/wp-content/uploads/2025/01/EscolasdeConducao-2021.pdf
A85: 84 | B85: A | C85: 4.7 | D85: Novo | E85: Pedro | F85: grupo | G85: Viseu | H85: Castro Daire | I85: Castro Daire | J85: Escola de Condução Castrense | K85: João & Vaz, Lda. (NIF 505085976) — Castrense (Castro Daire) + Cinfanense/S. João (Cinfães) | N85: 232382246 | S85: https://www.facebook.com/people/Escola-de-Condu%C3%A7%C3%A3o-Castrense/100053483172924/ | U85: 2.9 (escola-de-conducao.pt (agregado, não confirmado como Google)) | V85: 7 | Y85: Não | Z85: Seg-Sex 9h-19h; Sáb: fechado | AA85: 310 | AB85: A; B; C; CE (motociclos, ligeiros, pesados e pesados com reboque) | AC85: Classificação média baixa (2.9/5 em 7 avaliações agregadas no escola-de-conducao.pt) — texto das avaliações negativas não disponível | AD85: Grupo multi-escola (mesma sociedade João & Vaz Lda. detém Cinfanense em Cinfães); Facebook ativo (1299 seguidores, 47 'falam sobre isto'); rating agregado baixo (2.9). | AH85: 0 | AL85: =IF(IF(O85<>"",O85,IF(LEFT(TRIM(N85),1)="9",N85,""))="","",HYPERLINK("https://wa.me/351"&LEFT(SUBSTITUTE(SUBSTITUTE(SUBSTITUTE(IF(O85<>"",O85,IF(LEFT(TRIM(N85),1)="9",N85,""))," ",""),"+351",""),"-",""),9),"Abrir WhatsApp")) | AN85: Av. João Rodrigues Cabrilho, 9 / Bloco 2, R/C Esq., 3600-191 Castro Daire | AO85: https://www.racius.com/joao-vaz-lda/; https://codigopostal.ciberforma.pt/dir/505085976/joao-vaz-lda/; https://escola-de-conducao.pt/escola-de-conducao-castrense-306151.html; https://www.facebook.com/p/Escola-de-Condu%C3%A7%C3%A3o-Castrense-100053483172924/; https://www.andardemoto.pt/escolas-de-conducao/dir/d/viseu/c/castro-daire/p-2528/escola-de-conducao-castrense/
A86: 85 | B86: A | C86: 4.7 | D86: Novo | E86: Pedro | F86: grupo | G86: Viseu | H86: Viseu | I86: Viseu | J86: Escola de Condução Nova Viseu | K86: Grupo Caldas (11 escolas de condução) | N86: 232095570; 262877371 (sede Grupo Caldas) | O86: 910145020 | P86: yes | Q86: novaviseu@grupocaldas.pt; ecnovaviseu@gmail.com | R86: https://grupocaldas.pt/site/ecnovaviseu/ | S86: https://www.facebook.com/ecnovaviseu/ | T86: https://www.instagram.com/ecnova_viseu/ | W86: Nenhum visível (site do grupo com calendário por escola, sem área do aluno/app) | X86: Telefone/WhatsApp (wa.me/+351910145020 no site) | Y86: Sim | Z86: Secretaria: Seg-Sex 9h-12h30, 14h-19h; Sáb 9h-13h | AA86: 298 | AB86: A1, A2, A, B | AC86: Portal da Queixa (Nova Viseu) 23/08/2019: pedido de devolução de 499€ - https://portaldaqueixa.com/brands/escola-de-conducao-nova-viseu; Nível do grupo (marca Escola de Condução Caldas, não Viseu): índice de satisfação 10.1/100, queixas 'Falta de Agendamento' (26/07/2023) e 'Tempo de Espera' para marcar aulas práticas (28/09/2022) - https://portaldaqueixa.com/brands/escola-de-conducao-caldas | AD86: Grupo multi-escola (Grupo Caldas, 11 escolas) com queixas de agendamento a nível de grupo; decisão provavelmente na sede (Caldas da Rainha). IG ativo (549 posts). | AH86: 0 | AL86: =IF(IF(O86<>"",O86,IF(LEFT(TRIM(N86),1)="9",N86,""))="","",HYPERLINK("https://wa.me/351"&LEFT(SUBSTITUTE(SUBSTITUTE(SUBSTITUTE(IF(O86<>"",O86,IF(LEFT(TRIM(N86),1)="9",N86,""))," ",""),"+351",""),"-",""),9),"Abrir WhatsApp")) -> Abrir WhatsApp | AM86: https://grupocaldas.pt/site/ecnovaviseu/ | AN86: Rua Camilo Castelo Branco, Lote 8, Urb. Quinta das Mesuras, 3500-225 Viseu | AO86: https://grupocaldas.pt/site/ecnovaviseu/; https://grupocaldas.pt/; https://portaldaqueixa.com/brands/escola-de-conducao-nova-viseu; https://portaldaqueixa.com/brands/escola-de-conducao-caldas; https://www.facebook.com/ecnovaviseu/; https://www.instagram.com/ecnova_viseu/
A87: 86 | B87: A | C87: 4.7 | D87: Novo | E87: Pedro | F87: grupo | G87: Castelo Branco | H87: Castelo Branco | I87: Castelo Branco | J87: Técnica do Volante | K87: Técnica do Volante (Castelo Branco + Centro de Formação Lisboa-Expo) | N87: 272342028 | O87: 968778750 | Q87: info@tecnicadovolante.com | R87: https://www.tecnicadovolante.com | S87: https://www.facebook.com/tecnicadovolante | U87: 4.7 | V87: 30 | X87: Aulas teóricas em horário fixo; aulas de sábado 'por marcação' (site); contacto telefónico | Y87: Sim | Z87: Secretaria Seg-Sex 09:00-13:00, 14:00-19:00; Sábado 09:00-13:00 (aberto); aulas práticas 08:00-20:00 | AA87: 426 | AB87: A1, A2, A, B, C, CE, D, CAM | AD87: Multi-sítio (CB + centro de formação em Lisboa) e grande volume (426); discurso de 'inovação/tecnologia' | AH87: 0 | AL87: =IF(IF(O87<>"",O87,IF(LEFT(TRIM(N87),1)="9",N87,""))="","",HYPERLINK("https://wa.me/351"&LEFT(SUBSTITUTE(SUBSTITUTE(SUBSTITUTE(IF(O87<>"",O87,IF(LEFT(TRIM(N87),1)="9",N87,""))," ",""),"+351",""),"-",""),9),"Abrir WhatsApp")) -> Abrir WhatsApp | AM87: Link para plataforma de testes ProExamWeb (proexamweb.com) em tecnicadovolante.com/ensino.html; refere 'ensino virtual' para aulas teóricas; sem área do aluno de marcação | AN87: Av. 1º de Maio, 49 - S/L Dto, 6000-086 Castelo Branco | AO87: https://escola-de-conducao.pt/tecnica-do-volante-306783.html; https://passaprimeira.xyz/distritos-regioes/castelo-branco/concelhos/castelo-branco/escolas/tecnica-do-volante-00496/; https://tecnicadovolante.com/contactos.html; https://tecnicadovolante.com/ensino.html; https://tecnicadovolante.com/escola.html; https://escolasconducao.com/escola/escola-de-conducao-tecnica-do-volante-unipessoal-lda
A88: 87 | B88: A | C88: 4.5 | D88: Novo | E88: Pedro | F88: grupo | G88: Santarém | H88: Abrantes | I88: Abrantes | J88: Escola de Condução Abranjovem (Abrantes) | K88: Abranjovem (Abrantes + Mação) | N88: 241 364 138 | S88: https://www.facebook.com/Abranjovem/ | AD88: Marca com duas escolas (Abrantes e Mação); não identificada pelo nome no relatório IMT 2021, por isso convém confirmar que a escola de Abrantes ainda funciona | AH88: 0 | AL88: =IF(IF(O88<>"",O88,IF(LEFT(TRIM(N88),1)="9",N88,""))="","",HYPERLINK("https://wa.me/351"&LEFT(SUBSTITUTE(SUBSTITUTE(SUBSTITUTE(IF(O88<>"",O88,IF(LEFT(TRIM(N88),1)="9",N88,""))," ",""),"+351",""),"-",""),9),"Abrir WhatsApp")) | AN88: Rua Infante D. Luís 60, 1º D, 2200-090 Abrantes | AO88: https://www.autonews.pt/escolas-de-conducao/dir/d/santarem/c/abrantes/p-2242/abranjovem/; https://www.facebook.com/Abranjovem/; https://educacao-rodoviaria.pt/ensino/escolas/?loc=129&zona=4
A89: 88 | B89: A | C89: 4.5 | D89: Novo | E89: Pedro | F89: grupo | G89: Santarém | H89: Mação | I89: Mação | J89: Escola de Condução Abranjovem (Mação) | K89: Abranjovem (Abrantes + Mação) | S89: https://www.facebook.com/Abranjovem/ | AD89: Marca com duas escolas (Abrantes e Mação); Facebook com 425 seguidores. O relatório IMT 2021 tem uma 'Escola de Condução Mação' com 96 provas que pode ser esta, mas não foi confirmado | AH89: 0 | AL89: =IF(IF(O89<>"",O89,IF(LEFT(TRIM(N89),1)="9",N89,""))="","",HYPERLINK("https://wa.me/351"&LEFT(SUBSTITUTE(SUBSTITUTE(SUBSTITUTE(IF(O89<>"",O89,IF(LEFT(TRIM(N89),1)="9",N89,""))," ",""),"+351",""),"-",""),9),"Abrir WhatsApp")) | AN89: Mação (ao lado dos correios) | AO89: https://www.facebook.com/Abranjovem/
A90: 89 | B90: A | C90: 4.5 | D90: Novo | E90: Pedro | F90: grupo | G90: Santarém | H90: Almeirim | I90: Almeirim | J90: Escola de Condução Almeirinense | K90: Escolas de Condução Matos (família Tomé; antigo site matosconducao.com, inativo) | N90: 243 592 451 | O90: 934 624 220 | Q90: ecalmeirinense@hotmail.com | AD90: Parte do grupo Matos (multi-escola) | AH90: 0 | AL90: =IF(IF(O90<>"",O90,IF(LEFT(TRIM(N90),1)="9",N90,""))="","",HYPERLINK("https://wa.me/351"&LEFT(SUBSTITUTE(SUBSTITUTE(SUBSTITUTE(IF(O90<>"",O90,IF(LEFT(TRIM(N90),1)="9",N90,""))," ",""),"+351",""),"-",""),9),"Abrir WhatsApp")) -> Abrir WhatsApp | AM90: Site do grupo matosconducao.com já não resolve (arquivo web 2013-2016 lista: Almeirim J. Justino, Almeirinense, Alpiarça, Azambuja, Cartaxo, Fazendas de Almeirim, Santarém Ribatejana, Pedro de Santarém) — https://web.archive.org/web/2013/http://www.matosconducao.com/matos/4567579683; nenhum portal do aluno visível | AN90: Rua das Faias 10-12, 2080-086 Almeirim | AO90: https://www.andardemoto.pt/escolas-de-conducao/dir/d/santarem/c/almeirim/; https://www.testesdecodigogratis.com/escola-de-conducao/almeirinense/
A91: 90 | B91: A | C91: 4.5 | D91: Novo | E91: Pedro | F91: grupo | G91: Santarém | H91: Santarém | I91: Santarém | J91: Escola de Condução Caseiro & Sá, Lda. | K91: Nossa Senhora da Paz (provável) | N91: 263 517 675 | AD91: Só listada num diretório (coordenadas em Santarém, indicativo 263); sem avaliações — verificar se está ativa. Telefone 263 517 675 é o da EC Nossa Senhora da Paz (Benavente) — provável entidade/registo associado ao grupo, não escola distinta | AH91: 0 | AL91: =IF(IF(O91<>"",O91,IF(LEFT(TRIM(N91),1)="9",N91,""))="","",HYPERLINK("https://wa.me/351"&LEFT(SUBSTITUTE(SUBSTITUTE(SUBSTITUTE(IF(O91<>"",O91,IF(LEFT(TRIM(N91),1)="9",N91,""))," ",""),"+351",""),"-",""),9),"Abrir WhatsApp")) | AN91: Rua Doutor Eduardo F. Almeida 46, Ribasor, Santarém | AO91: https://escola-de-conducao.pt/escola-de-conducao-caseiro-sa-lda-308942.html; https://www.escolaconducao.pt/contactos.html
A92: 91 | B92: A | C92: 4.5 | D92: Novo | E92: Pedro | F92: grupo | G92: Santarém | H92: Almeirim | I92: Fazendas de Almeirim | J92: Escola de Condução de Fazendas de Almeirim | K92: Escolas de Condução Matos (família Tomé; antigo site matosconducao.com, inativo) | N92: 243 599 986 | O92: 934 624 171 | Q92: ecalmeirinense@hotmail.com | AD92: Delegação do grupo Matos (partilha email com Almeirinense) | AH92: 0 | AL92: =IF(IF(O92<>"",O92,IF(LEFT(TRIM(N92),1)="9",N92,""))="","",HYPERLINK("https://wa.me/351"&LEFT(SUBSTITUTE(SUBSTITUTE(SUBSTITUTE(IF(O92<>"",O92,IF(LEFT(TRIM(N92),1)="9",N92,""))," ",""),"+351",""),"-",""),9),"Abrir WhatsApp")) -> Abrir WhatsApp | AM92: Site do grupo matosconducao.com já não resolve (arquivo web 2013-2016 lista: Almeirim J. Justino, Almeirinense, Alpiarça, Azambuja, Cartaxo, Fazendas de Almeirim, Santarém Ribatejana, Pedro de Santarém) — https://web.archive.org/web/2013/http://www.matosconducao.com/matos/4567579683; nenhum portal do aluno visível | AN92: Rua Guilherme Nunes Godinho 368, Loja 3, 2080-562 Fazendas de Almeirim | AO92: https://www.andardemoto.pt/escolas-de-conducao/dir/d/santarem/c/almeirim/
A93: 92 | B93: A | C93: 4.5 | D93: Novo | E93: Pedro | F93: telefone | G93: Coimbra | H93: Vila Nova de Poiares | I93: Vila Nova de Poiares | J93: Escola de Condução A Poiarense | N93: 239 421 371 | O93: 927 206 076 | U93: 2 | V93: 4 | AA93: 250 | AC93: 'O serviço de atenção ao cliente foi pésimo' (2021, https://escola-de-conducao.pt/a-poiarense-307000.html) | AD93: Volume médio-baixo (250 provas 2021), sem digital; queixas sobre atendimento | AH93: 0 | AL93: =IF(IF(O93<>"",O93,IF(LEFT(TRIM(N93),1)="9",N93,""))="","",HYPERLINK("https://wa.me/351"&LEFT(SUBSTITUTE(SUBSTITUTE(SUBSTITUTE(IF(O93<>"",O93,IF(LEFT(TRIM(N93),1)="9",N93,""))," ",""),"+351",""),"-",""),9),"Abrir WhatsApp")) -> Abrir WhatsApp | AM93: Sem website | AN93: Rua Comendador José Joaquim Ferreira, 3350-158 Vila Nova de Poiares | AO93: https://escola-de-conducao.pt/a-poiarense-307000.html; https://www.bomcondutor.pt/escolas/escola/a-poiarense; https://www.andardemoto.pt/escolas-de-conducao/dir/d/coimbra/c/vila-nova-de-poiares/p-2037/a-poiarense/; https://www.imt-ip.pt/wp-content/uploads/2025/01/EscolasdeConducao-2021.pdf
A94: 93 | B94: A | C94: 4.5 | D94: Novo | E94: Pedro | F94: telefone | G94: Coimbra | H94: Coimbra | I94: Coimbra | J94: Escola de Condução Briosa | N94: 239 401 452; 239 050 214 | O94: 913 002 798 | Q94: mail@ecbriosa.com | R94: ecbriosa.com (domínio já não pertence à escola — redireciona para site de casinos) | S94: https://www.facebook.com/pages/Escola-de-Condu%C3%A7%C3%A3o-Briosa/184330364926545 | U94: 4.6 | V94: 45 | X94: Presencial/telefone (sem plataforma online identificada) | Y94: Sim | Z94: Seg-Sex 09:00-13:00 / 14:00-20:00; Sábado 11:00-12:45 (aberto ao sábado) | AA94: 796 | AC94: 'Devia ter mecanismos que promovessem a regularidade na concretização das lições e evitassem os longos períodos sem conduzir fruto da desmarcação de aulas previamente agendadas' (https://escola-de-conducao.pt/escola-de-conducao-briosa-305923.html) | AD94: Grande volume (796 provas 2021), sem app/site ativo, queixa explícita sobre desmarcação de aulas e falta de regularidade | AH94: 0 | AL94: =IF(IF(O94<>"",O94,IF(LEFT(TRIM(N94),1)="9",N94,""))="","",HYPERLINK("https://wa.me/351"&LEFT(SUBSTITUTE(SUBSTITUTE(SUBSTITUTE(IF(O94<>"",O94,IF(LEFT(TRIM(N94),1)="9",N94,""))," ",""),"+351",""),"-",""),9),"Abrir WhatsApp")) -> Abrir WhatsApp | AM94: Website antigo (ecbriosa.com/.pt) perdido; sem portal de aluno identificado | AN94: Rua Carlos Seixas, 163, 3030-177 Coimbra | AO94: https://escola-de-conducao.pt/escola-de-conducao-briosa-305923.html; https://www.bomcondutor.pt/escolas/escola/briosa; https://www.andardemoto.pt/escolas-de-conducao/dir/d/coimbra/c/coimbra/p-2516/escola-de-conducao-briosa/; https://www.imt-ip.pt/wp-content/uploads/2025/01/EscolasdeConducao-2021.pdf; https://portalnacional.com.pt/coimbra/empresas/ensino/escolas-de-conducao/
A95: 94 | B95: A | C95: 4.4 | D95: Novo | E95: Pedro | F95: telefone | G95: Santarém | H95: Santarém | I95: Santarém | J95: Escola de Condução Roda Segura | N95: 243 094 849 | U95: 4.2 | V95: 21 | X95: Telefone/presencial | Y95: Sim | Z95: Seg-Sex 10:00-13:00 e 15:00-20:00; Sábado 10:00-13:00 (ABERTO SÁBADO) | AA95: 346 | AC95: 'marcam aulas e não aparecem nem avisam. A dona é arrogante e desorganizada, ao fim de oito meses foi preciso ir lá dar um murro na mesa para finalmente ela marcar o exame de código' — https://escola-de-conducao.pt/escola-de-conducao-roda-segura-306349.html | AD95: Queixa explícita de aulas marcadas e faltadas sem aviso (dor de comunicação/agenda) + volume médio; sem presença digital própria | AH95: 0 | AL95: =IF(IF(O95<>"",O95,IF(LEFT(TRIM(N95),1)="9",N95,""))="","",HYPERLINK("https://wa.me/351"&LEFT(SUBSTITUTE(SUBSTITUTE(SUBSTITUTE(IF(O95<>"",O95,IF(LEFT(TRIM(N95),1)="9",N95,""))," ",""),"+351",""),"-",""),9),"Abrir WhatsApp")) | AN95: Praceta Dr. Francisco da Luz Rebelo Gonçalves nº 7 (traseiras, loja), 2005-173 Santarém | AO95: https://escola-de-conducao.pt/escola-de-conducao-roda-segura-306349.html; https://escolasconducao.com/escola/roda-segura-lda; https://www.imt-ip.pt/wp-content/uploads/2025/01/EscolasdeConducao-2021.pdf
A96: 95 | B96: A | C96: 4.4 | D96: Novo | E96: Pedro | F96: grupo | G96: Aveiro | H96: Ílhavo | I96: Gafanha da Nazaré | J96: Escola de Condução D. Pedro - Prina | K96: Prina / O Farol (mesmo telefone 234 391 371) | N96: 234 391 371; 234 362 732 | S96: https://www.facebook.com/pages/Escola-de-Condu%C3%A7%C3%A3o-Dom-Pedro/110523245717372 | U96: 4.4 | V96: 9 | X96: Não divulgado online (sem plataforma de marcação visível) | Y96: Sim | Z96: Seg-Sex 10:00-20:00; Sábado 09:00-12:30 (aberto ao sábado de manhã) | AA96: 109 | AC96: "Que escola mais absurdamente mal gerida... gigante incompetência" (09/2022) https://escola-de-conducao.pt/escola-de-conducao-d-pedro-prina-306691.html | AD96: Aparenta operar 2 escolas na Gafanha (Prina + O Farol partilham telefone); queixa de má gestão | AH96: 0 | AL96: =IF(IF(O96<>"",O96,IF(LEFT(TRIM(N96),1)="9",N96,""))="","",HYPERLINK("https://wa.me/351"&LEFT(SUBSTITUTE(SUBSTITUTE(SUBSTITUTE(IF(O96<>"",O96,IF(LEFT(TRIM(N96),1)="9",N96,""))," ",""),"+351",""),"-",""),9),"Abrir WhatsApp")) | AN96: Av. José Estêvão, 361-A, 3830-555 Gafanha da Nazaré (Google: Av. José Estêvão 421, 3830-554) | AO96: https://www.bomcondutor.pt/escolas/escola/dom-pedro; https://escola-de-conducao.pt/escola-de-conducao-d-pedro-prina-306691.html (rating Google via snapshot escola-de-conducao.pt); https://passaprimeira.xyz/en/districts-regions/aveiro/municipalities/ilhavo/schools/ (licença 1008 'Prina')
A97: 96 | B97: A | C97: 4.4 | D97: Novo | E97: Pedro | F97: grupo | G97: Aveiro | H97: Mealhada | I97: Mealhada | J97: Escola de Condução da Mealhada | K97: Escola de Condução da Mealhada / Via S (mesma gerência) | N97: 231 027 199 | O97: 961 711 984 | U97: 4.9 | V97: 62 | X97: Telefone/presencial (sem plataforma visível) | Y97: Não | Z97: Seg 10:00–19:00 Ter 10:00–19:00 Qua 10:00–19:00 Qui 10:00–19:00 Sex 10:00–19:00 SÁB 09:00–13:00 Dom Encerrado — aberto sábado de manhã | AA97: 219 | AD97: Grupo de 2 escolas (Mealhada + Via S Anadia); ~220 exames/ano; sem app | AH97: 0 | AL97: =IF(IF(O97<>"",O97,IF(LEFT(TRIM(N97),1)="9",N97,""))="","",HYPERLINK("https://wa.me/351"&LEFT(SUBSTITUTE(SUBSTITUTE(SUBSTITUTE(IF(O97<>"",O97,IF(LEFT(TRIM(N97),1)="9",N97,""))," ",""),"+351",""),"-",""),9),"Abrir WhatsApp")) -> Abrir WhatsApp | AM97: Sem website próprio encontrado; empresa associada no Google: Cicapamp, Lda (mesma morada, tel. 231 940 117 = Via S) | AN97: Avenida 25 de Abril, Bloco A, R/C Esq., 3050-334 Mealhada | AO97: https://escola-de-conducao.pt/escola-de-conducao-da-mealhada-306666.html; https://escola-de-conducao.pt/cicapamp-lda-306791.html; https://www.bomcondutor.pt/escolas/escola/mealhada; https://www.bairradainformacao.pt/2022/05/30/escola-de-conducao-da-mealhada-e-via-s-em-anadia-organizam-passeio-motard/; https://passaprimeira.xyz/en/districts-regions/aveiro/municipalities/mealhada/schools/
A98: 97 | B98: A | C98: 4.4 | D98: Novo | E98: Pedro | F98: grupo | G98: Aveiro | H98: Oliveira do Bairro | I98: Bustos | J98: Escola de Condução de Bustos (Alta Cilindrada) | K98: Alta Cilindrada | N98: 234 758 423 | O98: 926 574 800 | Q98: ecbustos@altacilindrada.pt | R98: https://altacilindrada.pt/escola-de-conducao-bustos-2/ | S98: https://www.facebook.com/AltaCilindradaECBustos/ ; https://www.facebook.com/ECAltaCilindrada/ | T98: https://www.instagram.com/escola.conducao.bustos/ | U98: 4.9 | V98: 8 | W98: ProExamWeb (e-learning teórico) | X98: Pré-inscrição por formulário web; aulas por telefone/presencial | Y98: Não | Z98: Seg 10:00–19:30 Ter 10:00–19:30 Qua 10:00–19:30 Qui 10:00–19:30 Sex 10:00–19:30 SÁB 09:00–12:00 Dom Encerrado — aberto sábado de manhã | AA98: 223 | AD98: Grupo Alta Cilindrada (Bustos, Ílhavo, Azurva-Aveiro); presença social ativa por escola; usa e-learning mas sem app de marcação | AH98: 0 | AL98: =IF(IF(O98<>"",O98,IF(LEFT(TRIM(N98),1)="9",N98,""))="","",HYPERLINK("https://wa.me/351"&LEFT(SUBSTITUTE(SUBSTITUTE(SUBSTITUTE(IF(O98<>"",O98,IF(LEFT(TRIM(N98),1)="9",N98,""))," ",""),"+351",""),"-",""),9),"Abrir WhatsApp")) -> Abrir WhatsApp | AM98: altacilindrada.pt: menu "Estudo Online" -> https://www.proexamweb.com/ e "Sala Virtual"; pré-inscrição online; sem área do aluno/marcação | AN98: Rua Frei Gil, Ed. Agra nº3 – Loja B, 3770-017 Bustos | AO98: https://altacilindrada.pt/; https://altacilindrada.pt/category/escola/; https://escola-de-conducao.pt/escola-de-conducao-de-bustos-alta-cilindrada-305955.html; https://passaprimeira.xyz/en/districts-regions/aveiro/municipalities/oliveira-do-bairro/schools/
A99: 98 | B99: A | C99: 4.3 | D99: Novo | E99: Pedro | F99: telefone | G99: Lisboa | H99: Torres Vedras | I99: Torres Vedras | J99: Escola de Condução Estrela Torreense | N99: 261 322 847; 261 315 081 | Q99: estrelatorreense@sapo.pt | X99: Presencial/telefone (sem site nem plataforma encontrados) | AA99: 571 | AD99: Maior volume do concelho (571 provas 2021) sem site/app próprios | AH99: 0 | AL99: =IF(IF(O99<>"",O99,IF(LEFT(TRIM(N99),1)="9",N99,""))="","",HYPERLINK("https://wa.me/351"&LEFT(SUBSTITUTE(SUBSTITUTE(SUBSTITUTE(IF(O99<>"",O99,IF(LEFT(TRIM(N99),1)="9",N99,""))," ",""),"+351",""),"-",""),9),"Abrir WhatsApp")) | AN99: Avenida 5 de Outubro, nº 2 - 1º, 2560-270 Torres Vedras | AO99: https://www.bomcondutor.pt/escolas/escola/estrela-torreense; https://www.andardemoto.pt/escolas-de-conducao/dir/d/lisboa/c/torres-vedras/p-2677/escola-de-conducao-estrela-torreense/; https://passaprimeira.xyz/distritos-regioes/lisboa/concelhos/torres-vedras/escolas/; https://www.imt-ip.pt/wp-content/uploads/2025/01/EscolasdeConducao-2021.pdf
A100: 99 | B100: A | C100: 4.3 | D100: Novo | E100: Pedro | F100: grupo | G100: Aveiro | H100: Ílhavo | I100: Ílhavo | J100: Escola de Condução Ílhavo (Alta Cilindrada) | K100: Alta Cilindrada | N100: 234 422 468 | O100: 967 332 747 | Q100: ecilhavo@altacilindrada.pt | R100: https://altacilindrada.pt/escola-de-conducao-ilhavo/ | S100: https://www.facebook.com/AltaCilindradaECIlhavo | T100: https://www.instagram.com/escola.conducao.ilhavo/ | U100: 4.6 | V100: 18 | W100: ProExamWeb (e-learning de código) | X100: Pré-inscrição online no site; marcação de aulas não divulgada | Y100: Sim | Z100: Seg-Sex 10:00-19:30; Sábado 09:00-12:00 (aberto ao sábado de manhã) | AA100: 76 | AB100: A, A1, A2, B, C, CE | AC100: "Os exames de condução são realizados em Albergaria. Deixa muitas duvidas" (12/2022) https://escola-de-conducao.pt/escola-de-conducao-de-ilhavo-alta-cilindrada-306832.html | AD100: Grupo Alta Cilindrada (multi-escola); redes sociais ativas por escola | AH100: 0 | AL100: =IF(IF(O100<>"",O100,IF(LEFT(TRIM(N100),1)="9",N100,""))="","",HYPERLINK("https://wa.me/351"&LEFT(SUBSTITUTE(SUBSTITUTE(SUBSTITUTE(IF(O100<>"",O100,IF(LEFT(TRIM(N100),1)="9",N100,""))," ",""),"+351",""),"-",""),9),"Abrir WhatsApp")) -> Abrir WhatsApp | AM100: Link 'Estudo Online' https://www.proexamweb.com/ + 'Sala Virtual' em altacilindrada.pt | AN100: Rua Coronel Cândido Teles, n.º 7, 3830-126 Ílhavo | AO100: https://altacilindrada.pt/escola-de-conducao-ilhavo/; https://escola-de-conducao.pt/escola-de-conducao-de-ilhavo-alta-cilindrada-306832.html (rating Google via snapshot escola-de-conducao.pt); https://passaprimeira.xyz/en/districts-regions/aveiro/municipalities/ilhavo/schools/ (licença 1362)
...

Sheet Como usar
A1: Convlyx · CRM de escolas da região Centro
A3: Separadores
A4: Leads: uma linha por escola/delegação. As colunas a amarelo são as de trabalho (Estado, Responsável, Ângulo, Contacto, próxima ação, notas). As restantes vêm da pesquisa de 8 de outubro de 2026.
A5: Modelos: os textos dos emails da sequência (C1 a C4) e da mensagem de WhatsApp (D1). Pode editá-los: o script usa sempre a versão desta folha.
A6: Config: emails, terra e assinatura de cada um, limite diário de envios e ID do folheto no Google Drive.
A7: Painel: contagens automáticas por estado, distrito e prioridade.
A9: Estados
A10: Novo → Em sequência (email automático) → Respondeu → Visita marcada → Demo feita → Em teste → Cliente. Saídas: Perdido (diz não ou pede para não ser contactada) · Arrefecer (sem resposta; volta daqui a 90 dias).
A12: Prioridade
A13: A = grupo com várias escolas/delegações, OU queixas públicas com avaliação Google abaixo de 4,3, OU 300 ou mais exames em 2021 (escola grande) · B = restantes · C = parece inativa ou já tem app própria. Dentro do A, comecem pelos grupos e pela distância a Leiria. A coluna "Motivo prioridade" tem a justificação da pesquisa.
A15: Pontuação
A16: Ordena as escolas dentro de cada prioridade: grupo +3; queixas públicas +1,5 (ou +0,5 se a avaliação for boa); Google abaixo de 3,8 +1; dimensão até +3 (exames de 2021 ÷ 250); proximidade de Leiria até +2. A folha já vem ordenada por Prioridade e Pontuação: as primeiras linhas são as primeiras escolas a contactar.
... A23: Se uma escola pedir para não ser contactada: Estado = Perdido e "não contactar" nas Notas.

Sheet Modelos
A1: Chave | B1: Assunto | C1: Corpo
A2: C1-telefone | B2: Alunos da {escola} a ligar para saber horários | C2: Bom dia {nome}, Sou o {remetente} e desenvolvo, com um colega, uma app para escolas de condução aqui da zona Centro. Na maioria das escolas que conhecemos, as aulas práticas marcam-se por telefone e WhatsApp. O problema aparece quando há um cancelamento: alguém tem de avisar os alunos um a um. O Convlyx dá a cada aluno e instrutor uma app no telemóvel com as suas aulas. Quando uma aula muda, todos os inscritos recebem o aviso no momento. Funciona ao lado do programa que já usam para o IMT, sem trocar nada. Estamos a abrir o programa a 10 escolas fundadoras, com 3 meses grátis e montagem feita por nós. Posso enviar-lhe um vídeo de 3 minutos a mostrar como funciona? Cumprimentos, {remetente} {assinatura}
A3: C1-grupo | B3: {grupo}: uma app para os alunos de todas as escolas | C3: Bom dia {nome}, Sou o {remetente}, do Convlyx. Vi que o {grupo} tem várias escolas na região. Imagino que coordenar instrutores, aulas e avisos entre elas dá bastante trabalho. Fizemos o Convlyx para isso. Cada escola tem o seu espaço, com os dados separados, e os alunos e instrutores de todas usam a mesma app no telemóvel: aulas, cancelamentos com aviso automático, e presenças nas teóricas por QR. Não substitui o vosso software do IMT; funciona ao lado dele. Para grupos, as primeiras escolas entram como fundadoras: 3 meses grátis, e depois um preço fixo por escola. Posso enviar-lhe um vídeo de 3 minutos? Se fizer sentido, montamos já o espaço de uma das vossas escolas para verem a funcionar. Cumprimentos, {remetente} {assinatura}
A4: C1-teoricas | B4: Folha de presenças das teóricas | C4: Bom dia {nome}, Pergunta rápida: na {escola}, as presenças das teóricas ainda se fazem numa folha que passa de mão em mão? Desenvolvemos uma forma mais simples: o instrutor projeta um QR, cada aluno confirma a presença com o telemóvel em segundos, e no fim sai a folha em PDF. O código muda a cada poucos segundos, por isso uma fotografia enviada a um amigo não serve. Faz parte do Convlyx, uma app para alunos e instrutores que funciona ao lado do programa do IMT que já usam. Estamos a convidar 10 escolas da zona Centro a experimentarem 3 meses sem pagar. Posso enviar-lhe um vídeo de 3 minutos a mostrar como funciona? Cumprimentos, {remetente} {assinatura}
A5: C2 | B5: (segue no mesmo fio) | C5: {nome}, só para garantir que isto não ficou perdido na caixa de entrada. Se for mais fácil, monto já um espaço com o nome da {escola}, para experimentarem com 2 ou 3 alunos, sem compromisso nenhum. Quer? {remetente}
A6: C3 | B6: O que acontece quando um instrutor fica doente | C6: Bom dia {nome}, Numa escola com 4 instrutores, um instrutor doente significa 4 a 6 alunos a avisar antes das 9h, normalmente por telefone e um de cada vez. No Convlyx, o instrutor carrega em "Não posso dar esta aula" e todos os inscritos recebem o aviso no telemóvel ao mesmo tempo. A secretaria só tem de remarcar. Deixo-lhe em anexo uma folha com o que a app faz e quanto custa. Ainda temos vagas de Escola Fundadora (3 meses grátis) até ao fim do ano. Cumprimentos, {remetente} {assinatura}
A7: C4 | B7: (segue no mesmo fio) | C7: {nome}, não quero encher-lhe a caixa de correio, por isso este é o meu último email. Se um dia a app para alunos fizer sentido para a {escola}, basta responder a esta mensagem e trato de tudo. E se puder dizer-me numa linha porque não é para já ("já temos solução", "não é prioridade", "preço"…), agradeço muito. Bom trabalho, {remetente}
A8: D1 | B8: (WhatsApp: copiar e colar depois de clicar em Abrir WhatsApp) | C8: Bom dia! O meu nome é {remetente} e sou de {terra}. Desenvolvemos uma app para alunos e instrutores de escolas de condução: aulas no telemóvel e aviso automático quando uma aula é cancelada. Funciona ao lado do programa que a escola já usa. Estamos a convidar 10 escolas da zona a experimentar 3 meses grátis. Posso enviar-lhe uma folha com a informação?
A10: Variáveis: {nome} (1.º nome do Contacto; se estiver vazio, a saudação fica "Bom dia,"), {escola}, {grupo}, {concelho}, {remetente}, {terra}, {assinatura}. O C1 usado depende da coluna Ângulo (telefone / grupo / teoricas). C2 e C4 seguem como "Re:" do C1. A C3 leva o folheto em anexo (Config → FOLHETO_DRIVE_ID).

Sheet Config
A1: Chave | B1: Valor | C1: Descrição
A2: EMAIL_Pedro | C2: Email Gmail com que o Pedro corre o script (tem de coincidir com o nome na coluna Responsável)
A3: EMAIL_Francisco | C3: Email Gmail com que o Francisco corre o script
A4: TERRA_Pedro | B4: Leiria | C4: Usado em "sou de {terra}"
A5: TERRA_Francisco | C5: Usado em "sou de {terra}"
A6: ASSINATURA_Pedro | B6: Convlyx · convlyx.com | C6: Linha por baixo do nome (sugestão: acrescentar o telemóvel)
A7: ASSINATURA_Francisco | B7: Convlyx · convlyx.com | C7: Linha por baixo do nome
A8: MAX_POR_DIA | B8: 25 | C8: Máximo de emails da sequência por dia e por pessoa
A9: DIAS_ENVIO | B9: 2,3,4 | C9: Dias da semana em que se enviam emails (1=seg … 5=sex). Por omissão, de terça a quinta.
A10: FOLHETO_DRIVE_ID | C10: ID no Google Drive do 03-folheto-escolas-fundadoras.pdf (a parte do link entre /d/ e /view)
A11: RODAPE | B11: Se preferir não receber mais emails meus sobre isto, basta responder com um "não" e não volto a escrever. | C11: Acrescentado a todos os emails (forma de oposição)

Sheet Painel
A1: Painel (atualiza sozinho)
A3: Estado | B3: N.º escolas
A4: Novo | B4: =COUNTIF(Leads!$D:$D,A4) -> 409
A5: Em sequência | B5: =COUNTIF(Leads!$D:$D,A5) -> 0
A6: Respondeu | B6: =COUNTIF(Leads!$D:$D,A6) -> 0
A7: Visita marcada | B7: =COUNTIF(Leads!$D:$D,A7) -> 0
A8: Demo feita | B8: =COUNTIF(Leads!$D:$D,A8) -> 0
A9: Em teste | B9: =COUNTIF(Leads!$D:$D,A9) -> 0
A10: Cliente | B10: =COUNTIF(Leads!$D:$D,A10) -> 0
A11: Perdido | B11: =COUNTIF(Leads!$D:$D,A11) -> 0
A12: Arrefecer | B12: =COUNTIF(Leads!$D:$D,A12) -> 0
A13: Total | B13: =SUM(B4:B12) -> 409
A15: Funil
A16: Contactadas (saíram de Novo) | B16: =B13-B4 -> 0
A17: Responderam ou mais à frente | B17: =SUM(B6:B10) -> 0
A18: Em teste + clientes | B18: =B9+B10 -> 0
A19: Clientes | B19: =B10 -> 0
A20: Taxa de resposta | B20: =IFERROR(B17/B16,0) -> 0
A21: Conversa → teste | B21: =IFERROR(B18/B17,0) -> 0
A24: Distrito | B24: A | C24: B | D24: C | E24: Total | F24: Clientes
A25: Leiria | B25: =COUNTIFS(Leads!$G:$G,$A25,Leads!$B:$B,"A") -> 39 | C25: =COUNTIFS(Leads!$G:$G,$A25,Leads!$B:$B,"B") -> 28 | D25: =COUNTIFS(Leads!$G:$G,$A25,Leads!$B:$B,"C") -> 12 | E25: =SUM(B25:D25) -> 79 | F25: =COUNTIFS(Leads!$G:$G,$A25,Leads!$D:$D,"Cliente") -> 0
A26: Santarém | B26: =COUNTIFS(Leads!$G:$G,$A26,Leads!$B:$B,"A") -> 36 | C26: =COUNTIFS(Leads!$G:$G,$A26,Leads!$B:$B,"B") -> 27 | D26: =COUNTIFS(Leads!$G:$G,$A26,Leads!$B:$B,"C") -> 9 | E26: =SUM(B26:D26) -> 72 | F26: =COUNTIFS(Leads!$G:$G,$A26,Leads!$D:$D,"Cliente") -> 0
A27: Lisboa | B27: =COUNTIFS(Leads!$G:$G,$A27,Leads!$B:$B,"A") -> 20 | C27: =COUNTIFS(Leads!$G:$G,$A27,Leads!$B:$B,"B") -> 4 | D27: =COUNTIFS(Leads!$G:$G,$A27,Leads!$B:$B,"C") -> 4 | E27: =SUM(B27:D27) -> 28 | F27: =COUNTIFS(Leads!$G:$G,$A27,Leads!$D:$D,"Cliente") -> 0
A28: Coimbra | B28: =COUNTIFS(Leads!$G:$G,$A28,Leads!$B:$B,"A") -> 39 | C28: =COUNTIFS(Leads!$G:$G,$A28,Leads!$B:$B,"B") -> 16 | D28: =COUNTIFS(Leads!$G:$G,$A28,Leads!$B:$B,"C") -> 2 | E28: =SUM(B28:D28) -> 57 | F28: =COUNTIFS(Leads!$G:$G,$A28,Leads!$D:$D,"Cliente") -> 0
A29: Aveiro | B29: =COUNTIFS(Leads!$G:$G,$A29,Leads!$B:$B,"A") -> 30 | C29: =COUNTIFS(Leads!$G:$G,$A29,Leads!$B:$B,"B") -> 14 | D29: =COUNTIFS(Leads!$G:$G,$A29,Leads!$B:$B,"C") -> 4 | E29: =SUM(B29:D29) -> 48 | F29: =COUNTIFS(Leads!$G:$G,$A29,Leads!$D:$D,"Cliente") -> 0
A30: Viseu | B30: =COUNTIFS(Leads!$G:$G,$A30,Leads!$B:$B,"A") -> 36 | C30: =COUNTIFS(Leads!$G:$G,$A30,Leads!$B:$B,"B") -> 23 | D30: =COUNTIFS(Leads!$G:$G,$A30,Leads!$B:$B,"C") -> 10 | E30: =SUM(B30:D30) -> 69 | F30: =COUNTIFS(Leads!$G:$G,$A30,Leads!$D:$D,"Cliente") -> 0
A31: Castelo Branco | B31: =COUNTIFS(Leads!$G:$G,$A31,Leads!$B:$B,"A") -> 11 | C31: =COUNTIFS(Leads!$G:$G,$A31,Leads!$B:$B,"B") -> 16 | D31: =COUNTIFS(Leads!$G:$G,$A31,Leads!$B:$B,"C") -> 4 | E31: =SUM(B31:D31) -> 31 | F31: =COUNTIFS(Leads!$G:$G,$A31,Leads!$D:$D,"Cliente") -> 0
A32: Guarda | B32: =COUNTIFS(Leads!$G:$G,$A32,Leads!$B:$B,"A") -> 12 | C32: =COUNTIFS(Leads!$G:$G,$A32,Leads!$B:$B,"B") -> 10 | D32: =COUNTIFS(Leads!$G:$G,$A32,Leads!$B:$B,"C") -> 3 | E32: =SUM(B32:D32) -> 25 | F32: =COUNTIFS(Leads!$G:$G,$A32,Leads!$D:$D,"Cliente") -> 0
